Workbook

Sheet Introduction
A1: Configuration Baseline based on NIST SP 800-53 Rev. 5 (Release 5.2.0) with NIST CSF 2.0 Mapping
A2: Prefix ESBIT- is applied to every original NIST control identifier to form the new Control ID (for example AC-01 becomes ESBIT-AC-01). Sheets: Introduction, Config Baseline (main register), Summary, Domain Summary, Baseline Summary (control families and IDs per topic), and one baseline sheet per topic: Cloud, Network, Identity, Monitoring, Database, Application, Backup, Governance, Physical and Third Party, plus Cloud Coverage Check.
A4: 1. Purpose of the Configuration Baseline
A5: This configuration baseline is established so that every cloud, network, database and infrastructure component is configured in accordance with a documented security baseline, giving the organization a consistent, repeatable and auditable way to harden its systems.
A6: It translates the NIST SP 800-53 Rev. 5 control catalog (20 families, base controls and control enhancements) into concrete configuration expectations, identifies which IT domain each control affects, and rates how strongly each control depends on technical configuration, so that administrators can prioritize what must be present in device and system configurations.
A7: The baseline supports: (1) a common security standard for all environments; (2) detection of configuration drift and unauthorized change; (3) evidence for internal audit and compliance reviews; and (4) alignment of technical settings with NIST CSF 2.0 outcomes.
A8: How to use the Config Baseline sheet: filter column K (IT domain) to select the technology in scope, filter column L to start with Level 1 items, read column I (English) or J (Thai) for the key configuration activity, then map each item to the vendor-specific setting (for example CIS Benchmark or STIG) for your platform.
A9: Important notes: the CSF 2.0 mapping and the Level rating are analyst-derived guidance for building the baseline and should be validated against the official NIST SP 800-53 to CSF 2.0 crosswalk and the organization's risk assessment. Withdrawn controls are excluded. Enhancement levels are derived from the base control (one level lower unless the enhancement concerns encryption, authentication, privilege, integrity, audit or deny-by-default).
A10: IT Domain (column K) uses ten domains: Network, Cloud, Identity, Monitoring, Database, Application, Backup, Governance, Physical and Third Party. A control can belong to more than one domain. The Cloud and Network domains are the scope of the cloud and network configuration baselines; see the Domain Summary sheet for counts and coverage by family.
A12: 2. The 20 NIST SP 800-53 Control Families and Their Relevance to the Configuration Baseline
A13: Control Family | B13: What it covers | C13: Relevance to the configuration baseline | D13: Typical configuration focus | E13: Rows in register | F13: of which Level 1
A14: AC - Access Control | B14: Who and what may access systems, data and networks, and how sessions and information flows are controlled. | C14: High - directly defines account, privilege, session, remote access and network flow settings. | D14: Account lockout, session timeout, least-privilege roles, VPN/remote access, firewall rules, login banner, wireless security. | E14: =COUNTIF('Config Baseline'!$C:$C,"Access Control (AC)") -> 127 | F14: =COUNTIFS('Config Baseline'!$C:$C,"Access Control (AC)",'Config Baseline'!$L:$L,"Level 1*") -> 22
A15: AT - Awareness and Training | B15: Security awareness and role-based training. | C15: Low - people/process control that supports correct configuration by trained administrators. | D15: Administrator and developer training on secure configuration. | E15: =COUNTIF('Config Baseline'!$C:$C,"Awareness and Training (AT)") -> 16 | F15: =COUNTIFS('Config Baseline'!$C:$C,"Awareness and Training (AT)",'Config Baseline'!$L:$L,"Level 1*") -> 0
A16: AU - Audit and Accountability | B16: Event logging, log content, protection, retention, time stamps and review. | C16: High - logging must be enabled and configured on every component. | D16: Enable logging, log format, NTP, central syslog/SIEM forwarding, retention, log integrity. | E16: =COUNTIF('Config Baseline'!$C:$C,"Audit and Accountability (AU)") -> 57 | F16: =COUNTIFS('Config Baseline'!$C:$C,"Audit and Accountability (AU)",'Config Baseline'!$L:$L,"Level 1*") -> 12
A17: CA - Assessment, Authorization, and Monitoring | B17: Control assessment, system interconnection, POA&M, continuous monitoring and penetration testing. | C17: Medium - drives compliance checking and monitoring of configuration. | D17: Configuration compliance scans, interconnection rules, drift monitoring. | E17: =COUNTIF('Config Baseline'!$C:$C,"Assessment, Authorization, and Monitoring (CA)") -> 25 | F17: =COUNTIFS('Config Baseline'!$C:$C,"Assessment, Authorization, and Monitoring (CA)",'Config Baseline'!$L:$L,"Level 1*") -> 0
A18: CM - Configuration Management | B18: Baseline configuration, change control, least functionality, software restrictions and inventory. | C18: Very high - the core of the configuration baseline. | D18: Hardened baselines (CIS/STIG), change control, disable unused services, allowlisting, asset inventory. | E18: =COUNTIF('Config Baseline'!$C:$C,"Configuration Management (CM)") -> 57 | F18: =COUNTIFS('Config Baseline'!$C:$C,"Configuration Management (CM)",'Config Baseline'!$L:$L,"Level 1*") -> 8
A19: CP - Contingency Planning | B19: Contingency planning, backup, alternate sites, telecommunications and recovery. | C19: Medium to high - backup, replication and failover settings. | D19: Backup jobs and encryption, replication, DR failover, redundant links. | E19: =COUNTIF('Config Baseline'!$C:$C,"Contingency Planning (CP)") -> 49 | F19: =COUNTIFS('Config Baseline'!$C:$C,"Contingency Planning (CP)",'Config Baseline'!$L:$L,"Level 1*") -> 3
A20: IA - Identification and Authentication | B20: Authentication of users, devices and services and management of authenticators. | C20: High - authentication settings on every platform. | D20: MFA, password policy, 802.1X/NAC, certificates, service identities, SSO. | E20: =COUNTIF('Config Baseline'!$C:$C,"Identification and Authentication (IA)") -> 61 | F20: =COUNTIFS('Config Baseline'!$C:$C,"Identification and Authentication (IA)",'Config Baseline'!$L:$L,"Level 1*") -> 7
A21: IR - Incident Response | B21: Incident handling capability, training, testing and reporting. | C21: Low to medium - mostly process, with tooling configuration for handling. | D21: SIEM/SOAR playbooks, containment actions, ticketing. | E21: =COUNTIF('Config Baseline'!$C:$C,"Incident Response (IR)") -> 39 | F21: =COUNTIFS('Config Baseline'!$C:$C,"Incident Response (IR)",'Config Baseline'!$L:$L,"Level 1*") -> 0
A22: MA - Maintenance | B22: Controlled and remote maintenance, maintenance tools and personnel. | C22: Low to medium - remote maintenance session settings. | D22: Vendor remote access with MFA, encryption, logging and session termination. | E22: =COUNTIF('Config Baseline'!$C:$C,"Maintenance (MA)") -> 28 | F22: =COUNTIFS('Config Baseline'!$C:$C,"Maintenance (MA)",'Config Baseline'!$L:$L,"Level 1*") -> 3
A23: MP - Media Protection | B23: Access, marking, storage, transport and sanitization of media. | C23: Low to medium - removable media and encryption settings. | D23: USB/removable media control, disk encryption, secure wipe. | E23: =COUNTIF('Config Baseline'!$C:$C,"Media Protection (MP)") -> 20 | F23: =COUNTIFS('Config Baseline'!$C:$C,"Media Protection (MP)",'Config Baseline'!$L:$L,"Level 1*") -> 0
A24: PE - Physical and Environmental Protection | B24: Physical access, monitoring, power, fire and environmental protection. | C24: Low - facility controls rather than IT configuration. | D24: Badge/CCTV systems, UPS, fire suppression, HVAC monitoring. | E24: =COUNTIF('Config Baseline'!$C:$C,"Physical and Environmental Protection (PE)") -> 50 | F24: =COUNTIFS('Config Baseline'!$C:$C,"Physical and Environmental Protection (PE)",'Config Baseline'!$L:$L,"Level 1*") -> 0
A25: PL - Planning | B25: Security planning, rules of behavior, security architecture and baseline selection. | C25: Medium - architecture and baseline tailoring drive the design. | D25: Zoning, defense in depth, segmentation, central management. | E25: =COUNTIF('Config Baseline'!$C:$C,"Planning (PL)") -> 11 | F25: =COUNTIFS('Config Baseline'!$C:$C,"Planning (PL)",'Config Baseline'!$L:$L,"Level 1*") -> 0
A26: PM - Program Management | B26: Enterprise security and privacy program management. | C26: Low - governance with no direct device configuration. | D26: Program plans, roles, metrics and risk strategy. | E26: =COUNTIF('Config Baseline'!$C:$C,"Program Management (PM)") -> 37 | F26: =COUNTIFS('Config Baseline'!$C:$C,"Program Management (PM)",'Config Baseline'!$L:$L,"Level 1*") -> 0
A27: PS - Personnel Security | B27: Personnel screening, termination, transfer and access agreements. | C27: Low - process, with account de-provisioning settings. | D27: Account disablement and access review on termination or transfer. | E27: =COUNTIF('Config Baseline'!$C:$C,"Personnel Security (PS)") -> 17 | F27: =COUNTIFS('Config Baseline'!$C:$C,"Personnel Security (PS)",'Config Baseline'!$L:$L,"Level 1*") -> 0
A28: PT - PII Processing and Transparency | B28: Authority, purposes, consent and notice for processing personally identifiable information. | C28: Low - privacy governance with limited technical settings. | D28: Data tagging and consent mechanisms. | E28: =COUNTIF('Config Baseline'!$C:$C,"PII Processing and Transparency (PT)") -> 21 | F28: =COUNTIFS('Config Baseline'!$C:$C,"PII Processing and Transparency (PT)",'Config Baseline'!$L:$L,"Level 1*") -> 0
A29: RA - Risk Assessment | B29: Risk assessment, vulnerability scanning and threat hunting. | C29: Medium - scanner and telemetry configuration. | D29: Authenticated vulnerability scanning, scan frequency, hunting telemetry. | E29: =COUNTIF('Config Baseline'!$C:$C,"Risk Assessment (RA)") -> 22 | F29: =COUNTIFS('Config Baseline'!$C:$C,"Risk Assessment (RA)",'Config Baseline'!$L:$L,"Level 1*") -> 3
A30: SA - System and Services Acquisition | B30: Acquisition, system development life cycle, external services and unsupported components. | C30: Medium - secure pipeline, cloud service settings and end-of-life replacement. | D30: CI/CD security testing, cloud service configuration, replacing unsupported OS/firmware. | E30: =COUNTIF('Config Baseline'!$C:$C,"System and Services Acquisition (SA)") -> 109 | F30: =COUNTIFS('Config Baseline'!$C:$C,"System and Services Acquisition (SA)",'Config Baseline'!$L:$L,"Level 1*") -> 0
A31: SC - System and Communications Protection | B31: Boundary protection, cryptography, denial-of-service protection, session authenticity and time synchronization. | C31: Very high - network and cryptographic settings are central. | D31: Firewall/DMZ, segmentation, TLS, DNSSEC, encryption at rest, DDoS, NTP. | E31: =COUNTIF('Config Baseline'!$C:$C,"System and Communications Protection (SC)") -> 138 | F31: =COUNTIFS('Config Baseline'!$C:$C,"System and Communications Protection (SC)",'Config Baseline'!$L:$L,"Level 1*") -> 17
A32: SI - System and Information Integrity | B32: Flaw remediation, malware protection, monitoring, integrity verification and input validation. | C32: Very high - patching, endpoint protection and monitoring settings. | D32: Patching, EDR/anti-malware, IDS/IPS, file integrity monitoring, secure boot, ASLR/DEP. | E32: =COUNTIF('Config Baseline'!$C:$C,"System and Information Integrity (SI)") -> 105 | F32: =COUNTIFS('Config Baseline'!$C:$C,"System and Information Integrity (SI)",'Config Baseline'!$L:$L,"Level 1*") -> 18
A33: SR - Supply Chain Risk Management | B33: Supply chain risk management, provenance and component authenticity. | C33: Low - procurement process with limited technical settings. | D33: Component authenticity checks, secure disposal. | E33: =COUNTIF('Config Baseline'!$C:$C,"Supply Chain Risk Management (SR)") -> 27 | F33: =COUNTIFS('Config Baseline'!$C:$C,"Supply Chain Risk Management (SR)",'Config Baseline'!$L:$L,"Level 1*") -> 0
A35: 3. NIST CSF 2.0 - The Six Functions (Pillars) and Their Relevance to the Configuration Baseline
A36: CSF 2.0 Function | B36: Purpose | C36: Relevance to the configuration baseline | D36: Example configuration items
A37: Govern (GV) | B37: Establishes and monitors the organization's cybersecurity risk management strategy, expectations, policy, roles and supply chain oversight. | C37: Sets the policies and standards from which baseline settings are derived; ensures ownership, exceptions handling and supplier requirements. | D37: Configuration standards and policy, roles for change approval, supplier security requirements.
A38: Identify (ID) | B38: Understands current cybersecurity risks to assets, data and capabilities. | C38: Asset inventory, vulnerability identification and change/exception risk assessment determine what must be baselined. | D38: CMDB/asset inventory, vulnerability scanning, change risk review.
A39: Protect (PR) | B39: Uses safeguards to prevent or reduce cybersecurity risk. | C39: Largest share of baseline settings: identity and access, data protection, platform hardening and infrastructure resilience. | D39: MFA, least privilege, encryption, hardened OS/network/DB settings, segmentation, backup.
A40: Detect (DE) | B40: Finds and analyzes possible cybersecurity attacks and compromises. | C40: Ensures logging, monitoring and alerting are configured so deviations and attacks are visible. | D40: Logging, SIEM rules, IDS/IPS, EDR, integrity monitoring.
A41: Respond (RS) | B41: Takes action regarding a detected cybersecurity incident. | C41: Configuration must allow rapid containment, evidence preservation and reporting. | D41: Isolation actions, forensic logging, incident ticketing and notification settings.
A42: Recover (RC) | B42: Restores assets and operations affected by a cybersecurity incident. | C42: Backups, restore procedures and known-good configurations support fast, trusted recovery. | D42: Backup and restore settings, golden images, DR failover configuration.
A44: 4. Configuration Baseline Levels (3 Levels)
A45: Every control row in the Config Baseline sheet is assigned one of three levels in column L. Level 1 is the strongest and must be present in the configuration; Level 3 has the least impact on the configuration baseline.
A46: Level | B46: Priority | C46: Definition | D46: Impact if not implemented | E46: Expectation | F46: Examples
A47: Level 1 | B47: Highest - Mandatory | C47: Controls that are enforced directly through technical settings and are essential to security. | D47: High risk of compromise, data exposure or loss of accountability if missing or misconfigured. | E47: Must be defined in the baseline and present in every applicable configuration; deviations require formal approved exceptions. | F47: Account lockout, MFA, TLS, deny-by-default firewall rules, logging, NTP, patching, disk encryption.
A48: Level 2 | B48: Medium - Recommended | C48: Controls that materially improve security and are configurable, but depend on technology or context. | D48: Moderate exposure or reduced ability to detect and respond. | E48: Should be applied where technically supported; document reasons where not applied. | F48: Login banner, DNSSEC, resource quotas, DR site settings, mobile device policy.
A49: Level 3 | B49: Lowest - Optional/Low impact | C49: Governance, process or physical controls, and specialized enhancements with limited or indirect effect on configuration. | D49: Low direct impact on system configuration. | E49: Apply by risk, project or environment; track as governance evidence rather than device settings. | F49: Policies, training, risk assessment, physical protections, supply chain governance.

Sheet Config Baseline
A1: Control ID New | B1: Control ID | C1: Control Family | D1: Control Name | E1: CSF 2.0 Function | F1: CSF 2.0 Category | G1: CSF 2.0 Subcategory ID | H1: CSF 2.0 Subcategory Description | I1: Key Activity | J1: Key Activity (Thai) | K1: IT Domain | L1: Config Baseline Relevance (Level)
A2: ESBIT-AC-01 | B2: AC-01 | C2: Access Control (AC) | D2: Policy and Procedures | E2: Govern (GV) | F2: GV.PO - Policy | G2: GV.PO-01 | H2: Policy for managing cybersecurity risks is established based on organizational context, cybersecurity strategy, and priorities and is communicated and enforced | I2: Not a direct configuration item - define, document, review and communicate the Access Control policy and procedures that drive the technical configuration standards. | J2: ไม่ใช่การ config โดยตรง - กำหนด จัดทำเอกสาร และทบทวนนโยบาย/ขั้นตอนของหมวดการควบคุมการเข้าถึง เพื่อเป็นฐานในการกำหนดมาตรฐาน Config | K2: Governance | L2: Level 3 - Low: governance/process control with no direct technical setting
A3: ESBIT-AC-02 | B3: AC-02 | C3: Access Control (AC) | D3: Account Management | E3: Protect (PR) | F3: PR.AA - Identity Management, Authentication, and Access Control | G3: PR.AA-01 | H3: Identities and credentials for authorized users, services, and hardware are managed by the organization | I3: Configure account types, naming, approval workflow and lifecycle in AD/LDAP, OS, database, network devices and cloud IAM; disable or remove inactive, temporary and shared accounts | J3: กำหนดประเภทบัญชี การอนุมัติ และวงจรชีวิตบัญชีบน AD/OS/DB/อุปกรณ์เครือข่าย/Cloud IAM พร้อมปิดหรือลบบัญชีที่ไม่ใช้งาน ชั่วคราว และบัญชีใช้ร่วม | K3: Network, Cloud, Identity, Database | L3: Level 1 - High: mandatory setting that must exist in the configuration baseline
A4: ESBIT-AC-02(01) | B4: AC-02(01) | C4: Access Control (AC) | D4: Account Management | Automated System Account Management | E4: Protect (PR) | F4: PR.AA - Identity Management, Authentication, and Access Control | G4: PR.AA-01 | H4: Identities and credentials for authorized users, services, and hardware are managed by the organization | I4: Enhances AC-02 (Account Management): configure and enforce 'Automated System Account Management' in addition to the base setting, keep it consistent across applicable systems and document approved exceptions. Base scope: Configure account types, naming, approval workflow and lifecycle in AD/LDAP, OS, database, network devices and cloud IAM; disable or remove inactive, temporary and shared accounts | J4: ส่วนขยายของ AC-02: กำหนดค่าและบังคับใช้ 'Automated System Account Management' เพิ่มเติมจากค่าพื้นฐาน ให้สอดคล้องทุกระบบที่เกี่ยวข้อง และบันทึกข้อยกเว้น - กำหนดประเภทบัญชี การอนุมัติ และวงจรชีวิตบัญชีบน AD/OS/DB/อุปกรณ์เครือข่าย/Cloud IAM พร้อมปิดหรือลบบัญชีที่ไม่ใช้งาน ชั่วคราว และบัญชีใช้ร่วม | K4: Network, Cloud, Identity, Database | L4: Level 2 - Medium: recommended setting; apply wherever technically applicable
A5: ESBIT-AC-02(02) | B5: AC-02(02) | C5: Access Control (AC) | D5: Account Management | Automated Temporary and Emergency Account Management | E5: Protect (PR) | F5: PR.AA - Identity Management, Authentication, and Access Control | G5: PR.AA-01 | H5: Identities and credentials for authorized users, services, and hardware are managed by the organization | I5: Enhances AC-02 (Account Management): configure and enforce 'Automated Temporary and Emergency Account Management' in addition to the base setting, keep it consistent across applicable systems and document approved exceptions. Base scope: Configure account types, naming, approval workflow and lifecycle in AD/LDAP, OS, database, network devices and cloud IAM; disable or remove inactive, temporary and shared accounts | J5: ส่วนขยายของ AC-02: กำหนดค่าและบังคับใช้ 'Automated Temporary and Emergency Account Management' เพิ่มเติมจากค่าพื้นฐาน ให้สอดคล้องทุกระบบที่เกี่ยวข้อง และบันทึกข้อยกเว้น - กำหนดประเภทบัญชี การอนุมัติ และวงจรชีวิตบัญชีบน AD/OS/DB/อุปกรณ์เครือข่าย/Cloud IAM พร้อมปิดหรือลบบัญชีที่ไม่ใช้งาน ชั่วคราว และบัญชีใช้ร่วม | K5: Network, Cloud, Identity, Database | L5: Level 2 - Medium: recommended setting; apply wherever technically applicable
A6: ESBIT-AC-02(03) | B6: AC-02(03) | C6: Access Control (AC) | D6: Account Management | Disable Accounts | E6: Protect (PR) | F6: PR.AA - Identity Management, Authentication, and Access Control | G6: PR.AA-01 | H6: Identities and credentials for authorized users, services, and hardware are managed by the organization | I6: Enhances AC-02 (Account Management): configure and enforce 'Disable Accounts' in addition to the base setting, keep it consistent across applicable systems and document approved exceptions. Base scope: Configure account types, naming, approval workflow and lifecycle in AD/LDAP, OS, database, network devices and cloud IAM; disable or remove inactive, temporary and shared accounts | J6: ส่วนขยายของ AC-02: กำหนดค่าและบังคับใช้ 'Disable Accounts' เพิ่มเติมจากค่าพื้นฐาน ให้สอดคล้องทุกระบบที่เกี่ยวข้อง และบันทึกข้อยกเว้น - กำหนดประเภทบัญชี การอนุมัติ และวงจรชีวิตบัญชีบน AD/OS/DB/อุปกรณ์เครือข่าย/Cloud IAM พร้อมปิดหรือลบบัญชีที่ไม่ใช้งาน ชั่วคราว และบัญชีใช้ร่วม | K6: Network, Cloud, Identity, Database | L6: Level 2 - Medium: recommended setting; apply wherever technically applicable
A7: ESBIT-AC-02(04) | B7: AC-02(04) | C7: Access Control (AC) | D7: Account Management | Automated Audit Actions | E7: Protect (PR) | F7: PR.AA - Identity Management, Authentication, and Access Control | G7: PR.AA-01 | H7: Identities and credentials for authorized users, services, and hardware are managed by the organization | I7: Enhances AC-02 (Account Management): configure and enforce 'Automated Audit Actions' in addition to the base setting, keep it consistent across applicable systems and document approved exceptions. Base scope: Configure account types, naming, approval workflow and lifecycle in AD/LDAP, OS, database, network devices and cloud IAM; disable or remove inactive, temporary and shared accounts | J7: ส่วนขยายของ AC-02: กำหนดค่าและบังคับใช้ 'Automated Audit Actions' เพิ่มเติมจากค่าพื้นฐาน ให้สอดคล้องทุกระบบที่เกี่ยวข้อง และบันทึกข้อยกเว้น - กำหนดประเภทบัญชี การอนุมัติ และวงจรชีวิตบัญชีบน AD/OS/DB/อุปกรณ์เครือข่าย/Cloud IAM พร้อมปิดหรือลบบัญชีที่ไม่ใช้งาน ชั่วคราว และบัญชีใช้ร่วม | K7: Network, Cloud, Identity, Database | L7: Level 1 - High: mandatory setting that must exist in the configuration baseline
A8: ESBIT-AC-02(05) | B8: AC-02(05) | C8: Access Control (AC) | D8: Account Management | Inactivity Logout | E8: Protect (PR) | F8: PR.AA - Identity Management, Authentication, and Access Control | G8: PR.AA-01 | H8: Identities and credentials for authorized users, services, and hardware are managed by the organization | I8: Enhances AC-02 (Account Management): configure and enforce 'Inactivity Logout' in addition to the base setting, keep it consistent across applicable systems and document approved exceptions. Base scope: Configure account types, naming, approval workflow and lifecycle in AD/LDAP, OS, database, network devices and cloud IAM; disable or remove inactive, temporary and shared accounts | J8: ส่วนขยายของ AC-02: กำหนดค่าและบังคับใช้ 'Inactivity Logout' เพิ่มเติมจากค่าพื้นฐาน ให้สอดคล้องทุกระบบที่เกี่ยวข้อง และบันทึกข้อยกเว้น - กำหนดประเภทบัญชี การอนุมัติ และวงจรชีวิตบัญชีบน AD/OS/DB/อุปกรณ์เครือข่าย/Cloud IAM พร้อมปิดหรือลบบัญชีที่ไม่ใช้งาน ชั่วคราว และบัญชีใช้ร่วม | K8: Network, Cloud, Identity, Database | L8: Level 2 - Medium: recommended setting; apply wherever technically applicable
A9: ESBIT-AC-02(06) | B9: AC-02(06) | C9: Access Control (AC) | D9: Account Management | Dynamic Privilege Management | E9: Protect (PR) | F9: PR.AA - Identity Management, Authentication, and Access Control | G9: PR.AA-01 | H9: Identities and credentials for authorized users, services, and hardware are managed by the organization | I9: Enhances AC-02 (Account Management): configure and enforce 'Dynamic Privilege Management' in addition to the base setting, keep it consistent across applicable systems and document approved exceptions. Base scope: Configure account types, naming, approval workflow and lifecycle in AD/LDAP, OS, database, network devices and cloud IAM; disable or remove inactive, temporary and shared accounts | J9: ส่วนขยายของ AC-02: กำหนดค่าและบังคับใช้ 'Dynamic Privilege Management' เพิ่มเติมจากค่าพื้นฐาน ให้สอดคล้องทุกระบบที่เกี่ยวข้อง และบันทึกข้อยกเว้น - กำหนดประเภทบัญชี การอนุมัติ และวงจรชีวิตบัญชีบน AD/OS/DB/อุปกรณ์เครือข่าย/Cloud IAM พร้อมปิดหรือลบบัญชีที่ไม่ใช้งาน ชั่วคราว และบัญชีใช้ร่วม | K9: Network, Cloud, Identity, Database | L9: Level 2 - Medium: recommended setting; apply wherever technically applicable
A10: ESBIT-AC-02(07) | B10: AC-02(07) | C10: Access Control (AC) | D10: Account Management | Privileged User Accounts | E10: Protect (PR) | F10: PR.AA - Identity Management, Authentication, and Access Control | G10: PR.AA-01 | H10: Identities and credentials for authorized users, services, and hardware are managed by the organization | I10: Enhances AC-02 (Account Management): configure and enforce 'Privileged User Accounts' in addition to the base setting, keep it consistent across applicable systems and document approved exceptions. Base scope: Configure account types, naming, approval workflow and lifecycle in AD/LDAP, OS, database, network devices and cloud IAM; disable or remove inactive, temporary and shared accounts | J10: ส่วนขยายของ AC-02: กำหนดค่าและบังคับใช้ 'Privileged User Accounts' เพิ่มเติมจากค่าพื้นฐาน ให้สอดคล้องทุกระบบที่เกี่ยวข้อง และบันทึกข้อยกเว้น - กำหนดประเภทบัญชี การอนุมัติ และวงจรชีวิตบัญชีบน AD/OS/DB/อุปกรณ์เครือข่าย/Cloud IAM พร้อมปิดหรือลบบัญชีที่ไม่ใช้งาน ชั่วคราว และบัญชีใช้ร่วม | K10: Network, Cloud, Identity, Database | L10: Level 1 - High: mandatory setting that must exist in the configuration baseline
A11: ESBIT-AC-02(08) | B11: AC-02(08) | C11: Access Control (AC) | D11: Account Management | Dynamic Account Management | E11: Protect (PR) | F11: PR.AA - Identity Management, Authentication, and Access Control | G11: PR.AA-01 | H11: Identities and credentials for authorized users, services, and hardware are managed by the organization | I11: Enhances AC-02 (Account Management): configure and enforce 'Dynamic Account Management' in addition to the base setting, keep it consistent across applicable systems and document approved exceptions. Base scope: Configure account types, naming, approval workflow and lifecycle in AD/LDAP, OS, database, network devices and cloud IAM; disable or remove inactive, temporary and shared accounts | J11: ส่วนขยายของ AC-02: กำหนดค่าและบังคับใช้ 'Dynamic Account Management' เพิ่มเติมจากค่าพื้นฐาน ให้สอดคล้องทุกระบบที่เกี่ยวข้อง และบันทึกข้อยกเว้น - กำหนดประเภทบัญชี การอนุมัติ และวงจรชีวิตบัญชีบน AD/OS/DB/อุปกรณ์เครือข่าย/Cloud IAM พร้อมปิดหรือลบบัญชีที่ไม่ใช้งาน ชั่วคราว และบัญชีใช้ร่วม | K11: Network, Cloud, Identity, Database | L11: Level 2 - Medium: recommended setting; apply wherever technically applicable
A12: ESBIT-AC-02(09) | B12: AC-02(09) | C12: Access Control (AC) | D12: Account Management | Restrictions on Use of Shared and Group Accounts | E12: Protect (PR) | F12: PR.AA - Identity Management, Authentication, and Access Control | G12: PR.AA-01 | H12: Identities and credentials for authorized users, services, and hardware are managed by the organization | I12: Enhances AC-02 (Account Management): configure and enforce 'Restrictions on Use of Shared and Group Accounts' in addition to the base setting, keep it consistent across applicable systems and document approved exceptions. Base scope: Configure account types, naming, approval workflow and lifecycle in AD/LDAP, OS, database, network devices and cloud IAM; disable or remove inactive, temporary and shared accounts | J12: ส่วนขยายของ AC-02: กำหนดค่าและบังคับใช้ 'Restrictions on Use of Shared and Group Accounts' เพิ่มเติมจากค่าพื้นฐาน ให้สอดคล้องทุกระบบที่เกี่ยวข้อง และบันทึกข้อยกเว้น - กำหนดประเภทบัญชี การอนุมัติ และวงจรชีวิตบัญชีบน AD/OS/DB/อุปกรณ์เครือข่าย/Cloud IAM พร้อมปิดหรือลบบัญชีที่ไม่ใช้งาน ชั่วคราว และบัญชีใช้ร่วม | K12: Network, Cloud, Identity, Database | L12: Level 2 - Medium: recommended setting; apply wherever technically applicable
... A1017: ESBIT-SR-12 | B1017: SR-12 | C1017: Supply Chain Risk Management (SR) | D1017: Component Disposal | E1017: Protect (PR) | F1017: PR.PS - Platform Security | G1017: PR.PS-03 | H1017: Hardware is maintained, replaced, and removed commensurate with risk | I1017: Dispose of components using secure sanitization and destruction | J1017: กำจัดคอมโพเนนต์ด้วยการลบข้อมูลและทำลายอย่างปลอดภัย | K1017: Physical | L1017: Level 3 - Low: optional or limited impact; apply based on risk and context

Sheet Summary
A1: Control Family | B1: Level 1 | C1: Level 2 | D1: Level 3 | E1: Total
A2: Access Control (AC) | B2: =COUNTIFS('Config Baseline'!$C:$C,$A2,'Config Baseline'!$L:$L,"Level 1*") -> 22 | C2: =COUNTIFS('Config Baseline'!$C:$C,$A2,'Config Baseline'!$L:$L,"Level 2*") -> 75 | D2: =COUNTIFS('Config Baseline'!$C:$C,$A2,'Config Baseline'!$L:$L,"Level 3*") -> 30 | E2: =SUM(B2:D2) -> 127
A3: Awareness and Training (AT) | B3: =COUNTIFS('Config Baseline'!$C:$C,$A3,'Config Baseline'!$L:$L,"Level 1*") -> 0 | C3: =COUNTIFS('Config Baseline'!$C:$C,$A3,'Config Baseline'!$L:$L,"Level 2*") -> 0 | D3: =COUNTIFS('Config Baseline'!$C:$C,$A3,'Config Baseline'!$L:$L,"Level 3*") -> 16 | E3: =SUM(B3:D3) -> 16
A4: Audit and Accountability (AU) | B4: =COUNTIFS('Config Baseline'!$C:$C,$A4,'Config Baseline'!$L:$L,"Level 1*") -> 12 | C4: =COUNTIFS('Config Baseline'!$C:$C,$A4,'Config Baseline'!$L:$L,"Level 2*") -> 19 | D4: =COUNTIFS('Config Baseline'!$C:$C,$A4,'Config Baseline'!$L:$L,"Level 3*") -> 26 | E4: =SUM(B4:D4) -> 57
A5: Assessment, Authorization, and Monitoring (CA) | B5: =COUNTIFS('Config Baseline'!$C:$C,$A5,'Config Baseline'!$L:$L,"Level 1*") -> 0 | C5: =COUNTIFS('Config Baseline'!$C:$C,$A5,'Config Baseline'!$L:$L,"Level 2*") -> 3 | D5: =COUNTIFS('Config Baseline'!$C:$C,$A5,'Config Baseline'!$L:$L,"Level 3*") -> 22 | E5: =SUM(B5:D5) -> 25
A6: Configuration Management (CM) | B6: =COUNTIFS('Config Baseline'!$C:$C,$A6,'Config Baseline'!$L:$L,"Level 1*") -> 8 | C6: =COUNTIFS('Config Baseline'!$C:$C,$A6,'Config Baseline'!$L:$L,"Level 2*") -> 37 | D6: =COUNTIFS('Config Baseline'!$C:$C,$A6,'Config Baseline'!$L:$L,"Level 3*") -> 12 | E6: =SUM(B6:D6) -> 57
A7: Contingency Planning (CP) | B7: =COUNTIFS('Config Baseline'!$C:$C,$A7,'Config Baseline'!$L:$L,"Level 1*") -> 3 | C7: =COUNTIFS('Config Baseline'!$C:$C,$A7,'Config Baseline'!$L:$L,"Level 2*") -> 9 | D7: =COUNTIFS('Config Baseline'!$C:$C,$A7,'Config Baseline'!$L:$L,"Level 3*") -> 37 | E7: =SUM(B7:D7) -> 49
A8: Identification and Authentication (IA) | B8: =COUNTIFS('Config Baseline'!$C:$C,$A8,'Config Baseline'!$L:$L,"Level 1*") -> 7 | C8: =COUNTIFS('Config Baseline'!$C:$C,$A8,'Config Baseline'!$L:$L,"Level 2*") -> 36 | D8: =COUNTIFS('Config Baseline'!$C:$C,$A8,'Config Baseline'!$L:$L,"Level 3*") -> 18 | E8: =SUM(B8:D8) -> 61
A9: Incident Response (IR) | B9: =COUNTIFS('Config Baseline'!$C:$C,$A9,'Config Baseline'!$L:$L,"Level 1*") -> 0 | C9: =COUNTIFS('Config Baseline'!$C:$C,$A9,'Config Baseline'!$L:$L,"Level 2*") -> 1 | D9: =COUNTIFS('Config Baseline'!$C:$C,$A9,'Config Baseline'!$L:$L,"Level 3*") -> 38 | E9: =SUM(B9:D9) -> 39
A10: Maintenance (MA) | B10: =COUNTIFS('Config Baseline'!$C:$C,$A10,'Config Baseline'!$L:$L,"Level 1*") -> 3 | C10: =COUNTIFS('Config Baseline'!$C:$C,$A10,'Config Baseline'!$L:$L,"Level 2*") -> 4 | D10: =COUNTIFS('Config Baseline'!$C:$C,$A10,'Config Baseline'!$L:$L,"Level 3*") -> 21 | E10: =SUM(B10:D10) -> 28
A11: Media Protection (MP) | B11: =COUNTIFS('Config Baseline'!$C:$C,$A11,'Config Baseline'!$L:$L,"Level 1*") -> 0 | C11: =COUNTIFS('Config Baseline'!$C:$C,$A11,'Config Baseline'!$L:$L,"Level 2*") -> 6 | D11: =COUNTIFS('Config Baseline'!$C:$C,$A11,'Config Baseline'!$L:$L,"Level 3*") -> 14 | E11: =SUM(B11:D11) -> 20
A12: Physical and Environmental Protection (PE) | B12: =COUNTIFS('Config Baseline'!$C:$C,$A12,'Config Baseline'!$L:$L,"Level 1*") -> 0 | C12: =COUNTIFS('Config Baseline'!$C:$C,$A12,'Config Baseline'!$L:$L,"Level 2*") -> 0 | D12: =COUNTIFS('Config Baseline'!$C:$C,$A12,'Config Baseline'!$L:$L,"Level 3*") -> 50 | E12: =SUM(B12:D12) -> 50
A13: Planning (PL) | B13: =COUNTIFS('Config Baseline'!$C:$C,$A13,'Config Baseline'!$L:$L,"Level 1*") -> 0 | C13: =COUNTIFS('Config Baseline'!$C:$C,$A13,'Config Baseline'!$L:$L,"Level 2*") -> 1 | D13: =COUNTIFS('Config Baseline'!$C:$C,$A13,'Config Baseline'!$L:$L,"Level 3*") -> 10 | E13: =SUM(B13:D13) -> 11
... A21: Supply Chain Risk Management (SR) | B21: =COUNTIFS('Config Baseline'!$C:$C,$A21,'Config Baseline'!$L:$L,"Level 1*") -> 0 | C21: =COUNTIFS('Config Baseline'!$C:$C,$A21,'Config Baseline'!$L:$L,"Level 2*") -> 0 | D21: =COUNTIFS('Config Baseline'!$C:$C,$A21,'Config Baseline'!$L:$L,"Level 3*") -> 27 | E21: =SUM(B21:D21) -> 27
A22: Total | B22: =SUM(B2:B21) -> 93 | C22: =SUM(C2:C21) -> 311 | D22: =SUM(D2:D21) -> 612 | E22: =SUM(E2:E21) -> 1016

Sheet Domain Summary
A1: IT Domain Summary - counts of control families, base controls and control IDs (a control can appear in more than one domain)
A3: IT Domain | B3: Families | C3: Base Controls | D3: Control IDs (base + enhancements) | E3: Level 1 | F3: Level 2 | G3: Level 3
A4: Network | B4: =COUNTIF(B32:U32,">0") -> 14 | C4: =SUMPRODUCT(ISNUMBER(SEARCH($A4,'Config Baseline'!$K$2:$K$1017))*ISERROR(SEARCH("(",'Config Baseline'!$B$2:$B$1017))) -> 76 | D4: =COUNTIF('Config Baseline'!$K$2:$K$1017,"*"&$A4&"*") -> 413 | E4: =COUNTIFS('Config Baseline'!$K$2:$K$1017,"*"&$A4&"*",'Config Baseline'!$L$2:$L$1017,"Level 1*") -> 80 | F4: =COUNTIFS('Config Baseline'!$K$2:$K$1017,"*"&$A4&"*",'Config Baseline'!$L$2:$L$1017,"Level 2*") -> 251 | G4: =COUNTIFS('Config Baseline'!$K$2:$K$1017,"*"&$A4&"*",'Config Baseline'!$L$2:$L$1017,"Level 3*") -> 82
A5: Cloud | B5: =COUNTIF(B33:U33,">0") -> 15 | C5: =SUMPRODUCT(ISNUMBER(SEARCH($A5,'Config Baseline'!$K$2:$K$1017))*ISERROR(SEARCH("(",'Config Baseline'!$B$2:$B$1017))) -> 115 | D5: =COUNTIF('Config Baseline'!$K$2:$K$1017,"*"&$A5&"*") -> 596 | E5: =COUNTIFS('Config Baseline'!$K$2:$K$1017,"*"&$A5&"*",'Config Baseline'!$L$2:$L$1017,"Level 1*") -> 87 | F5: =COUNTIFS('Config Baseline'!$K$2:$K$1017,"*"&$A5&"*",'Config Baseline'!$L$2:$L$1017,"Level 2*") -> 285 | G5: =COUNTIFS('Config Baseline'!$K$2:$K$1017,"*"&$A5&"*",'Config Baseline'!$L$2:$L$1017,"Level 3*") -> 224
A6: Identity | B6: =COUNTIF(B34:U34,">0") -> 3 | C6: =SUMPRODUCT(ISNUMBER(SEARCH($A6,'Config Baseline'!$K$2:$K$1017))*ISERROR(SEARCH("(",'Config Baseline'!$B$2:$B$1017))) -> 21 | D6: =COUNTIF('Config Baseline'!$K$2:$K$1017,"*"&$A6&"*") -> 119 | E6: =COUNTIFS('Config Baseline'!$K$2:$K$1017,"*"&$A6&"*",'Config Baseline'!$L$2:$L$1017,"Level 1*") -> 21 | F6: =COUNTIFS('Config Baseline'!$K$2:$K$1017,"*"&$A6&"*",'Config Baseline'!$L$2:$L$1017,"Level 2*") -> 71 | G6: =COUNTIFS('Config Baseline'!$K$2:$K$1017,"*"&$A6&"*",'Config Baseline'!$L$2:$L$1017,"Level 3*") -> 27
A7: Monitoring | B7: =COUNTIF(B35:U35,">0") -> 6 | C7: =SUMPRODUCT(ISNUMBER(SEARCH($A7,'Config Baseline'!$K$2:$K$1017))*ISERROR(SEARCH("(",'Config Baseline'!$B$2:$B$1017))) -> 18 | D7: =COUNTIF('Config Baseline'!$K$2:$K$1017,"*"&$A7&"*") -> 100 | E7: =COUNTIFS('Config Baseline'!$K$2:$K$1017,"*"&$A7&"*",'Config Baseline'!$L$2:$L$1017,"Level 1*") -> 14 | F7: =COUNTIFS('Config Baseline'!$K$2:$K$1017,"*"&$A7&"*",'Config Baseline'!$L$2:$L$1017,"Level 2*") -> 43 | G7: =COUNTIFS('Config Baseline'!$K$2:$K$1017,"*"&$A7&"*",'Config Baseline'!$L$2:$L$1017,"Level 3*") -> 43
A8: Database | B8: =COUNTIF(B36:U36,">0") -> 7 | C8: =SUMPRODUCT(ISNUMBER(SEARCH($A8,'Config Baseline'!$K$2:$K$1017))*ISERROR(SEARCH("(",'Config Baseline'!$B$2:$B$1017))) -> 19 | D8: =COUNTIF('Config Baseline'!$K$2:$K$1017,"*"&$A8&"*") -> 115 | E8: =COUNTIFS('Config Baseline'!$K$2:$K$1017,"*"&$A8&"*",'Config Baseline'!$L$2:$L$1017,"Level 1*") -> 25 | F8: =COUNTIFS('Config Baseline'!$K$2:$K$1017,"*"&$A8&"*",'Config Baseline'!$L$2:$L$1017,"Level 2*") -> 70 | G8: =COUNTIFS('Config Baseline'!$K$2:$K$1017,"*"&$A8&"*",'Config Baseline'!$L$2:$L$1017,"Level 3*") -> 20
A9: Application | B9: =COUNTIF(B37:U37,">0") -> 12 | C9: =SUMPRODUCT(ISNUMBER(SEARCH($A9,'Config Baseline'!$K$2:$K$1017))*ISERROR(SEARCH("(",'Config Baseline'!$B$2:$B$1017))) -> 113 | D9: =COUNTIF('Config Baseline'!$K$2:$K$1017,"*"&$A9&"*") -> 484 | E9: =COUNTIFS('Config Baseline'!$K$2:$K$1017,"*"&$A9&"*",'Config Baseline'!$L$2:$L$1017,"Level 1*") -> 63 | F9: =COUNTIFS('Config Baseline'!$K$2:$K$1017,"*"&$A9&"*",'Config Baseline'!$L$2:$L$1017,"Level 2*") -> 193 | G9: =COUNTIFS('Config Baseline'!$K$2:$K$1017,"*"&$A9&"*",'Config Baseline'!$L$2:$L$1017,"Level 3*") -> 228
A10: Backup | B10: =COUNTIF(B38:U38,">0") -> 1 | C10: =SUMPRODUCT(ISNUMBER(SEARCH($A10,'Config Baseline'!$K$2:$K$1017))*ISERROR(SEARCH("(",'Config Baseline'!$B$2:$B$1017))) -> 6 | D10: =COUNTIF('Config Baseline'!$K$2:$K$1017,"*"&$A10&"*") -> 33 | E10: =COUNTIFS('Config Baseline'!$K$2:$K$1017,"*"&$A10&"*",'Config Baseline'!$L$2:$L$1017,"Level 1*") -> 3 | F10: =COUNTIFS('Config Baseline'!$K$2:$K$1017,"*"&$A10&"*",'Config Baseline'!$L$2:$L$1017,"Level 2*") -> 7 | G10: =COUNTIFS('Config Baseline'!$K$2:$K$1017,"*"&$A10&"*",'Config Baseline'!$L$2:$L$1017,"Level 3*") -> 23
A11: Governance | B11: =COUNTIF(B39:U39,">0") -> 19 | C11: =SUMPRODUCT(ISNUMBER(SEARCH($A11,'Config Baseline'!$K$2:$K$1017))*ISERROR(SEARCH("(",'Config Baseline'!$B$2:$B$1017))) -> 91 | D11: =COUNTIF('Config Baseline'!$K$2:$K$1017,"*"&$A11&"*") -> 179 | E11: =COUNTIFS('Config Baseline'!$K$2:$K$1017,"*"&$A11&"*",'Config Baseline'!$L$2:$L$1017,"Level 1*") -> 0 | F11: =COUNTIFS('Config Baseline'!$K$2:$K$1017,"*"&$A11&"*",'Config Baseline'!$L$2:$L$1017,"Level 2*") -> 6 | G11: =COUNTIFS('Config Baseline'!$K$2:$K$1017,"*"&$A11&"*",'Config Baseline'!$L$2:$L$1017,"Level 3*") -> 173
A12: Physical | B12: =COUNTIF(B40:U40,">0") -> 4 | C12: =SUMPRODUCT(ISNUMBER(SEARCH($A12,'Config Baseline'!$K$2:$K$1017))*ISERROR(SEARCH("(",'Config Baseline'!$B$2:$B$1017))) -> 38 | D12: =COUNTIF('Config Baseline'!$K$2:$K$1017,"*"&$A12&"*") -> 103 | E12: =COUNTIFS('Config Baseline'!$K$2:$K$1017,"*"&$A12&"*",'Config Baseline'!$L$2:$L$1017,"Level 1*") -> 3 | F12: =COUNTIFS('Config Baseline'!$K$2:$K$1017,"*"&$A12&"*",'Config Baseline'!$L$2:$L$1017,"Level 2*") -> 10 | G12: =COUNTIFS('Config Baseline'!$K$2:$K$1017,"*"&$A12&"*",'Config Baseline'!$L$2:$L$1017,"Level 3*") -> 90
A13: Third Party | B13: =COUNTIF(B41:U41,">0") -> 2 | C13: =SUMPRODUCT(ISNUMBER(SEARCH($A13,'Config Baseline'!$K$2:$K$1017))*ISERROR(SEARCH("(",'Config Baseline'!$B$2:$B$1017))) -> 10 | D13: =COUNTIF('Config Baseline'!$K$2:$K$1017,"*"&$A13&"*") -> 32 | E13: =COUNTIFS('Config Baseline'!$K$2:$K$1017,"*"&$A13&"*",'Config Baseline'!$L$2:$L$1017,"Level 1*") -> 0 | F13: =COUNTIFS('Config Baseline'!$K$2:$K$1017,"*"&$A13&"*",'Config Baseline'!$L$2:$L$1017,"Level 2*") -> 3 | G13: =COUNTIFS('Config Baseline'!$K$2:$K$1017,"*"&$A13&"*",'Config Baseline'!$L$2:$L$1017,"Level 3*") -> 29
A14: Unique rows in register (all domains) | C14: =SUMPRODUCT(ISERROR(SEARCH("(",'Config Baseline'!$B$2:$B$1017))*1) -> 300 | D14: =COUNTA('Config Baseline'!$B$2:$B$1017) -> 1016
A15: Note: domain rows overlap, so they add up to more than the unique total.
A17: IT Domain | B17: Scope and assignment note
A18: Network | B18: Routers, switches, firewalls, wireless and DNS/NTP. Baseline scope: AC, AU, CA, CM, CP (links), IA, IR, MA (remote), PL, RA, SA (unsupported devices), SC, SI, SR (authentic components).
A19: Cloud | B19: IaaS/PaaS/SaaS tenant and workload configuration. Baseline scope: AC, AU, CA, CM, CP, IA, IR, RA, SA, SC, SI, SR, plus MP-6, PL-8/9, PS-4/5.
A20: Identity | B20: Account, authentication and privilege management (IAM, directory, SSO/MFA).
A21: Monitoring | B21: Logging, SIEM, monitoring and detection tooling.
A22: Database | B22: Database engines, data stores and data-level protection.
A23: Application | B23: Applications and the operating-system/endpoint software layer (former Infrastructure and Endpoint items were placed here).
A24: Backup | B24: Backup, DR, alternate sites and resilience.
A25: Governance | B25: Policies, procedures, training, risk and privacy governance (non-technical controls).
A26: Physical | B26: Facilities, data center, media, hardware maintenance and hardware supply chain.
A27: Third Party | B27: Suppliers, outsourced services and supply chain risk.
A30: Control IDs (base + enhancements) by domain and family
A31: IT Domain | B31: AC | C31: AT | D31: AU | E31: CA | F31: CM | G31: CP | H31: IA | I31: IR | J31: MA | K31: MP | L31: PE | M31: PL | N31: PM | O31: PS | P31: PT | Q31: RA | R31: SA | S31: SC | T31: SI | U31: SR | V31: Total
A32: Network | B32: =COUNTIFS('Config Baseline'!$C$2:$C$1017,"*("&B$31&")",'Config Baseline'!$K$2:$K$1017,"*"&$A32&"*") -> 97 | C32: =COUNTIFS('Config Baseline'!$C$2:$C$1017,"*("&C$31&")",'Config Baseline'!$K$2:$K$1017,"*"&$A32&"*") -> 0 | D32: =COUNTIFS('Config Baseline'!$C$2:$C$1017,"*("&D$31&")",'Config Baseline'!$K$2:$K$1017,"*"&$A32&"*") -> 38 | E32: =COUNTIFS('Config Baseline'!$C$2:$C$1017,"*("&E$31&")",'Config Baseline'!$K$2:$K$1017,"*"&$A32&"*") -> 19 | F32: =COUNTIFS('Config Baseline'!$C$2:$C$1017,"*("&F$31&")",'Config Baseline'!$K$2:$K$1017,"*"&$A32&"*") -> 46 | G32: =COUNTIFS('Config Baseline'!$C$2:$C$1017,"*("&G$31&")",'Config Baseline'!$K$2:$K$1017,"*"&$A32&"*") -> 7 | H32: =COUNTIFS('Config Baseline'!$C$2:$C$1017,"*("&H$31&")",'Config Baseline'!$K$2:$K$1017,"*"&$A32&"*") -> 37 | I32: =COUNTIFS('Config Baseline'!$C$2:$C$1017,"*("&I$31&")",'Config Baseline'!$K$2:$K$1017,"*"&$A32&"*") -> 16 | ... U32: =COUNTIFS('Config Baseline'!$C$2:$C$1017,"*("&U$31&")",'Config Baseline'!$K$2:$K$1017,"*"&$A32&"*") -> 4 | V32: =SUM(B32:U32) -> 413
A33: Cloud | B33: =COUNTIFS('Config Baseline'!$C$2:$C$1017,"*("&B$31&")",'Config Baseline'!$K$2:$K$1017,"*"&$A33&"*") -> 95 | C33: =COUNTIFS('Config Baseline'!$C$2:$C$1017,"*("&C$31&")",'Config Baseline'!$K$2:$K$1017,"*"&$A33&"*") -> 0 | D33: =COUNTIFS('Config Baseline'!$C$2:$C$1017,"*("&D$31&")",'Config Baseline'!$K$2:$K$1017,"*"&$A33&"*") -> 40 | E33: =COUNTIFS('Config Baseline'!$C$2:$C$1017,"*("&E$31&")",'Config Baseline'!$K$2:$K$1017,"*"&$A33&"*") -> 21 | F33: =COUNTIFS('Config Baseline'!$C$2:$C$1017,"*("&F$31&")",'Config Baseline'!$K$2:$K$1017,"*"&$A33&"*") -> 49 | G33: =COUNTIFS('Config Baseline'!$C$2:$C$1017,"*("&G$31&")",'Config Baseline'!$K$2:$K$1017,"*"&$A33&"*") -> 36 | H33: =COUNTIFS('Config Baseline'!$C$2:$C$1017,"*("&H$31&")",'Config Baseline'!$K$2:$K$1017,"*"&$A33&"*") -> 52 | I33: =COUNTIFS('Config Baseline'!$C$2:$C$1017,"*("&I$31&")",'Config Baseline'!$K$2:$K$1017,"*"&$A33&"*") -> 26 | ... U33: =COUNTIFS('Config Baseline'!$C$2:$C$1017,"*("&U$31&")",'Config Baseline'!$K$2:$K$1017,"*"&$A33&"*") -> 12 | V33: =SUM(B33:U33) -> 596
A34: Identity | B34: =COUNTIFS('Config Baseline'!$C$2:$C$1017,"*("&B$31&")",'Config Baseline'!$K$2:$K$1017,"*"&$A34&"*") -> 61 | C34: =COUNTIFS('Config Baseline'!$C$2:$C$1017,"*("&C$31&")",'Config Baseline'!$K$2:$K$1017,"*"&$A34&"*") -> 0 | D34: =COUNTIFS('Config Baseline'!$C$2:$C$1017,"*("&D$31&")",'Config Baseline'!$K$2:$K$1017,"*"&$A34&"*") -> 0 | E34: =COUNTIFS('Config Baseline'!$C$2:$C$1017,"*("&E$31&")",'Config Baseline'!$K$2:$K$1017,"*"&$A34&"*") -> 0 | F34: =COUNTIFS('Config Baseline'!$C$2:$C$1017,"*("&F$31&")",'Config Baseline'!$K$2:$K$1017,"*"&$A34&"*") -> 0 | G34: =COUNTIFS('Config Baseline'!$C$2:$C$1017,"*("&G$31&")",'Config Baseline'!$K$2:$K$1017,"*"&$A34&"*") -> 0 | H34: =COUNTIFS('Config Baseline'!$C$2:$C$1017,"*("&H$31&")",'Config Baseline'!$K$2:$K$1017,"*"&$A34&"*") -> 54 | I34: =COUNTIFS('Config Baseline'!$C$2:$C$1017,"*("&I$31&")",'Config Baseline'!$K$2:$K$1017,"*"&$A34&"*") -> 0 | ... U34: =COUNTIFS('Config Baseline'!$C$2:$C$1017,"*("&U$31&")",'Config Baseline'!$K$2:$K$1017,"*"&$A34&"*") -> 0 | V34: =SUM(B34:U34) -> 119
A35: Monitoring | B35: =COUNTIFS('Config Baseline'!$C$2:$C$1017,"*("&B$31&")",'Config Baseline'!$K$2:$K$1017,"*"&$A35&"*") -> 0 | C35: =COUNTIFS('Config Baseline'!$C$2:$C$1017,"*("&C$31&")",'Config Baseline'!$K$2:$K$1017,"*"&$A35&"*") -> 0 | D35: =COUNTIFS('Config Baseline'!$C$2:$C$1017,"*("&D$31&")",'Config Baseline'!$K$2:$K$1017,"*"&$A35&"*") -> 50 | E35: =COUNTIFS('Config Baseline'!$C$2:$C$1017,"*("&E$31&")",'Config Baseline'!$K$2:$K$1017,"*"&$A35&"*") -> 6 | F35: =COUNTIFS('Config Baseline'!$C$2:$C$1017,"*("&F$31&")",'Config Baseline'!$K$2:$K$1017,"*"&$A35&"*") -> 0 | G35: =COUNTIFS('Config Baseline'!$C$2:$C$1017,"*("&G$31&")",'Config Baseline'!$K$2:$K$1017,"*"&$A35&"*") -> 0 | H35: =COUNTIFS('Config Baseline'!$C$2:$C$1017,"*("&H$31&")",'Config Baseline'!$K$2:$K$1017,"*"&$A35&"*") -> 0 | I35: =COUNTIFS('Config Baseline'!$C$2:$C$1017,"*("&I$31&")",'Config Baseline'!$K$2:$K$1017,"*"&$A35&"*") -> 18 | ... U35: =COUNTIFS('Config Baseline'!$C$2:$C$1017,"*("&U$31&")",'Config Baseline'!$K$2:$K$1017,"*"&$A35&"*") -> 0 | V35: =SUM(B35:U35) -> 100
A36: Database | B36: =COUNTIFS('Config Baseline'!$C$2:$C$1017,"*("&B$31&")",'Config Baseline'!$K$2:$K$1017,"*"&$A36&"*") -> 42 | C36: =COUNTIFS('Config Baseline'!$C$2:$C$1017,"*("&C$31&")",'Config Baseline'!$K$2:$K$1017,"*"&$A36&"*") -> 0 | D36: =COUNTIFS('Config Baseline'!$C$2:$C$1017,"*("&D$31&")",'Config Baseline'!$K$2:$K$1017,"*"&$A36&"*") -> 0 | E36: =COUNTIFS('Config Baseline'!$C$2:$C$1017,"*("&E$31&")",'Config Baseline'!$K$2:$K$1017,"*"&$A36&"*") -> 0 | F36: =COUNTIFS('Config Baseline'!$C$2:$C$1017,"*("&F$31&")",'Config Baseline'!$K$2:$K$1017,"*"&$A36&"*") -> 10 | G36: =COUNTIFS('Config Baseline'!$C$2:$C$1017,"*("&G$31&")",'Config Baseline'!$K$2:$K$1017,"*"&$A36&"*") -> 12 | H36: =COUNTIFS('Config Baseline'!$C$2:$C$1017,"*("&H$31&")",'Config Baseline'!$K$2:$K$1017,"*"&$A36&"*") -> 16 | I36: =COUNTIFS('Config Baseline'!$C$2:$C$1017,"*("&I$31&")",'Config Baseline'!$K$2:$K$1017,"*"&$A36&"*") -> 0 | ... U36: =COUNTIFS('Config Baseline'!$C$2:$C$1017,"*("&U$31&")",'Config Baseline'!$K$2:$K$1017,"*"&$A36&"*") -> 0 | V36: =SUM(B36:U36) -> 115
A37: Application | B37: =COUNTIFS('Config Baseline'!$C$2:$C$1017,"*("&B$31&")",'Config Baseline'!$K$2:$K$1017,"*"&$A37&"*") -> 63 | C37: =COUNTIFS('Config Baseline'!$C$2:$C$1017,"*("&C$31&")",'Config Baseline'!$K$2:$K$1017,"*"&$A37&"*") -> 0 | D37: =COUNTIFS('Config Baseline'!$C$2:$C$1017,"*("&D$31&")",'Config Baseline'!$K$2:$K$1017,"*"&$A37&"*") -> 17 | E37: =COUNTIFS('Config Baseline'!$C$2:$C$1017,"*("&E$31&")",'Config Baseline'!$K$2:$K$1017,"*"&$A37&"*") -> 6 | F37: =COUNTIFS('Config Baseline'!$C$2:$C$1017,"*("&F$31&")",'Config Baseline'!$K$2:$K$1017,"*"&$A37&"*") -> 54 | G37: =COUNTIFS('Config Baseline'!$C$2:$C$1017,"*("&G$31&")",'Config Baseline'!$K$2:$K$1017,"*"&$A37&"*") -> 20 | H37: =COUNTIFS('Config Baseline'!$C$2:$C$1017,"*("&H$31&")",'Config Baseline'!$K$2:$K$1017,"*"&$A37&"*") -> 40 | I37: =COUNTIFS('Config Baseline'!$C$2:$C$1017,"*("&I$31&")",'Config Baseline'!$K$2:$K$1017,"*"&$A37&"*") -> 0 | ... U37: =COUNTIFS('Config Baseline'!$C$2:$C$1017,"*("&U$31&")",'Config Baseline'!$K$2:$K$1017,"*"&$A37&"*") -> 0 | V37: =SUM(B37:U37) -> 484
A38: Backup | B38: =COUNTIFS('Config Baseline'!$C$2:$C$1017,"*("&B$31&")",'Config Baseline'!$K$2:$K$1017,"*"&$A38&"*") -> 0 | C38: =COUNTIFS('Config Baseline'!$C$2:$C$1017,"*("&C$31&")",'Config Baseline'!$K$2:$K$1017,"*"&$A38&"*") -> 0 | D38: =COUNTIFS('Config Baseline'!$C$2:$C$1017,"*("&D$31&")",'Config Baseline'!$K$2:$K$1017,"*"&$A38&"*") -> 0 | E38: =COUNTIFS('Config Baseline'!$C$2:$C$1017,"*("&E$31&")",'Config Baseline'!$K$2:$K$1017,"*"&$A38&"*") -> 0 | F38: =COUNTIFS('Config Baseline'!$C$2:$C$1017,"*("&F$31&")",'Config Baseline'!$K$2:$K$1017,"*"&$A38&"*") -> 0 | G38: =COUNTIFS('Config Baseline'!$C$2:$C$1017,"*("&G$31&")",'Config Baseline'!$K$2:$K$1017,"*"&$A38&"*") -> 33 | H38: =COUNTIFS('Config Baseline'!$C$2:$C$1017,"*("&H$31&")",'Config Baseline'!$K$2:$K$1017,"*"&$A38&"*") -> 0 | I38: =COUNTIFS('Config Baseline'!$C$2:$C$1017,"*("&I$31&")",'Config Baseline'!$K$2:$K$1017,"*"&$A38&"*") -> 0 | ... U38: =COUNTIFS('Config Baseline'!$C$2:$C$1017,"*("&U$31&")",'Config Baseline'!$K$2:$K$1017,"*"&$A38&"*") -> 0 | V38: =SUM(B38:U38) -> 33
A39: Governance | B39: =COUNTIFS('Config Baseline'!$C$2:$C$1017,"*("&B$31&")",'Config Baseline'!$K$2:$K$1017,"*"&$A39&"*") -> 1 | C39: =COUNTIFS('Config Baseline'!$C$2:$C$1017,"*("&C$31&")",'Config Baseline'!$K$2:$K$1017,"*"&$A39&"*") -> 16 | D39: =COUNTIFS('Config Baseline'!$C$2:$C$1017,"*("&D$31&")",'Config Baseline'!$K$2:$K$1017,"*"&$A39&"*") -> 10 | E39: =COUNTIFS('Config Baseline'!$C$2:$C$1017,"*("&E$31&")",'Config Baseline'!$K$2:$K$1017,"*"&$A39&"*") -> 14 | F39: =COUNTIFS('Config Baseline'!$C$2:$C$1017,"*("&F$31&")",'Config Baseline'!$K$2:$K$1017,"*"&$A39&"*") -> 1 | G39: =COUNTIFS('Config Baseline'!$C$2:$C$1017,"*("&G$31&")",'Config Baseline'!$K$2:$K$1017,"*"&$A39&"*") -> 1 | H39: =COUNTIFS('Config Baseline'!$C$2:$C$1017,"*("&H$31&")",'Config Baseline'!$K$2:$K$1017,"*"&$A39&"*") -> 1 | I39: =COUNTIFS('Config Baseline'!$C$2:$C$1017,"*("&I$31&")",'Config Baseline'!$K$2:$K$1017,"*"&$A39&"*") -> 37 | ... U39: =COUNTIFS('Config Baseline'!$C$2:$C$1017,"*("&U$31&")",'Config Baseline'!$K$2:$K$1017,"*"&$A39&"*") -> 1 | V39: =SUM(B39:U39) -> 179
A40: Physical | B40: =COUNTIFS('Config Baseline'!$C$2:$C$1017,"*("&B$31&")",'Config Baseline'!$K$2:$K$1017,"*"&$A40&"*") -> 0 | C40: =COUNTIFS('Config Baseline'!$C$2:$C$1017,"*("&C$31&")",'Config Baseline'!$K$2:$K$1017,"*"&$A40&"*") -> 0 | D40: =COUNTIFS('Config Baseline'!$C$2:$C$1017,"*("&D$31&")",'Config Baseline'!$K$2:$K$1017,"*"&$A40&"*") -> 0 | E40: =COUNTIFS('Config Baseline'!$C$2:$C$1017,"*("&E$31&")",'Config Baseline'!$K$2:$K$1017,"*"&$A40&"*") -> 0 | F40: =COUNTIFS('Config Baseline'!$C$2:$C$1017,"*("&F$31&")",'Config Baseline'!$K$2:$K$1017,"*"&$A40&"*") -> 0 | G40: =COUNTIFS('Config Baseline'!$C$2:$C$1017,"*("&G$31&")",'Config Baseline'!$K$2:$K$1017,"*"&$A40&"*") -> 0 | H40: =COUNTIFS('Config Baseline'!$C$2:$C$1017,"*("&H$31&")",'Config Baseline'!$K$2:$K$1017,"*"&$A40&"*") -> 0 | I40: =COUNTIFS('Config Baseline'!$C$2:$C$1017,"*("&I$31&")",'Config Baseline'!$K$2:$K$1017,"*"&$A40&"*") -> 0 | ... U40: =COUNTIFS('Config Baseline'!$C$2:$C$1017,"*("&U$31&")",'Config Baseline'!$K$2:$K$1017,"*"&$A40&"*") -> 7 | V40: =SUM(B40:U40) -> 103
A41: Third Party | B41: =COUNTIFS('Config Baseline'!$C$2:$C$1017,"*("&B$31&")",'Config Baseline'!$K$2:$K$1017,"*"&$A41&"*") -> 0 | C41: =COUNTIFS('Config Baseline'!$C$2:$C$1017,"*("&C$31&")",'Config Baseline'!$K$2:$K$1017,"*"&$A41&"*") -> 0 | D41: =COUNTIFS('Config Baseline'!$C$2:$C$1017,"*("&D$31&")",'Config Baseline'!$K$2:$K$1017,"*"&$A41&"*") -> 0 | E41: =COUNTIFS('Config Baseline'!$C$2:$C$1017,"*("&E$31&")",'Config Baseline'!$K$2:$K$1017,"*"&$A41&"*") -> 0 | F41: =COUNTIFS('Config Baseline'!$C$2:$C$1017,"*("&F$31&")",'Config Baseline'!$K$2:$K$1017,"*"&$A41&"*") -> 0 | G41: =COUNTIFS('Config Baseline'!$C$2:$C$1017,"*("&G$31&")",'Config Baseline'!$K$2:$K$1017,"*"&$A41&"*") -> 0 | H41: =COUNTIFS('Config Baseline'!$C$2:$C$1017,"*("&H$31&")",'Config Baseline'!$K$2:$K$1017,"*"&$A41&"*") -> 0 | I41: =COUNTIFS('Config Baseline'!$C$2:$C$1017,"*("&I$31&")",'Config Baseline'!$K$2:$K$1017,"*"&$A41&"*") -> 0 | ... U41: =COUNTIFS('Config Baseline'!$C$2:$C$1017,"*("&U$31&")",'Config Baseline'!$K$2:$K$1017,"*"&$A41&"*") -> 23 | V41: =SUM(B41:U41) -> 32
A44: Base controls only, by domain and family
A45: IT Domain | B45: AC | C45: AT | D45: AU | E45: CA | F45: CM | G45: CP | H45: IA | I45: IR | J45: MA | K45: MP | L45: PE | M45: PL | N45: PM | O45: PS | P45: PT | Q45: RA | R45: SA | S45: SC | T45: SI | U45: SR | V45: Total
A46: Network | B46: =SUMPRODUCT(ISNUMBER(SEARCH("("&B$45&")",'Config Baseline'!$C$2:$C$1017))*ISNUMBER(SEARCH($A46,'Config Baseline'!$K$2:$K$1017))*ISERROR(SEARCH("(",'Config Baseline'!$B$2:$B$1017))) -> 13 | C46: =SUMPRODUCT(ISNUMBER(SEARCH("("&C$45&")",'Config Baseline'!$C$2:$C$1017))*ISNUMBER(SEARCH($A46,'Config Baseline'!$K$2:$K$1017))*ISERROR(SEARCH("(",'Config Baseline'!$B$2:$B$1017))) -> 0 | D46: =SUMPRODUCT(ISNUMBER(SEARCH("("&D$45&")",'Config Baseline'!$C$2:$C$1017))*ISNUMBER(SEARCH($A46,'Config Baseline'!$K$2:$K$1017))*ISERROR(SEARCH("(",'Config Baseline'!$B$2:$B$1017))) -> 9 | E46: =SUMPRODUCT(ISNUMBER(SEARCH("("&E$45&")",'Config Baseline'!$C$2:$C$1017))*ISNUMBER(SEARCH($A46,'Config Baseline'!$K$2:$K$1017))*ISERROR(SEARCH("(",'Config Baseline'!$B$2:$B$1017))) -> 5 | F46: =SUMPRODUCT(ISNUMBER(SEARCH("("&F$45&")",'Config Baseline'!$C$2:$C$1017))*ISNUMBER(SEARCH($A46,'Config Baseline'!$K$2:$K$1017))*ISERROR(SEARCH("(",'Config Baseline'!$B$2:$B$1017))) -> 8 | G46: =SUMPRODUCT(ISNUMBER(SEARCH("("&G$45&")",'Config Baseline'!$C$2:$C$1017))*ISNUMBER(SEARCH($A46,'Config Baseline'!$K$2:$K$1017))*ISERROR(SEARCH("(",'Config Baseline'!$B$2:$B$1017))) -> 2 | H46: =SUMPRODUCT(ISNUMBER(SEARCH("("&H$45&")",'Config Baseline'!$C$2:$C$1017))*ISNUMBER(SEARCH($A46,'Config Baseline'!$K$2:$K$1017))*ISERROR(SEARCH("(",'Config Baseline'!$B$2:$B$1017))) -> 5 | I46: =SUMPRODUCT(ISNUMBER(SEARCH("("&I$45&")",'Config Baseline'!$C$2:$C$1017))*ISNUMBER(SEARCH($A46,'Config Baseline'!$K$2:$K$1017))*ISERROR(SEARCH("(",'Config Baseline'!$B$2:$B$1017))) -> 1 | ... U46: =SUMPRODUCT(ISNUMBER(SEARCH("("&U$45&")",'Config Baseline'!$C$2:$C$1017))*ISNUMBER(SEARCH($A46,'Config Baseline'!$K$2:$K$1017))*ISERROR(SEARCH("(",'Config Baseline'!$B$2:$B$1017))) -> 1 | V46: =SUM(B46:U46) -> 76
A47: Cloud | B47: =SUMPRODUCT(ISNUMBER(SEARCH("("&B$45&")",'Config Baseline'!$C$2:$C$1017))*ISNUMBER(SEARCH($A47,'Config Baseline'!$K$2:$K$1017))*ISERROR(SEARCH("(",'Config Baseline'!$B$2:$B$1017))) -> 13 | C47: =SUMPRODUCT(ISNUMBER(SEARCH("("&C$45&")",'Config Baseline'!$C$2:$C$1017))*ISNUMBER(SEARCH($A47,'Config Baseline'!$K$2:$K$1017))*ISERROR(SEARCH("(",'Config Baseline'!$B$2:$B$1017))) -> 0 | D47: =SUMPRODUCT(ISNUMBER(SEARCH("("&D$45&")",'Config Baseline'!$C$2:$C$1017))*ISNUMBER(SEARCH($A47,'Config Baseline'!$K$2:$K$1017))*ISERROR(SEARCH("(",'Config Baseline'!$B$2:$B$1017))) -> 10 | E47: =SUMPRODUCT(ISNUMBER(SEARCH("("&E$45&")",'Config Baseline'!$C$2:$C$1017))*ISNUMBER(SEARCH($A47,'Config Baseline'!$K$2:$K$1017))*ISERROR(SEARCH("(",'Config Baseline'!$B$2:$B$1017))) -> 6 | F47: =SUMPRODUCT(ISNUMBER(SEARCH("("&F$45&")",'Config Baseline'!$C$2:$C$1017))*ISNUMBER(SEARCH($A47,'Config Baseline'!$K$2:$K$1017))*ISERROR(SEARCH("(",'Config Baseline'!$B$2:$B$1017))) -> 10 | G47: =SUMPRODUCT(ISNUMBER(SEARCH("("&G$45&")",'Config Baseline'!$C$2:$C$1017))*ISNUMBER(SEARCH($A47,'Config Baseline'!$K$2:$K$1017))*ISERROR(SEARCH("(",'Config Baseline'!$B$2:$B$1017))) -> 6 | H47: =SUMPRODUCT(ISNUMBER(SEARCH("("&H$45&")",'Config Baseline'!$C$2:$C$1017))*ISNUMBER(SEARCH($A47,'Config Baseline'!$K$2:$K$1017))*ISERROR(SEARCH("(",'Config Baseline'!$B$2:$B$1017))) -> 10 | I47: =SUMPRODUCT(ISNUMBER(SEARCH("("&I$45&")",'Config Baseline'!$C$2:$C$1017))*ISNUMBER(SEARCH($A47,'Config Baseline'!$K$2:$K$1017))*ISERROR(SEARCH("(",'Config Baseline'!$B$2:$B$1017))) -> 5 | ... U47: =SUMPRODUCT(ISNUMBER(SEARCH("("&U$45&")",'Config Baseline'!$C$2:$C$1017))*ISNUMBER(SEARCH($A47,'Config Baseline'!$K$2:$K$1017))*ISERROR(SEARCH("(",'Config Baseline'!$B$2:$B$1017))) -> 5 | V47: =SUM(B47:U47) -> 115
A48: Identity | B48: =SUMPRODUCT(ISNUMBER(SEARCH("("&B$45&")",'Config Baseline'!$C$2:$C$1017))*ISNUMBER(SEARCH($A48,'Config Baseline'!$K$2:$K$1017))*ISERROR(SEARCH("(",'Config Baseline'!$B$2:$B$1017))) -> 10 | C48: =SUMPRODUCT(ISNUMBER(SEARCH("("&C$45&")",'Config Baseline'!$C$2:$C$1017))*ISNUMBER(SEARCH($A48,'Config Baseline'!$K$2:$K$1017))*ISERROR(SEARCH("(",'Config Baseline'!$B$2:$B$1017))) -> 0 | D48: =SUMPRODUCT(ISNUMBER(SEARCH("("&D$45&")",'Config Baseline'!$C$2:$C$1017))*ISNUMBER(SEARCH($A48,'Config Baseline'!$K$2:$K$1017))*ISERROR(SEARCH("(",'Config Baseline'!$B$2:$B$1017))) -> 0 | E48: =SUMPRODUCT(ISNUMBER(SEARCH("("&E$45&")",'Config Baseline'!$C$2:$C$1017))*ISNUMBER(SEARCH($A48,'Config Baseline'!$K$2:$K$1017))*ISERROR(SEARCH("(",'Config Baseline'!$B$2:$B$1017))) -> 0 | F48: =SUMPRODUCT(ISNUMBER(SEARCH("("&F$45&")",'Config Baseline'!$C$2:$C$1017))*ISNUMBER(SEARCH($A48,'Config Baseline'!$K$2:$K$1017))*ISERROR(SEARCH("(",'Config Baseline'!$B$2:$B$1017))) -> 0 | G48: =SUMPRODUCT(ISNUMBER(SEARCH("("&G$45&")",'Config Baseline'!$C$2:$C$1017))*ISNUMBER(SEARCH($A48,'Config Baseline'!$K$2:$K$1017))*ISERROR(SEARCH("(",'Config Baseline'!$B$2:$B$1017))) -> 0 | H48: =SUMPRODUCT(ISNUMBER(SEARCH("("&H$45&")",'Config Baseline'!$C$2:$C$1017))*ISNUMBER(SEARCH($A48,'Config Baseline'!$K$2:$K$1017))*ISERROR(SEARCH("(",'Config Baseline'!$B$2:$B$1017))) -> 9 | I48: =SUMPRODUCT(ISNUMBER(SEARCH("("&I$45&")",'Config Baseline'!$C$2:$C$1017))*ISNUMBER(SEARCH($A48,'Config Baseline'!$K$2:$K$1017))*ISERROR(SEARCH("(",'Config Baseline'!$B$2:$B$1017))) -> 0 | ... U48: =SUMPRODUCT(ISNUMBER(SEARCH("("&U$45&")",'Config Baseline'!$C$2:$C$1017))*ISNUMBER(SEARCH($A48,'Config Baseline'!$K$2:$K$1017))*ISERROR(SEARCH("(",'Config Baseline'!$B$2:$B$1017))) -> 0 | V48: =SUM(B48:U48) -> 21
A49: Monitoring | B49: =SUMPRODUCT(ISNUMBER(SEARCH("("&B$45&")",'Config Baseline'!$C$2:$C$1017))*ISNUMBER(SEARCH($A49,'Config Baseline'!$K$2:$K$1017))*ISERROR(SEARCH("(",'Config Baseline'!$B$2:$B$1017))) -> 0 | C49: =SUMPRODUCT(ISNUMBER(SEARCH("("&C$45&")",'Config Baseline'!$C$2:$C$1017))*ISNUMBER(SEARCH($A49,'Config Baseline'!$K$2:$K$1017))*ISERROR(SEARCH("(",'Config Baseline'!$B$2:$B$1017))) -> 0 | D49: =SUMPRODUCT(ISNUMBER(SEARCH("("&D$45&")",'Config Baseline'!$C$2:$C$1017))*ISNUMBER(SEARCH($A49,'Config Baseline'!$K$2:$K$1017))*ISERROR(SEARCH("(",'Config Baseline'!$B$2:$B$1017))) -> 12 | E49: =SUMPRODUCT(ISNUMBER(SEARCH("("&E$45&")",'Config Baseline'!$C$2:$C$1017))*ISNUMBER(SEARCH($A49,'Config Baseline'!$K$2:$K$1017))*ISERROR(SEARCH("(",'Config Baseline'!$B$2:$B$1017))) -> 1 | F49: =SUMPRODUCT(ISNUMBER(SEARCH("("&F$45&")",'Config Baseline'!$C$2:$C$1017))*ISNUMBER(SEARCH($A49,'Config Baseline'!$K$2:$K$1017))*ISERROR(SEARCH("(",'Config Baseline'!$B$2:$B$1017))) -> 0 | G49: =SUMPRODUCT(ISNUMBER(SEARCH("("&G$45&")",'Config Baseline'!$C$2:$C$1017))*ISNUMBER(SEARCH($A49,'Config Baseline'!$K$2:$K$1017))*ISERROR(SEARCH("(",'Config Baseline'!$B$2:$B$1017))) -> 0 | H49: =SUMPRODUCT(ISNUMBER(SEARCH("("&H$45&")",'Config Baseline'!$C$2:$C$1017))*ISNUMBER(SEARCH($A49,'Config Baseline'!$K$2:$K$1017))*ISERROR(SEARCH("(",'Config Baseline'!$B$2:$B$1017))) -> 0 | I49: =SUMPRODUCT(ISNUMBER(SEARCH("("&I$45&")",'Config Baseline'!$C$2:$C$1017))*ISNUMBER(SEARCH($A49,'Config Baseline'!$K$2:$K$1017))*ISERROR(SEARCH("(",'Config Baseline'!$B$2:$B$1017))) -> 2 | ... U49: =SUMPRODUCT(ISNUMBER(SEARCH("("&U$45&")",'Config Baseline'!$C$2:$C$1017))*ISNUMBER(SEARCH($A49,'Config Baseline'!$K$2:$K$1017))*ISERROR(SEARCH("(",'Config Baseline'!$B$2:$B$1017))) -> 0 | V49: =SUM(B49:U49) -> 18
A50: Database | B50: =SUMPRODUCT(ISNUMBER(SEARCH("("&B$45&")",'Config Baseline'!$C$2:$C$1017))*ISNUMBER(SEARCH($A50,'Config Baseline'!$K$2:$K$1017))*ISERROR(SEARCH("(",'Config Baseline'!$B$2:$B$1017))) -> 6 | C50: =SUMPRODUCT(ISNUMBER(SEARCH("("&C$45&")",'Config Baseline'!$C$2:$C$1017))*ISNUMBER(SEARCH($A50,'Config Baseline'!$K$2:$K$1017))*ISERROR(SEARCH("(",'Config Baseline'!$B$2:$B$1017))) -> 0 | D50: =SUMPRODUCT(ISNUMBER(SEARCH("("&D$45&")",'Config Baseline'!$C$2:$C$1017))*ISNUMBER(SEARCH($A50,'Config Baseline'!$K$2:$K$1017))*ISERROR(SEARCH("(",'Config Baseline'!$B$2:$B$1017))) -> 0 | E50: =SUMPRODUCT(ISNUMBER(SEARCH("("&E$45&")",'Config Baseline'!$C$2:$C$1017))*ISNUMBER(SEARCH($A50,'Config Baseline'!$K$2:$K$1017))*ISERROR(SEARCH("(",'Config Baseline'!$B$2:$B$1017))) -> 0 | F50: =SUMPRODUCT(ISNUMBER(SEARCH("("&F$45&")",'Config Baseline'!$C$2:$C$1017))*ISNUMBER(SEARCH($A50,'Config Baseline'!$K$2:$K$1017))*ISERROR(SEARCH("(",'Config Baseline'!$B$2:$B$1017))) -> 3 | G50: =SUMPRODUCT(ISNUMBER(SEARCH("("&G$45&")",'Config Baseline'!$C$2:$C$1017))*ISNUMBER(SEARCH($A50,'Config Baseline'!$K$2:$K$1017))*ISERROR(SEARCH("(",'Config Baseline'!$B$2:$B$1017))) -> 2 | H50: =SUMPRODUCT(ISNUMBER(SEARCH("("&H$45&")",'Config Baseline'!$C$2:$C$1017))*ISNUMBER(SEARCH($A50,'Config Baseline'!$K$2:$K$1017))*ISERROR(SEARCH("(",'Config Baseline'!$B$2:$B$1017))) -> 1 | I50: =SUMPRODUCT(ISNUMBER(SEARCH("("&I$45&")",'Config Baseline'!$C$2:$C$1017))*ISNUMBER(SEARCH($A50,'Config Baseline'!$K$2:$K$1017))*ISERROR(SEARCH("(",'Config Baseline'!$B$2:$B$1017))) -> 0 | ... U50: =SUMPRODUCT(ISNUMBER(SEARCH("("&U$45&")",'Config Baseline'!$C$2:$C$1017))*ISNUMBER(SEARCH($A50,'Config Baseline'!$K$2:$K$1017))*ISERROR(SEARCH("(",'Config Baseline'!$B$2:$B$1017))) -> 0 | V50: =SUM(B50:U50) -> 19
A51: Application | B51: =SUMPRODUCT(ISNUMBER(SEARCH("("&B$45&")",'Config Baseline'!$C$2:$C$1017))*ISNUMBER(SEARCH($A51,'Config Baseline'!$K$2:$K$1017))*ISERROR(SEARCH("(",'Config Baseline'!$B$2:$B$1017))) -> 16 | C51: =SUMPRODUCT(ISNUMBER(SEARCH("("&C$45&")",'Config Baseline'!$C$2:$C$1017))*ISNUMBER(SEARCH($A51,'Config Baseline'!$K$2:$K$1017))*ISERROR(SEARCH("(",'Config Baseline'!$B$2:$B$1017))) -> 0 | D51: =SUMPRODUCT(ISNUMBER(SEARCH("("&D$45&")",'Config Baseline'!$C$2:$C$1017))*ISNUMBER(SEARCH($A51,'Config Baseline'!$K$2:$K$1017))*ISERROR(SEARCH("(",'Config Baseline'!$B$2:$B$1017))) -> 4 | E51: =SUMPRODUCT(ISNUMBER(SEARCH("("&E$45&")",'Config Baseline'!$C$2:$C$1017))*ISNUMBER(SEARCH($A51,'Config Baseline'!$K$2:$K$1017))*ISERROR(SEARCH("(",'Config Baseline'!$B$2:$B$1017))) -> 1 | F51: =SUMPRODUCT(ISNUMBER(SEARCH("("&F$45&")",'Config Baseline'!$C$2:$C$1017))*ISNUMBER(SEARCH($A51,'Config Baseline'!$K$2:$K$1017))*ISERROR(SEARCH("(",'Config Baseline'!$B$2:$B$1017))) -> 12 | G51: =SUMPRODUCT(ISNUMBER(SEARCH("("&G$45&")",'Config Baseline'!$C$2:$C$1017))*ISNUMBER(SEARCH($A51,'Config Baseline'!$K$2:$K$1017))*ISERROR(SEARCH("(",'Config Baseline'!$B$2:$B$1017))) -> 5 | H51: =SUMPRODUCT(ISNUMBER(SEARCH("("&H$45&")",'Config Baseline'!$C$2:$C$1017))*ISNUMBER(SEARCH($A51,'Config Baseline'!$K$2:$K$1017))*ISERROR(SEARCH("(",'Config Baseline'!$B$2:$B$1017))) -> 8 | I51: =SUMPRODUCT(ISNUMBER(SEARCH("("&I$45&")",'Config Baseline'!$C$2:$C$1017))*ISNUMBER(SEARCH($A51,'Config Baseline'!$K$2:$K$1017))*ISERROR(SEARCH("(",'Config Baseline'!$B$2:$B$1017))) -> 0 | ... U51: =SUMPRODUCT(ISNUMBER(SEARCH("("&U$45&")",'Config Baseline'!$C$2:$C$1017))*ISNUMBER(SEARCH($A51,'Config Baseline'!$K$2:$K$1017))*ISERROR(SEARCH("(",'Config Baseline'!$B$2:$B$1017))) -> 0 | V51: =SUM(B51:U51) -> 113
A52: Backup | B52: =SUMPRODUCT(ISNUMBER(SEARCH("("&B$45&")",'Config Baseline'!$C$2:$C$1017))*ISNUMBER(SEARCH($A52,'Config Baseline'!$K$2:$K$1017))*ISERROR(SEARCH("(",'Config Baseline'!$B$2:$B$1017))) -> 0 | C52: =SUMPRODUCT(ISNUMBER(SEARCH("("&C$45&")",'Config Baseline'!$C$2:$C$1017))*ISNUMBER(SEARCH($A52,'Config Baseline'!$K$2:$K$1017))*ISERROR(SEARCH("(",'Config Baseline'!$B$2:$B$1017))) -> 0 | D52: =SUMPRODUCT(ISNUMBER(SEARCH("("&D$45&")",'Config Baseline'!$C$2:$C$1017))*ISNUMBER(SEARCH($A52,'Config Baseline'!$K$2:$K$1017))*ISERROR(SEARCH("(",'Config Baseline'!$B$2:$B$1017))) -> 0 | E52: =SUMPRODUCT(ISNUMBER(SEARCH("("&E$45&")",'Config Baseline'!$C$2:$C$1017))*ISNUMBER(SEARCH($A52,'Config Baseline'!$K$2:$K$1017))*ISERROR(SEARCH("(",'Config Baseline'!$B$2:$B$1017))) -> 0 | F52: =SUMPRODUCT(ISNUMBER(SEARCH("("&F$45&")",'Config Baseline'!$C$2:$C$1017))*ISNUMBER(SEARCH($A52,'Config Baseline'!$K$2:$K$1017))*ISERROR(SEARCH("(",'Config Baseline'!$B$2:$B$1017))) -> 0 | G52: =SUMPRODUCT(ISNUMBER(SEARCH("("&G$45&")",'Config Baseline'!$C$2:$C$1017))*ISNUMBER(SEARCH($A52,'Config Baseline'!$K$2:$K$1017))*ISERROR(SEARCH("(",'Config Baseline'!$B$2:$B$1017))) -> 6 | H52: =SUMPRODUCT(ISNUMBER(SEARCH("("&H$45&")",'Config Baseline'!$C$2:$C$1017))*ISNUMBER(SEARCH($A52,'Config Baseline'!$K$2:$K$1017))*ISERROR(SEARCH("(",'Config Baseline'!$B$2:$B$1017))) -> 0 | I52: =SUMPRODUCT(ISNUMBER(SEARCH("("&I$45&")",'Config Baseline'!$C$2:$C$1017))*ISNUMBER(SEARCH($A52,'Config Baseline'!$K$2:$K$1017))*ISERROR(SEARCH("(",'Config Baseline'!$B$2:$B$1017))) -> 0 | ... U52: =SUMPRODUCT(ISNUMBER(SEARCH("("&U$45&")",'Config Baseline'!$C$2:$C$1017))*ISNUMBER(SEARCH($A52,'Config Baseline'!$K$2:$K$1017))*ISERROR(SEARCH("(",'Config Baseline'!$B$2:$B$1017))) -> 0 | V52: =SUM(B52:U52) -> 6
A53: Governance | B53: =SUMPRODUCT(ISNUMBER(SEARCH("("&B$45&")",'Config Baseline'!$C$2:$C$1017))*ISNUMBER(SEARCH($A53,'Config Baseline'!$K$2:$K$1017))*ISERROR(SEARCH("(",'Config Baseline'!$B$2:$B$1017))) -> 1 | C53: =SUMPRODUCT(ISNUMBER(SEARCH("("&C$45&")",'Config Baseline'!$C$2:$C$1017))*ISNUMBER(SEARCH($A53,'Config Baseline'!$K$2:$K$1017))*ISERROR(SEARCH("(",'Config Baseline'!$B$2:$B$1017))) -> 5 | D53: =SUMPRODUCT(ISNUMBER(SEARCH("("&D$45&")",'Config Baseline'!$C$2:$C$1017))*ISNUMBER(SEARCH($A53,'Config Baseline'!$K$2:$K$1017))*ISERROR(SEARCH("(",'Config Baseline'!$B$2:$B$1017))) -> 2 | E53: =SUMPRODUCT(ISNUMBER(SEARCH("("&E$45&")",'Config Baseline'!$C$2:$C$1017))*ISNUMBER(SEARCH($A53,'Config Baseline'!$K$2:$K$1017))*ISERROR(SEARCH("(",'Config Baseline'!$B$2:$B$1017))) -> 5 | F53: =SUMPRODUCT(ISNUMBER(SEARCH("("&F$45&")",'Config Baseline'!$C$2:$C$1017))*ISNUMBER(SEARCH($A53,'Config Baseline'!$K$2:$K$1017))*ISERROR(SEARCH("(",'Config Baseline'!$B$2:$B$1017))) -> 1 | G53: =SUMPRODUCT(ISNUMBER(SEARCH("("&G$45&")",'Config Baseline'!$C$2:$C$1017))*ISNUMBER(SEARCH($A53,'Config Baseline'!$K$2:$K$1017))*ISERROR(SEARCH("(",'Config Baseline'!$B$2:$B$1017))) -> 1 | H53: =SUMPRODUCT(ISNUMBER(SEARCH("("&H$45&")",'Config Baseline'!$C$2:$C$1017))*ISNUMBER(SEARCH($A53,'Config Baseline'!$K$2:$K$1017))*ISERROR(SEARCH("(",'Config Baseline'!$B$2:$B$1017))) -> 1 | I53: =SUMPRODUCT(ISNUMBER(SEARCH("("&I$45&")",'Config Baseline'!$C$2:$C$1017))*ISNUMBER(SEARCH($A53,'Config Baseline'!$K$2:$K$1017))*ISERROR(SEARCH("(",'Config Baseline'!$B$2:$B$1017))) -> 8 | ... U53: =SUMPRODUCT(ISNUMBER(SEARCH("("&U$45&")",'Config Baseline'!$C$2:$C$1017))*ISNUMBER(SEARCH($A53,'Config Baseline'!$K$2:$K$1017))*ISERROR(SEARCH("(",'Config Baseline'!$B$2:$B$1017))) -> 1 | V53: =SUM(B53:U53) -> 91
A54: Physical | B54: =SUMPRODUCT(ISNUMBER(SEARCH("("&B$45&")",'Config Baseline'!$C$2:$C$1017))*ISNUMBER(SEARCH($A54,'Config Baseline'!$K$2:$K$1017))*ISERROR(SEARCH("(",'Config Baseline'!$B$2:$B$1017))) -> 0 | C54: =SUMPRODUCT(ISNUMBER(SEARCH("("&C$45&")",'Config Baseline'!$C$2:$C$1017))*ISNUMBER(SEARCH($A54,'Config Baseline'!$K$2:$K$1017))*ISERROR(SEARCH("(",'Config Baseline'!$B$2:$B$1017))) -> 0 | D54: =SUMPRODUCT(ISNUMBER(SEARCH("("&D$45&")",'Config Baseline'!$C$2:$C$1017))*ISNUMBER(SEARCH($A54,'Config Baseline'!$K$2:$K$1017))*ISERROR(SEARCH("(",'Config Baseline'!$B$2:$B$1017))) -> 0 | E54: =SUMPRODUCT(ISNUMBER(SEARCH("("&E$45&")",'Config Baseline'!$C$2:$C$1017))*ISNUMBER(SEARCH($A54,'Config Baseline'!$K$2:$K$1017))*ISERROR(SEARCH("(",'Config Baseline'!$B$2:$B$1017))) -> 0 | F54: =SUMPRODUCT(ISNUMBER(SEARCH("("&F$45&")",'Config Baseline'!$C$2:$C$1017))*ISNUMBER(SEARCH($A54,'Config Baseline'!$K$2:$K$1017))*ISERROR(SEARCH("(",'Config Baseline'!$B$2:$B$1017))) -> 0 | G54: =SUMPRODUCT(ISNUMBER(SEARCH("("&G$45&")",'Config Baseline'!$C$2:$C$1017))*ISNUMBER(SEARCH($A54,'Config Baseline'!$K$2:$K$1017))*ISERROR(SEARCH("(",'Config Baseline'!$B$2:$B$1017))) -> 0 | H54: =SUMPRODUCT(ISNUMBER(SEARCH("("&H$45&")",'Config Baseline'!$C$2:$C$1017))*ISNUMBER(SEARCH($A54,'Config Baseline'!$K$2:$K$1017))*ISERROR(SEARCH("(",'Config Baseline'!$B$2:$B$1017))) -> 0 | I54: =SUMPRODUCT(ISNUMBER(SEARCH("("&I$45&")",'Config Baseline'!$C$2:$C$1017))*ISNUMBER(SEARCH($A54,'Config Baseline'!$K$2:$K$1017))*ISERROR(SEARCH("(",'Config Baseline'!$B$2:$B$1017))) -> 0 | ... U54: =SUMPRODUCT(ISNUMBER(SEARCH("("&U$45&")",'Config Baseline'!$C$2:$C$1017))*ISNUMBER(SEARCH($A54,'Config Baseline'!$K$2:$K$1017))*ISERROR(SEARCH("(",'Config Baseline'!$B$2:$B$1017))) -> 3 | V54: =SUM(B54:U54) -> 38
A55: Third Party | B55: =SUMPRODUCT(ISNUMBER(SEARCH("("&B$45&")",'Config Baseline'!$C$2:$C$1017))*ISNUMBER(SEARCH($A55,'Config Baseline'!$K$2:$K$1017))*ISERROR(SEARCH("(",'Config Baseline'!$B$2:$B$1017))) -> 0 | C55: =SUMPRODUCT(ISNUMBER(SEARCH("("&C$45&")",'Config Baseline'!$C$2:$C$1017))*ISNUMBER(SEARCH($A55,'Config Baseline'!$K$2:$K$1017))*ISERROR(SEARCH("(",'Config Baseline'!$B$2:$B$1017))) -> 0 | D55: =SUMPRODUCT(ISNUMBER(SEARCH("("&D$45&")",'Config Baseline'!$C$2:$C$1017))*ISNUMBER(SEARCH($A55,'Config Baseline'!$K$2:$K$1017))*ISERROR(SEARCH("(",'Config Baseline'!$B$2:$B$1017))) -> 0 | E55: =SUMPRODUCT(ISNUMBER(SEARCH("("&E$45&")",'Config Baseline'!$C$2:$C$1017))*ISNUMBER(SEARCH($A55,'Config Baseline'!$K$2:$K$1017))*ISERROR(SEARCH("(",'Config Baseline'!$B$2:$B$1017))) -> 0 | F55: =SUMPRODUCT(ISNUMBER(SEARCH("("&F$45&")",'Config Baseline'!$C$2:$C$1017))*ISNUMBER(SEARCH($A55,'Config Baseline'!$K$2:$K$1017))*ISERROR(SEARCH("(",'Config Baseline'!$B$2:$B$1017))) -> 0 | G55: =SUMPRODUCT(ISNUMBER(SEARCH("("&G$45&")",'Config Baseline'!$C$2:$C$1017))*ISNUMBER(SEARCH($A55,'Config Baseline'!$K$2:$K$1017))*ISERROR(SEARCH("(",'Config Baseline'!$B$2:$B$1017))) -> 0 | H55: =SUMPRODUCT(ISNUMBER(SEARCH("("&H$45&")",'Config Baseline'!$C$2:$C$1017))*ISNUMBER(SEARCH($A55,'Config Baseline'!$K$2:$K$1017))*ISERROR(SEARCH("(",'Config Baseline'!$B$2:$B$1017))) -> 0 | I55: =SUMPRODUCT(ISNUMBER(SEARCH("("&I$45&")",'Config Baseline'!$C$2:$C$1017))*ISNUMBER(SEARCH($A55,'Config Baseline'!$K$2:$K$1017))*ISERROR(SEARCH("(",'Config Baseline'!$B$2:$B$1017))) -> 0 | ... U55: =SUMPRODUCT(ISNUMBER(SEARCH("("&U$45&")",'Config Baseline'!$C$2:$C$1017))*ISNUMBER(SEARCH($A55,'Config Baseline'!$K$2:$K$1017))*ISERROR(SEARCH("(",'Config Baseline'!$B$2:$B$1017))) -> 9 | V55: =SUM(B55:U55) -> 10

Sheet Baseline Summary
A1: Configuration Baseline Summary - control families and control IDs used by each topic
A2: How to read: "Control families" = number of NIST SP 800-53 families (AC, AU, CA ...) that have at least one row in the topic baseline sheet. "Control IDs" = number of rows (base controls plus enhancements) in that sheet. All values are formulas that read the topic sheets. "Tagged in master" comes from Domain Summary (every control tagged to the domain in Config Baseline) so you can see how much of it each baseline keeps. Network and Cloud are the existing sheets; the other eight topics use the same core-item approach (only rows tagged to that domain, similar controls consolidated).
A4: Topic (IT Domain) | B4: Baseline sheet | C4: Control families used | D4: Control IDs used | E4: Level 1 | F4: Level 2 | G4: Level 3 | H4: Families tagged in master | I4: IDs tagged in master | J4: IDs used as % of tagged
A5: Network | B5: Network Config Baseline | C5: =COUNTIF('Network Config Baseline'!$B$15:$B$22,">0") -> 8 | D5: =COUNTA('Network Config Baseline'!$B$26:$B$95) -> 70 | E5: =COUNTIF('Network Config Baseline'!$I$26:$I$95,"Level 1*") -> 43 | F5: =COUNTIF('Network Config Baseline'!$I$26:$I$95,"Level 2*") -> 27 | G5: =COUNTIF('Network Config Baseline'!$I$26:$I$95,"Level 3*") -> 0 | H5: ='Domain Summary'!B4 -> 14 | I5: ='Domain Summary'!D4 -> 413 | J5: =IF(I5=0,0,D5/I5) -> 0.16949153
A6: Cloud | B6: Cloud Config Baseline | C6: =COUNTIF('Cloud Config Baseline'!$B$16:$B$26,">0") -> 11 | D6: =COUNTA('Cloud Config Baseline'!$B$30:$B$313) -> 284 | E6: =COUNTIF('Cloud Config Baseline'!$I$30:$I$313,"Level 1*") -> 69 | F6: =COUNTIF('Cloud Config Baseline'!$I$30:$I$313,"Level 2*") -> 121 | G6: =COUNTIF('Cloud Config Baseline'!$I$30:$I$313,"Level 3*") -> 94 | H6: ='Domain Summary'!B5 -> 15 | I6: ='Domain Summary'!D5 -> 596 | J6: =IF(I6=0,0,D6/I6) -> 0.47651007
A7: Identity | B7: Identity Config Baseline | C7: =COUNTIF('Identity Config Baseline'!$B$15:$B$17,">0") -> 3 | D7: =COUNTA('Identity Config Baseline'!$B$21:$B$68) -> 48 | E7: =COUNTIF('Identity Config Baseline'!$I$21:$I$68,"Level 1*") -> 14 | F7: =COUNTIF('Identity Config Baseline'!$I$21:$I$68,"Level 2*") -> 34 | G7: =COUNTIF('Identity Config Baseline'!$I$21:$I$68,"Level 3*") -> 0 | H7: ='Domain Summary'!B6 -> 3 | I7: ='Domain Summary'!D6 -> 119 | J7: =IF(I7=0,0,D7/I7) -> 0.40336134
A8: Monitoring | B8: Monitoring Config Baseline | C8: =COUNTIF('Monitoring Config Baseline'!$B$15:$B$19,">0") -> 5 | D8: =COUNTA('Monitoring Config Baseline'!$B$23:$B$58) -> 36 | E8: =COUNTIF('Monitoring Config Baseline'!$I$23:$I$58,"Level 1*") -> 14 | F8: =COUNTIF('Monitoring Config Baseline'!$I$23:$I$58,"Level 2*") -> 22 | G8: =COUNTIF('Monitoring Config Baseline'!$I$23:$I$58,"Level 3*") -> 0 | H8: ='Domain Summary'!B7 -> 6 | I8: ='Domain Summary'!D7 -> 100 | J8: =IF(I8=0,0,D8/I8) -> 0.36
A9: Database | B9: Database Config Baseline | C9: =COUNTIF('Database Config Baseline'!$B$15:$B$21,">0") -> 7 | D9: =COUNTA('Database Config Baseline'!$B$25:$B$66) -> 42 | E9: =COUNTIF('Database Config Baseline'!$I$25:$I$66,"Level 1*") -> 21 | F9: =COUNTIF('Database Config Baseline'!$I$25:$I$66,"Level 2*") -> 21 | G9: =COUNTIF('Database Config Baseline'!$I$25:$I$66,"Level 3*") -> 0 | H9: ='Domain Summary'!B8 -> 7 | I9: ='Domain Summary'!D8 -> 115 | J9: =IF(I9=0,0,D9/I9) -> 0.36521739
A10: Application | B10: Application Config Baseline | C10: =COUNTIF('Application Config Baseline'!$B$15:$B$24,">0") -> 10 | D10: =COUNTA('Application Config Baseline'!$B$28:$B$117) -> 90 | E10: =COUNTIF('Application Config Baseline'!$I$28:$I$117,"Level 1*") -> 39 | F10: =COUNTIF('Application Config Baseline'!$I$28:$I$117,"Level 2*") -> 34 | G10: =COUNTIF('Application Config Baseline'!$I$28:$I$117,"Level 3*") -> 17 | H10: ='Domain Summary'!B9 -> 12 | I10: ='Domain Summary'!D9 -> 484 | J10: =IF(I10=0,0,D10/I10) -> 0.18595041
A11: Backup | B11: Backup Config Baseline | C11: =COUNTIF('Backup Config Baseline'!$B$15:$B$15,">0") -> 1 | D11: =COUNTA('Backup Config Baseline'!$B$19:$B$33) -> 15 | E11: =COUNTIF('Backup Config Baseline'!$I$19:$I$33,"Level 1*") -> 3 | F11: =COUNTIF('Backup Config Baseline'!$I$19:$I$33,"Level 2*") -> 7 | G11: =COUNTIF('Backup Config Baseline'!$I$19:$I$33,"Level 3*") -> 5 | H11: ='Domain Summary'!B10 -> 1 | I11: ='Domain Summary'!D10 -> 33 | J11: =IF(I11=0,0,D11/I11) -> 0.45454545
A12: Governance | B12: Governance Config Baseline | C12: =COUNTIF('Governance Config Baseline'!$B$15:$B$33,">0") -> 19 | D12: =COUNTA('Governance Config Baseline'!$B$37:$B$78) -> 42 | E12: =COUNTIF('Governance Config Baseline'!$I$37:$I$78,"Level 1*") -> 0 | F12: =COUNTIF('Governance Config Baseline'!$I$37:$I$78,"Level 2*") -> 3 | G12: =COUNTIF('Governance Config Baseline'!$I$37:$I$78,"Level 3*") -> 39 | H12: ='Domain Summary'!B11 -> 19 | I12: ='Domain Summary'!D11 -> 179 | J12: =IF(I12=0,0,D12/I12) -> 0.23463687
A13: Physical | B13: Physical Config Baseline | C13: =COUNTIF('Physical Config Baseline'!$B$15:$B$18,">0") -> 4 | D13: =COUNTA('Physical Config Baseline'!$B$22:$B$47) -> 26 | E13: =COUNTIF('Physical Config Baseline'!$I$22:$I$47,"Level 1*") -> 3 | F13: =COUNTIF('Physical Config Baseline'!$I$22:$I$47,"Level 2*") -> 7 | G13: =COUNTIF('Physical Config Baseline'!$I$22:$I$47,"Level 3*") -> 16 | H13: ='Domain Summary'!B12 -> 4 | I13: ='Domain Summary'!D12 -> 103 | J13: =IF(I13=0,0,D13/I13) -> 0.25242718
A14: Third Party | B14: Third Party Config Baseline | C14: =COUNTIF('Third Party Config Baseline'!$B$15:$B$16,">0") -> 2 | D14: =COUNTA('Third Party Config Baseline'!$B$20:$B$33) -> 14 | E14: =COUNTIF('Third Party Config Baseline'!$I$20:$I$33,"Level 1*") -> 0 | F14: =COUNTIF('Third Party Config Baseline'!$I$20:$I$33,"Level 2*") -> 3 | G14: =COUNTIF('Third Party Config Baseline'!$I$20:$I$33,"Level 3*") -> 11 | H14: ='Domain Summary'!B13 -> 2 | I14: ='Domain Summary'!D13 -> 32 | J14: =IF(I14=0,0,D14/I14) -> 0.4375
A15: Total (topics overlap, so IDs add up) | D15: =SUM(D5:D14) -> 667 | E15: =SUM(E5:E14) -> 206 | F15: =SUM(F5:F14) -> 279 | G15: =SUM(G5:G14) -> 182 | I15: =SUM(I5:I14) -> 2174 | J15: =IF(I15=0,0,D15/I15) -> 0.30680773
A16: Unique control IDs across all topic sheets | D16: =SUMPRODUCT(1/COUNTIF(Helper!$A$2:$A$668,Helper!$A$2:$A$668)) -> 402
A17: Note: a control ID can belong to several topics (for example AC-06 is in Identity, Database, Application and Cloud), so the Total row counts it once per topic and the row above counts it once overall.

Sheet Cloud Config Baseline
A1: Cloud Configuration Baseline (NIST SP 800-53 Rev. 5 - core configuration items)
A2: Purpose: this sheet turns the NIST SP 800-53 Rev. 5 controls into the Cloud Configuration Baseline. It lists the settings that administrators must configure, implement, install or enable in a cloud environment (IaaS, PaaS and SaaS tenant configuration) so that every account, subscription or project meets the same security baseline.
A3: Scope (v3.1 update): the baseline covers the 11 families AC, AU, CA, CM, CP, IA, IR, RA, SA, SC, SI and now contains every control ID that Bitdefender GravityZone evaluated for this organisation (126 IDs, all present) plus the control IDs of the Cloud Baseline Groups sheet (164 representative IDs; 4 of them - AC-12(2), AC-12(3), AC-19(4), SA-15(13) - and SC-7(16) from Bitdefender are not in the Config Baseline master and were added with analyst-assigned Level and CSF mapping). Governance and process controls (policy -1 controls, training, testing, assessment) are now listed as Level 3 rows so the baseline can be compared one-to-one with those files.
A4: Selection principle: original rows are kept unchanged. Rows added from Bitdefender and Cloud Baseline Groups are marked in column M (Source of Row). Column K gives the Cloud Baseline Groups domain (9 domains), column L the Bitdefender result (PASS / FAIL / NOT EVALUATED) and column N the related control IDs that the Groups sheet folds into the same practice. Use the Cloud Coverage Check sheet to verify coverage.
A5: Supply chain (SR): SR controls are contractual and process based (supplier assessment, notification agreements) with no direct cloud setting, so they are not listed. The technical side of cloud provider risk is covered by SA-9, SA-9(5) and SA-9(6).
A6: Examples name AWS, Azure and Google Cloud features and are vendor-neutral guidance; adapt them to the platforms in use. Level is taken from the Config Baseline sheet (Level 1 = mandatory, Level 3 = lowest impact); for the five IDs missing in that sheet the Level is analyst-assigned. Text for added rows is analyst-written guidance and should be validated by the platform owners.
A8: Action Type legend
A9: Configure = set a parameter, policy or rule on an existing platform/service.
A10: Implement = build or deploy a mechanism, template, automation or architecture pattern.
A11: Install = install or onboard a tool, agent or scanner.
A12: Enable = turn on a feature, log source or detection service that is off by default.
A14: Coverage by control family
A15: Family | B15: Items | C15: Level 1 | D15: Level 2 | E15: Level 3 | F15: Configuration focus
A16: Access Control (AC) | B16: =COUNTIF($C$30:$C$313,$A16) -> 55 | C16: =COUNTIFS($C$30:$C$313,$A16,$I$30:$I$313,"Level 1*") -> 18 | D16: =COUNTIFS($C$30:$C$313,$A16,$I$30:$I$313,"Level 2*") -> 28 | E16: =COUNTIFS($C$30:$C$313,$A16,$I$30:$I$313,"Level 3*") -> 9 | F16: Identity lifecycle, least privilege, root/admin protection, public-access blocking, private management access, cross-account trust.
A17: Audit and Accountability (AU) | B17: =COUNTIF($C$30:$C$313,$A17) -> 29 | C17: =COUNTIFS($C$30:$C$313,$A17,$I$30:$I$313,"Level 1*") -> 10 | D17: =COUNTIFS($C$30:$C$313,$A17,$I$30:$I$313,"Level 2*") -> 10 | E17: =COUNTIFS($C$30:$C$313,$A17,$I$30:$I$313,"Level 3*") -> 9 | F17: Organization-wide audit logging, immutable central log storage, alerts on logging failure, SIEM correlation, retention and time sync.
A18: Assessment, Authorization, and Monitoring (CA) | B18: =COUNTIF($C$30:$C$313,$A18) -> 9 | C18: =COUNTIFS($C$30:$C$313,$A18,$I$30:$I$313,"Level 1*") -> 0 | D18: =COUNTIFS($C$30:$C$313,$A18,$I$30:$I$313,"Level 2*") -> 3 | E18: =COUNTIFS($C$30:$C$313,$A18,$I$30:$I$313,"Level 3*") -> 6 | F18: Secure connectivity to on-premises and partners, continuous posture assessment (CSPM), documented internal flows.
A19: Configuration Management (CM) | B19: =COUNTIF($C$30:$C$313,$A19) -> 19 | C19: =COUNTIFS($C$30:$C$313,$A19,$I$30:$I$313,"Level 1*") -> 7 | D19: =COUNTIFS($C$30:$C$313,$A19,$I$30:$I$313,"Level 2*") -> 10 | E19: =COUNTIFS($C$30:$C$313,$A19,$I$30:$I$313,"Level 3*") -> 2 | F19: Golden images and IaC, pipeline-only change, CIS baseline enforcement with auto-remediation, allowed regions/services, asset inventory, signed artifacts.
A20: Contingency Planning (CP) | B20: =COUNTIF($C$30:$C$313,$A20) -> 15 | C20: =COUNTIFS($C$30:$C$313,$A20,$I$30:$I$313,"Level 1*") -> 2 | D20: =COUNTIFS($C$30:$C$313,$A20,$I$30:$I$313,"Level 2*") -> 5 | E20: =COUNTIFS($C$30:$C$313,$A20,$I$30:$I$313,"Level 3*") -> 8 | F20: Cross-region replication, multi-AZ and DR failover, scheduled and immutable encrypted backups, automated restore.
A21: Identification and Authentication (IA) | B21: =COUNTIF($C$30:$C$313,$A21) -> 17 | C21: =COUNTIFS($C$30:$C$313,$A21,$I$30:$I$313,"Level 1*") -> 5 | D21: =COUNTIFS($C$30:$C$313,$A21,$I$30:$I$313,"Level 2*") -> 12 | E21: =COUNTIFS($C$30:$C$313,$A21,$I$30:$I$313,"Level 3*") -> 0 | F21: Unique identities, phishing-resistant MFA, SSO, secret rotation and no embedded secrets, workload identities, token validation.
A22: Incident Response (IR) | B22: =COUNTIF($C$30:$C$313,$A22) -> 16 | C22: =COUNTIFS($C$30:$C$313,$A22,$I$30:$I$313,"Level 1*") -> 0 | D22: =COUNTIFS($C$30:$C$313,$A22,$I$30:$I$313,"Level 2*") -> 1 | E22: =COUNTIFS($C$30:$C$313,$A22,$I$30:$I$313,"Level 3*") -> 15 | F22: Automated containment playbooks, alert routing to tickets and notification channels.
A23: Risk Assessment (RA) | B23: =COUNTIF($C$30:$C$313,$A23) -> 12 | C23: =COUNTIFS($C$30:$C$313,$A23,$I$30:$I$313,"Level 1*") -> 3 | D23: =COUNTIFS($C$30:$C$313,$A23,$I$30:$I$313,"Level 2*") -> 2 | E23: =COUNTIFS($C$30:$C$313,$A23,$I$30:$I$313,"Level 3*") -> 7 | F23: Vulnerability scanning for VMs, containers and images; authenticated scanning; hunting telemetry.
A24: System and Services Acquisition (SA) | B24: =COUNTIF($C$30:$C$313,$A24) -> 28 | C24: =COUNTIFS($C$30:$C$313,$A24,$I$30:$I$313,"Level 1*") -> 0 | D24: =COUNTIFS($C$30:$C$313,$A24,$I$30:$I$313,"Level 2*") -> 4 | E24: =COUNTIFS($C$30:$C$313,$A24,$I$30:$I$313,"Level 3*") -> 24 | F24: Shared-responsibility service settings, data residency, customer-managed keys, secure pipeline and scanning, end-of-life blocking.
A25: System and Communications Protection (SC) | B25: =COUNTIF($C$30:$C$313,$A25) -> 46 | C25: =COUNTIFS($C$30:$C$313,$A25,$I$30:$I$313,"Level 1*") -> 13 | D25: =COUNTIFS($C$30:$C$313,$A25,$I$30:$I$313,"Level 2*") -> 26 | E25: =COUNTIFS($C$30:$C$313,$A25,$I$30:$I$313,"Level 3*") -> 7 | F25: DDoS/WAF, private subnets, default-deny and egress control, TLS, KMS key management, encryption at rest, DNSSEC, account isolation.
A26: System and Information Integrity (SI) | B26: =COUNTIF($C$30:$C$313,$A26) -> 38 | C26: =COUNTIFS($C$30:$C$313,$A26,$I$30:$I$313,"Level 1*") -> 11 | D26: =COUNTIFS($C$30:$C$313,$A26,$I$30:$I$313,"Level 2*") -> 20 | E26: =COUNTIFS($C$30:$C$313,$A26,$I$30:$I$313,"Level 3*") -> 7 | F26: Automated patching, EDR/malware scanning, managed threat detection, flow logs, integrity monitoring, secure boot, WAF managed rules.
A27: Total | B27: =SUM(B16:B26) -> 284 | C27: =SUM(C16:C26) -> 69 | D27: =SUM(D16:D26) -> 121 | E27: =SUM(E16:E26) -> 94
A29: Control ID New | B29: Control ID | C29: Control Family | D29: Control Name | E29: Action Type | F29: Baseline Setting to Configure | G29: Implementation Example | H29: Verification / Evidence | I29: Level | J29: CSF 2.0 Subcategory ID | K29: Cloud Baseline Domain (from Cloud Baseline Groups) | L29: Bitdefender Check (All Accounts) | M29: Source of Row | N29: Related Control IDs (Cloud Baseline Groups)
A30: ESBIT-AC-01 | B30: AC-01 | C30: Access Control (AC) | D30: Policy and Procedures | E30: Implement | F30: Publish an approved cloud access control policy covering account types, least privilege, remote access and review cycle; review it at least annually | G30: Policy in the GRC tool, linked to AWS Organizations SCPs, Azure Policy initiatives and GCP Organization Policies | H30: Signed policy with review date; policy-to-control mapping | I30: Level 3 - Low | J30: GV.PO-01 | K30: 1. Identity & Access Management (IAM Baseline) | L30: NOT EVALUATED | M30: Added - Groups | N30: AC-1, IA-1
A31: ESBIT-AC-02 | B31: AC-02 | C31: Access Control (AC) | D31: Account Management | E31: Configure | F31: Manage all human, service and break-glass identities in one central directory; require an owner, approval and expiry for each account; remove unused accounts and access keys | G31: AWS IAM Identity Center, Azure Entra ID, Google Cloud Identity; SCIM provisioning for joiner-mover-leaver | H31: IAM credential report; Entra access review results | I31: Level 1 - High | J31: PR.AA-01 | K31: 1. Identity & Access Management (IAM Baseline) | L31: FAIL | M31: Original v3 | N31: AC-2
A32: ESBIT-AC-02(01) | B32: AC-02(01) | C32: Access Control (AC) | D32: Account Management | Automated System Account Management | E32: Implement | F32: Automate account creation, modification, disabling and removal for cloud users and service accounts from the authoritative HR/IdP source | G32: SCIM provisioning to AWS IAM Identity Center, Entra ID lifecycle workflows, Google Cloud Directory Sync | H32: Provisioning logs; no accounts outside the IdP | I32: Level 2 - Medium | J32: PR.AA-01 | K32: 1. Identity & Access Management (IAM Baseline) | L32: FAIL | M32: Added - Bitdefender + Groups | N32: AC-2(1), AC-2(4), AC-2(8)
A33: ESBIT-AC-02(02) | B33: AC-02(02) | C33: Access Control (AC) | D33: Account Management | Automated Temporary and Emergency Account Management | E33: Configure | F33: Create temporary and emergency accounts only with an expiry time and auto-disable them when it lapses; alert on every use | G33: Entra PIM time-bound eligible roles, AWS IAM roles with session duration and expiring credentials, GCP IAM Conditions on expiry | H33: Report of temporary accounts with expiry; alert log of break-glass use | I33: Level 2 - Medium | J33: PR.AA-01 | K33: 1. Identity & Access Management (IAM Baseline) | L33: NOT EVALUATED | M33: Added - Groups | N33: AC-2(2)
A34: ESBIT-AC-02(03) | B34: AC-02(03) | C34: Access Control (AC) | D34: Account Management | Disable Accounts | E34: Configure | F34: Automatically disable accounts and access keys that are inactive beyond the policy period (for example 45-90 days) | G34: AWS IAM Access Analyzer unused access, Entra lifecycle workflows, GCP IAM Recommender | H34: Unused-credential report shows no stale credentials | I34: Level 2 - Medium | J34: PR.AA-01 | K34: 1. Identity & Access Management (IAM Baseline) | L34: FAIL | M34: Original v3 | N34: AC-2(3), AC-2(13)
A35: ESBIT-AC-02(04) | B35: AC-02(04) | C35: Access Control (AC) | D35: Account Management | Automated Audit Actions | E35: Enable | F35: Automatically log and notify security when accounts are created, modified, enabled, disabled or removed | G35: CloudTrail IAM events to EventBridge alert, Entra audit logs to Sentinel, GCP Admin Activity log-based alerts | H35: Alert rule export; sample alert for an account change | I35: Level 1 - High | J35: PR.AA-01 | K35: 1. Identity & Access Management (IAM Baseline) | L35: FAIL | M35: Added - Bitdefender
A36: ESBIT-AC-02(05) | B36: AC-02(05) | C36: Access Control (AC) | D36: Account Management | Inactivity Logout | E36: Configure | F36: Force console and portal users to log out after the defined period of inactivity | G36: IAM Identity Center session duration, Entra Conditional Access sign-in frequency, GCP session length control | H36: Session policy export | I36: Level 2 - Medium | J36: PR.AA-01 | K36: 1. Identity & Access Management (IAM Baseline) | L36: PASS | M36: Added - Bitdefender + Groups | N36: AC-2(5)
A37: ESBIT-AC-02(06) | B37: AC-02(06) | C37: Access Control (AC) | D37: Account Management | Dynamic Privilege Management | E37: Implement | F37: Grant privileged access dynamically and just-in-time using policy-based, time-limited elevation rather than standing rights | G37: Entra PIM, AWS IAM Identity Center temporary elevated access, GCP Privileged Access Manager | H37: Count of standing admin roles is near zero; PIM activation log | I37: Level 2 - Medium | J37: PR.AA-01 | K37: 1. Identity & Access Management (IAM Baseline) | L37: NOT EVALUATED | M37: Added - Groups | N37: AC-2(6), AC-2(7), AC-3(2), AC-4(10), AC-4(11), AC-6(2), AC-6(3), AC-6(5), AC-6(6), AC-6(10)
A38: ESBIT-AC-02(07) | B38: AC-02(07) | C38: Access Control (AC) | D38: Account Management | Privileged User Accounts | E38: Configure | F38: Define and monitor privileged user accounts; keep them separate from daily-use accounts and review their membership regularly | G38: Dedicated admin identities, AWS IAM Access Analyzer, Entra privileged role access reviews | H38: Privileged account list; access review record | I38: Level 1 - High | J38: PR.AA-01 | K38: 1. Identity & Access Management (IAM Baseline) | L38: FAIL | M38: Added - Bitdefender
A39: ESBIT-AC-02(11) | B39: AC-02(11) | C39: Access Control (AC) | D39: Account Management | Usage Conditions | E39: Configure | F39: Enforce usage conditions for cloud accounts such as trusted location, compliant device, time window and risk level | G39: Entra Conditional Access, AWS IAM policy conditions (aws:SourceIp, MFA age), GCP Access Context Manager | H39: Conditional access policy export; blocked sign-in report | I39: Level 2 - Medium | J39: PR.AA-01 | K39: 1. Identity & Access Management (IAM Baseline) | L39: FAIL | M39: Added - Bitdefender + Groups | N39: AC-2(11)
A40: ESBIT-AC-02(12) | B40: AC-02(12) | C40: Access Control (AC) | D40: Account Management | Account Monitoring for Atypical Usage | E40: Enable | F40: Monitor cloud accounts for atypical usage (impossible travel, unusual API calls, mass data access) and report to the security team | G40: Entra ID Protection, Amazon GuardDuty IAM findings, Google Security Command Center, UEBA in SIEM | H40: Detection rule list; sample atypical-usage alert | I40: Level 2 - Medium | J40: PR.AA-01 | K40: 1. Identity & Access Management (IAM Baseline) | L40: FAIL | M40: Added - Bitdefender + Groups | N40: AC-2(12)
A41: ESBIT-AC-03 | B41: AC-03 | C41: Access Control (AC) | D41: Access Enforcement | E41: Configure | F41: Enforce role-based (and attribute-based where supported) authorization on every cloud resource; deny public access by default | G41: IAM policies with conditions, Azure RBAC and Policy, GCP Organization Policy constraints | H41: IAM policy simulator; CSPM public-resource finding | I41: Level 1 - High | J41: PR.AA-05 | K41: 1. Identity & Access Management (IAM Baseline) | L41: FAIL | M41: Original v3 | N41: AC-2(9), AC-3, AC-3(5), AC-3(7), AC-3(8), AC-3(9), AC-3(10), AC-3(11), AC-3(12), AC-3(13), AC-4, AC-4(1), AC-4(2), AC-4(3), AC-4(4), AC-4(5), AC-4(6), AC-4(7), AC-4(8), AC-4(9), AC-4(12), AC-4(13), AC-4(14), AC-4(15), AC-4(17), AC-4(19), AC-4(20), AC-4(21), AC-4(22), AC-4(23), AC-4(24), AC-4(26), AC-4(28), AC-4(29), AC-4(30), AC-4(31), AC-4(32), AC-6(1), AC-6(4), AC-6(7), AC-6(8), AC-7(3), AC-7(4), AC-9(2), AC-9(3), AC-9(4), AC-12(1), AC-14, AC-16, AC-16(1), AC-16(2), AC-16(3), AC-16(4), AC-16(5), AC-16(6), AC-16(7), AC-16(8), AC-16(9), AC-16(10), AC-17(3), AC-17(10), AC-19, AC-20(3), AC-21(1), AC-21(2), AC-24, AC-24(1), AC-24(2), AC-25
A42: ESBIT-AC-03(02) | B42: AC-03(02) | C42: Access Control (AC) | D42: Access Enforcement | Dual Authorization | E42: Implement | F42: Require dual authorization (two approvers) for critical actions such as deleting backups or logs, changing key policies and disabling security services | G42: AWS S3 MFA Delete and multi-party approval, Azure Resource Guard for Backup, GCP approval workflows in change pipeline | H42: Approval records for critical changes | I42: Level 2 - Medium | J42: PR.AA-05 | K42: 1. Identity & Access Management (IAM Baseline) | L42: FAIL | M42: Added - Bitdefender
A43: ESBIT-AC-03(03) | B43: AC-03(03) | C43: Access Control (AC) | D43: Access Enforcement | Mandatory Access Control | E43: Configure | F43: Where required, enforce mandatory access control labels on sensitive data and workloads independent of resource owner discretion | G43: Azure Purview sensitivity labels, AWS Organizations SCPs, GCP Organization Policy constraints, SELinux enforcing on VMs | H43: Policy export; label coverage report | I43: Level 2 - Medium | J43: PR.AA-05 | K43: 1. Identity & Access Management (IAM Baseline) | L43: NOT EVALUATED | M43: Added - Groups | N43: AC-3(3)
A44: ESBIT-AC-03(04) | B44: AC-03(04) | C44: Access Control (AC) | D44: Access Enforcement | Discretionary Access Control | E44: Configure | F44: Restrict owner-managed (discretionary) sharing so owners cannot grant broader access than policy permits | G44: S3 Block Public Access and bucket ownership controls, Azure storage shared-key disabled, GCP uniform bucket-level access | H44: No object-level ACL or unrestricted sharing in CSPM report | I44: Level 2 - Medium | J44: PR.AA-05 | K44: 1. Identity & Access Management (IAM Baseline) | L44: NOT EVALUATED | M44: Added - Groups | N44: AC-3(4)
A45: ESBIT-AC-03(07) | B45: AC-03(07) | C45: Access Control (AC) | D45: Access Enforcement | Role-based Access Control | E45: Configure | F45: Implement role-based access control with named roles mapped to job functions; assign roles to groups, not individuals | G45: AWS IAM roles and IAM Identity Center permission sets, Azure RBAC built-in roles, GCP predefined roles | H45: Role-to-group matrix; no direct user assignments | I45: Level 2 - Medium | J45: PR.AA-05 | K45: 1. Identity & Access Management (IAM Baseline) | L45: FAIL | M45: Added - Bitdefender
A46: ESBIT-AC-03(13) | B46: AC-03(13) | C46: Access Control (AC) | D46: Access Enforcement | Attribute-based Access Control | E46: Configure | F46: Use attribute-based access control (tags, department, data classification) so permissions follow resource and identity attributes | G46: AWS ABAC with tag conditions, Azure ABAC role assignment conditions, GCP IAM Conditions with resource tags | H46: Policy showing tag conditions; tag compliance report | I46: Level 2 - Medium | J46: PR.AA-05 | K46: 1. Identity & Access Management (IAM Baseline) | L46: FAIL | M46: Added - Bitdefender
A47: ESBIT-AC-03(14) | B47: AC-03(14) | C47: Access Control (AC) | D47: Access Enforcement | Individual Access | E47: Implement | F47: Provide a mechanism for individuals to access their own personal data held in cloud services where privacy law requires it | G47: Data subject request workflow with export from cloud data stores, Microsoft Priva or equivalent | H47: Completed data subject request log | I47: Level 2 - Medium | J47: PR.AA-05 | K47: 1. Identity & Access Management (IAM Baseline) | L47: NOT EVALUATED | M47: Added - Groups | N47: AC-3(14)
A48: ESBIT-AC-03(15) | B48: AC-03(15) | C48: Access Control (AC) | D48: Access Enforcement | Discretionary and Mandatory Access Control | E48: Configure | F48: Combine mandatory and discretionary access controls consistently so owner sharing never overrides the mandatory policy | G48: SCP or Organization Policy guardrails above resource-level IAM, sensitivity labels with sharing restrictions | H48: Guardrail policy export; test showing owner cannot bypass | I48: Level 2 - Medium | J48: PR.AA-05 | K48: 1. Identity & Access Management (IAM Baseline) | L48: FAIL | M48: Added - Bitdefender + Groups | N48: AC-3(15)
A49: ESBIT-AC-04 | B49: AC-04 | C49: Access Control (AC) | D49: Information Flow Enforcement | E49: Configure | F49: Segment workloads into separate VPC/VNet and subnets by tier; control flows with security groups/NSGs and network ACLs | G49: AWS Security Groups and NACLs, Azure NSG/ASG, GCP VPC firewall rules | H49: VPC flow logs; reachability analyzer output | I49: Level 1 - High | J49: PR.IR-01 | K49: 1. Identity & Access Management (IAM Baseline) | L49: FAIL | M49: Original v3
A50: ESBIT-AC-04(01) | B50: AC-04(01) | C50: Access Control (AC) | D50: Information Flow Enforcement | Object Security and Privacy Attributes | E50: Configure | F50: Tag data and resources with security and privacy attributes (classification, owner, environment) and use them to control flows | G50: Cloud resource tags and labels enforced by tag policy, Azure Purview labels, AWS Macie classification | H50: Tag compliance report; classification coverage | I50: Level 2 - Medium | J50: PR.IR-01 | K50: 1. Identity & Access Management (IAM Baseline) | L50: FAIL | M50: Added - Bitdefender
A51: ESBIT-AC-04(21) | B51: AC-04(21) | C51: Access Control (AC) | D51: Information Flow Enforcement | Physical or Logical Separation of Information Flows | E51: Configure | F51: Separate information flows physically or logically by security domain using separate accounts, VPC/VNets and subnets | G51: Separate AWS accounts per environment, Azure landing-zone subscriptions, GCP projects and Shared VPC | H51: Network diagram; no peering between prod and non-prod without approval | I51: Level 2 - Medium | J51: PR.IR-01 | K51: 1. Identity & Access Management (IAM Baseline) | L51: FAIL | M51: Added - Bitdefender
A52: ESBIT-AC-04(25) | B52: AC-04(25) | C52: Access Control (AC) | D52: Information Flow Enforcement | Data Sanitization | E52: Implement | F52: Sanitize or filter data when moving between security domains (for example remove secrets and personal data before copying prod data to test) | G52: Data masking pipeline, AWS Glue DataBrew masking, Azure Data Factory masking, DLP API de-identification | H52: Masking job logs; test dataset scan shows no personal data | I52: Level 2 - Medium | J52: PR.IR-01 | K52: 1. Identity & Access Management (IAM Baseline) | L52: NOT EVALUATED | M52: Added - Groups | N52: AC-4(25)
A53: ESBIT-AC-04(26) | B53: AC-04(26) | C53: Access Control (AC) | D53: Information Flow Enforcement | Audit Filtering Actions | E53: Enable | F53: Log the actions of cross-domain filtering and network filtering devices such as allowed and blocked flows | G53: VPC flow logs and Route 53 Resolver query logs, Azure Firewall logs, GCP firewall rules logging | H53: Log delivery confirmed in SIEM | I53: Level 1 - High | J53: PR.IR-01 | K53: 1. Identity & Access Management (IAM Baseline) | L53: FAIL | M53: Added - Bitdefender
A54: ESBIT-AC-04(27) | B54: AC-04(27) | C54: Access Control (AC) | D54: Information Flow Enforcement | Redundant/Independent Filtering Mechanisms | E54: Implement | F54: Apply redundant, independent content filtering layers at cross-domain transfers (for example WAF plus DLP plus malware scan) | G54: AWS WAF with Macie and GuardDuty Malware Protection for S3, Azure Front Door WAF with Purview DLP, GCP Cloud Armor with Cloud DLP | H54: Design document; filter chain test results | I54: Level 2 - Medium | J54: PR.IR-01 | K54: 1. Identity & Access Management (IAM Baseline) | L54: NOT EVALUATED | M54: Added - Groups | N54: AC-4(27)
A55: ESBIT-AC-05 | B55: AC-05 | C55: Access Control (AC) | D55: Separation of Duties | E55: Implement | F55: Separate administration, security audit, billing and approval roles so no single identity can both change and approve or delete logs | G55: Separate IAM roles and groups, Azure PIM eligible roles, AWS Organizations SCPs | H55: Role-to-user matrix; access review record | I55: Level 2 - Medium | J55: PR.AA-05 | K55: 1. Identity & Access Management (IAM Baseline) | L55: NOT EVALUATED | M55: Original v3 | N55: AC-5
A56: ESBIT-AC-06 | B56: AC-06 | C56: Access Control (AC) | D56: Least Privilege | E56: Configure | F56: Grant minimum permissions only; prohibit wildcard admin permissions; apply permission boundaries and just-in-time elevation | G56: IAM permission boundaries, Azure PIM, GCP IAM Conditions, Access Analyzer policy generation | H56: Count of full-admin principals; Access Analyzer findings | I56: Level 1 - High | J56: PR.AA-05 | K56: 1. Identity & Access Management (IAM Baseline) | L56: FAIL | M56: Original v3 | N56: AC-6
A57: ESBIT-AC-06(02) | B57: AC-06(02) | C57: Access Control (AC) | D57: Least Privilege | Non-privileged Access for Nonsecurity Functions | E57: Configure | F57: Require administrators to use a separate non-privileged account for email, browsing and other non-security tasks | G57: Separate admin identities, Entra PIM eligible roles, privileged access workstations | H57: No admin role on mail-enabled daily accounts | I57: Level 2 - Medium | J57: PR.AA-05 | K57: 1. Identity & Access Management (IAM Baseline) | L57: FAIL | M57: Added - Bitdefender
A58: ESBIT-AC-06(03) | B58: AC-06(03) | C58: Access Control (AC) | D58: Least Privilege | Network Access to Privileged Commands | E58: Configure | F58: Allow privileged commands over the network only from approved management paths with MFA and logging | G58: AWS Session Manager with MFA, Azure Bastion and PIM, GCP IAP with context-aware access, IP allowlist for management APIs | H58: Management-plane access policy; session logs | I58: Level 1 - High | J58: PR.AA-05 | K58: 1. Identity & Access Management (IAM Baseline) | L58: FAIL | M58: Added - Bitdefender
A59: ESBIT-AC-06(05) | B59: AC-06(05) | C59: Access Control (AC) | D59: Least Privilege | Privileged Accounts | E59: Configure | F59: Restrict root/global-admin accounts: no daily use, hardware MFA, no access keys, vaulted break-glass credentials | G59: AWS root MFA and no keys, Azure emergency access accounts, GCP super admin controls | H59: Alert on every root/global admin sign-in | I59: Level 1 - High | J59: PR.AA-05 | K59: 1. Identity & Access Management (IAM Baseline) | L59: NOT EVALUATED | M59: Original v3
A60: ESBIT-AC-06(07) | B60: AC-06(07) | C60: Access Control (AC) | D60: Least Privilege | Review of User Privileges | E60: Implement | F60: Review all user and service privileges at a fixed interval (for example quarterly) and remove those no longer needed | G60: Entra access reviews, AWS IAM Access Analyzer unused access, GCP IAM Recommender | H60: Completed access review with removals | I60: Level 2 - Medium | J60: PR.AA-05 | K60: 1. Identity & Access Management (IAM Baseline) | L60: FAIL | M60: Added - Bitdefender
A61: ESBIT-AC-06(09) | B61: AC-06(09) | C61: Access Control (AC) | D61: Least Privilege | Log Use of Privileged Functions | E61: Enable | F61: Log all privileged actions and administrative API calls | G61: AWS CloudTrail management events, Azure Activity Log, GCP Admin Activity audit logs | H61: Trail enabled in all regions/subscriptions | I61: Level 1 - High | J61: PR.AA-05 | K61: 1. Identity & Access Management (IAM Baseline) | L61: FAIL | M61: Original v3 | N61: AC-6(9)
A62: ESBIT-AC-06(10) | B62: AC-06(10) | C62: Access Control (AC) | D62: Least Privilege | Prohibit Non-privileged Users from Executing Privileged Functions | E62: Configure | F62: Prevent non-privileged users from executing privileged functions such as changing security services, IAM or logging | G62: SCPs denying security service changes, Azure Policy deny effects, GCP Organization Policy, permission boundaries | H62: Policy simulator test denies action for standard user | I62: Level 1 - High | J62: PR.AA-05 | K62: 1. Identity & Access Management (IAM Baseline) | L62: FAIL | M62: Added - Bitdefender
A63: ESBIT-AC-07 | B63: AC-07 | C63: Access Control (AC) | D63: Unsuccessful Logon Attempts | E63: Configure | F63: Apply sign-in throttling and lockout for repeated failed authentications at the identity provider | G63: Entra Smart Lockout, IdP lockout policy, Cloud Identity login challenges | H63: Lockout policy export | I63: Level 1 - High | J63: PR.AA-03 | K63: 1. Identity & Access Management (IAM Baseline) | L63: FAIL | M63: Original v3 | N63: AC-7, AC-9(1)
A64: ESBIT-AC-07(02) | B64: AC-07(02) | C64: Access Control (AC) | D64: Unsuccessful Logon Attempts | Purge or Wipe Mobile Device | E64: Configure | F64: Enforce remote wipe or lock of managed mobile devices after repeated failed unlock attempts where devices access cloud data | G64: Intune or Workspace ONE compliance policy, wipe after failed attempts | H64: Device compliance report | I64: Level 2 - Medium | J64: PR.AA-03 | K64: 1. Identity & Access Management (IAM Baseline) | L64: NOT EVALUATED | M64: Added - Groups | N64: AC-7(2)
A65: ESBIT-AC-08 | B65: AC-08 | C65: Access Control (AC) | D65: System Use Notification | E65: Configure | F65: Display an approved system use notification before granting access to cloud consoles, bastion hosts and VMs | G65: Entra custom sign-in banner and terms of use, SSH and RDP login banner via image baseline | H65: Screenshot of banner; image configuration | I65: Level 2 - Medium | J65: GV.PO-01 | K65: 1. Identity & Access Management (IAM Baseline) | L65: NOT EVALUATED | M65: Added - Groups | N65: AC-8
A66: ESBIT-AC-09 | B66: AC-09 | C66: Access Control (AC) | D66: Previous Logon Notification | E66: Configure | F66: Show users the date and time of their last successful sign-in where the platform supports it | G66: Entra sign-in activity, OS last-login message on VMs, IdP last login display | H66: Sample login screen | I66: Level 3 - Low | J66: DE.CM-03 | K66: 1. Identity & Access Management (IAM Baseline) | L66: NOT EVALUATED | M66: Added - Groups | N66: AC-9
A67: ESBIT-AC-10 | B67: AC-10 | C67: Access Control (AC) | D67: Concurrent Session Control | E67: Configure | F67: Limit concurrent sessions per privileged account and terminate extra sessions | G67: Entra Conditional Access session controls, IdP concurrent-session limit, bastion session limits | H67: Session policy export | I67: Level 2 - Medium | J67: PR.AA-05 | K67: 1. Identity & Access Management (IAM Baseline) | L67: NOT EVALUATED | M67: Added - Groups | N67: AC-10
A68: ESBIT-AC-11 | B68: AC-11 | C68: Access Control (AC) | D68: Device Lock | E68: Configure | F68: Lock idle sessions on VMs, bastions and admin workstations after the defined idle time (for example 10-15 minutes) | G68: GPO or Intune screen lock, tmux or shell TMOUT on Linux, Azure Bastion idle timeout | H68: Configuration compliance report | I68: Level 1 - High | J68: PR.AA-03 | K68: 1. Identity & Access Management (IAM Baseline) | L68: NOT EVALUATED | M68: Added - Groups | N68: AC-11, AC-11(1)
A69: ESBIT-AC-12 | B69: AC-12 | C69: Access Control (AC) | D69: Session Termination | E69: Configure | F69: Set console and portal session lifetime and idle timeout (for example 15-60 minutes) and force re-authentication | G69: Entra Conditional Access session controls, IAM Identity Center session duration, GCP session length control | H69: Policy export | I69: Level 1 - High | J69: PR.AA-03 | K69: 1. Identity & Access Management (IAM Baseline) | L69: PASS | M69: Original v3 | N69: AC-12
A70: ESBIT-AC-12(02) | B70: AC-12(02) | C70: Access Control (AC) | D70: Termination Message | E70: Configure | F70: Show a message to the user when a session is terminated by policy | G70: IdP sign-out page message, application session-expired page | H70: Screenshot of termination message | I70: Level 3 - Low | J70: PR.AA-03 | K70: 1. Identity & Access Management (IAM Baseline) | L70: NOT EVALUATED | M70: Added - Groups | N70: AC-12(2)
A71: ESBIT-AC-12(03) | B71: AC-12(03) | C71: Access Control (AC) | D71: Timeout Warning Message | E71: Configure | F71: Warn the user before an idle session is terminated | G71: IdP or application idle-timeout warning prompt | H71: Screenshot of timeout warning | I71: Level 3 - Low | J71: PR.AA-03 | K71: 1. Identity & Access Management (IAM Baseline) | L71: NOT EVALUATED | M71: Added - Groups | N71: AC-12(3)
A72: ESBIT-AC-17 | B72: AC-17 | C72: Access Control (AC) | D72: Remote Access | E72: Configure | F72: Remove direct public management access (SSH/RDP); provide access only through bastion, private endpoints or session manager with MFA | G72: AWS Systems Manager Session Manager, Azure Bastion, GCP IAP TCP forwarding | H72: No security rule allows 0.0.0.0/0 to ports 22/3389 | I72: Level 1 - High | J72: PR.IR-01 | K72: 1. Identity & Access Management (IAM Baseline) | L72: NOT EVALUATED | M72: Original v3 | N72: AC-17, AC-17(1), AC-17(6), AC-17(9)
A73: ESBIT-AC-17(01) | B73: AC-17(01) | C73: Access Control (AC) | D73: Remote Access | Monitoring and Control | E73: Enable | F73: Monitor and control all remote access to cloud management and workloads with logging of connections | G73: AWS Session Manager logging, Azure Bastion session recording, GCP IAP audit logs, VPN logs to SIEM | H73: Remote session logs available; alert on unapproved paths | I73: Level 2 - Medium | J73: PR.IR-01 | K73: 1. Identity & Access Management (IAM Baseline) | L73: FAIL | M73: Added - Bitdefender
A74: ESBIT-AC-17(02) | B74: AC-17(02) | C74: Access Control (AC) | D74: Remote Access | Protection of Confidentiality and Integrity Using Encryption | E74: Configure | F74: Protect remote access sessions with strong encryption (TLS 1.2+ or IPsec/SSH with approved ciphers) | G74: TLS-only bastion and VPN gateway, IPsec with AES-256, disable legacy SSH ciphers | H74: Scan of management endpoints shows only approved protocols | I74: Level 1 - High | J74: PR.IR-01 | K74: 1. Identity & Access Management (IAM Baseline) | L74: FAIL | M74: Added - Bitdefender + Groups | N74: AC-17(2)
A75: ESBIT-AC-17(04) | B75: AC-17(04) | C75: Access Control (AC) | D75: Remote Access | Privileged Commands and Access | E75: Configure | F75: Permit privileged commands and access via remote sessions only for documented operational needs and log them | G75: SSM Run Command with approval, PIM with justification, GCP OS Login with 2FA | H75: Privileged remote session log with justification | I75: Level 1 - High | J75: PR.IR-01 | K75: 1. Identity & Access Management (IAM Baseline) | L75: NOT EVALUATED | M75: Added - Groups | N75: AC-17(4)
A76: ESBIT-AC-18 | B76: AC-18 | C76: Access Control (AC) | D76: Wireless Access | E76: Configure | F76: For cloud-managed wireless or IoT access to cloud resources, require authentication, encryption and authorized devices only | G76: Cloud-managed Wi-Fi with WPA3-Enterprise, AWS IoT Core certificates, Azure IoT Hub device identity | H76: Wireless configuration export; rogue device report | I76: Level 1 - High | J76: PR.IR-01 | K76: 1. Identity & Access Management (IAM Baseline) | L76: NOT EVALUATED | M76: Added - Groups | N76: AC-18, AC-18(1), AC-18(3), AC-18(4), AC-18(5)
A77: ESBIT-AC-19(04) | B77: AC-19(04) | C77: Access Control (AC) | D77: Access Control for Mobile Devices | Restrictions for Classified Information | E77: Configure | F77: Where classified or highly regulated data is accessed from mobile devices, restrict access to approved managed devices and approved services only | G77: Conditional Access requiring compliant managed device, app protection policies, no access from unmanaged devices | H77: Conditional Access policy export | I77: Level 3 - Low | J77: PR.AA-05 | K77: 1. Identity & Access Management (IAM Baseline) | L77: NOT EVALUATED | M77: Added - Groups | N77: AC-19(4)
A78: ESBIT-AC-19(05) | B78: AC-19(05) | C78: Access Control (AC) | D78: Access Control for Mobile Devices | Full Device or Container-based Encryption | E78: Configure | F78: Require full-device or container-based encryption on mobile devices that access cloud data | G78: Intune or Jamf encryption compliance policy, managed app containers | H78: Device encryption compliance report | I78: Level 2 - Medium | J78: PR.PS-01 | K78: 1. Identity & Access Management (IAM Baseline) | L78: NOT EVALUATED | M78: Added - Groups | N78: AC-19(5)
A79: ESBIT-AC-20 | B79: AC-20 | C79: Access Control (AC) | D79: Use of External Systems | E79: Configure | F79: Restrict cross-account, cross-tenant and third-party access to approved principals with external ID and time limits | G79: AWS Organizations SCP and role trust policies, Entra cross-tenant access settings, GCP domain-restricted sharing | H79: Access Analyzer external-access findings | I79: Level 2 - Medium | J79: PR.IR-01 | K79: 1. Identity & Access Management (IAM Baseline) | L79: NOT EVALUATED | M79: Original v3 | N79: AC-20, AC-20(2), AC-20(5)
A80: ESBIT-AC-20(01) | B80: AC-20(01) | C80: Access Control (AC) | D80: Use of External Systems | Limits on Authorized Use | E80: Configure | F80: Allow use of external systems and personal devices to access cloud data only after verifying required controls are in place | G80: Conditional Access device compliance, Entra cross-tenant access settings, session-only browser access | H80: Policy export; external access review | I80: Level 3 - Low | J80: PR.IR-01 | K80: 1. Identity & Access Management (IAM Baseline) | L80: NOT EVALUATED | M80: Added - Groups | N80: AC-20(1)
A81: ESBIT-AC-20(04) | B81: AC-20(04) | C81: Access Control (AC) | D81: Use of External Systems | Network Accessible Storage Devices - Prohibited Use | E81: Configure | F81: Prohibit use of unapproved network-accessible or consumer storage services for organisation data | G81: CASB or DLP block of consumer cloud storage, Organization Policy domain-restricted sharing | H81: CASB or DLP block report | I81: Level 3 - Low | J81: PR.IR-01 | K81: 1. Identity & Access Management (IAM Baseline) | L81: NOT EVALUATED | M81: Added - Groups | N81: AC-20(4)
A82: ESBIT-AC-21 | B82: AC-21 | C82: Access Control (AC) | D82: Information Sharing | E82: Configure | F82: Restrict information sharing to authorized partners and approved sharing methods; require approval for external sharing | G82: S3 Access Points and bucket policies, Azure storage private endpoints, GCP domain-restricted sharing, SaaS external sharing limits | H82: External sharing report; approvals | I82: Level 3 - Low | J82: PR.DS-01 | K82: 1. Identity & Access Management (IAM Baseline) | L82: FAIL | M82: Added - Bitdefender + Groups | N82: AC-21
A83: ESBIT-AC-22 | B83: AC-22 | C83: Access Control (AC) | D83: Publicly Accessible Content | E83: Configure | F83: Block anonymous and public exposure of storage, snapshots, images and databases unless formally approved | G83: S3 Block Public Access, Azure storage public access disabled, GCP public access prevention | H83: CSPM public-exposure report is empty | I83: Level 2 - Medium | J83: PR.DS-01 | K83: 1. Identity & Access Management (IAM Baseline) | L83: NOT EVALUATED | M83: Original v3 | N83: AC-22
A84: ESBIT-AC-23 | B84: AC-23 | C84: Access Control (AC) | D84: Data Mining Protection | E84: Configure | F84: Protect against bulk data mining and harvesting with rate limits, query quotas and anomaly alerts on data services | G84: API Gateway throttling, AWS WAF rate rules, Azure API Management rate limits, BigQuery quotas and audit alerts | H84: Rate limit configuration; anomaly alert sample | I84: Level 3 - Low | J84: PR.DS-01 | K84: 1. Identity & Access Management (IAM Baseline) | L84: NOT EVALUATED | M84: Added - Groups | N84: AC-23
A85: ESBIT-AU-01 | B85: AU-01 | C85: Audit and Accountability (AU) | D85: Policy and Procedures | E85: Implement | F85: Publish an approved audit and logging policy covering scope, retention, protection and review; review it at least annually | G85: Policy in the GRC tool mapped to cloud logging standard | H85: Signed policy with review date | I85: Level 3 - Low | J85: GV.PO-01 | K85: 2. Logging & Monitoring | L85: NOT EVALUATED | M85: Added - Groups | N85: AU-1
... A88: ESBIT-AU-03(03) | B88: AU-03(03) | C88: Audit and Accountability (AU) | D88: Content of Audit Records | Limit Personally Identifiable Information Elements | E88: Configure | F88: Limit personal data in audit records to what is required and mask or tokenize sensitive fields in logs | G88: Log field filtering or masking in CloudWatch Logs data protection, Azure Monitor transformations, Cloud Logging exclusions | H88: Sample logs contain no unmasked personal data | I88: Level 2 - Medium | J88: PR.PS-04 | K88: 2. Logging & Monitoring | L88: NOT EVALUATED | M88: Added - Groups | N88: AU-3(3)
A89: ESBIT-AU-04 | B89: AU-04 | C89: Audit and Accountability (AU) | D89: Audit Log Storage Capacity | E89: Configure | F89: Provision log storage sized for the retention period and set lifecycle and capacity alarms | G89: Log bucket with lifecycle rules, Log Analytics workspace cap and alerts | H89: Storage utilization alarm exists | I89: Level 2 - Medium | J89: PR.IR-04 | K89: 2. Logging & Monitoring | L89: NOT EVALUATED | M89: Original v3
A90: ESBIT-AU-04(01) | B90: AU-04(01) | C90: Audit and Accountability (AU) | D90: Audit Log Storage Capacity | Transfer to Alternate Storage | E90: Configure | F90: Automatically transfer audit logs to alternate long-term storage before local capacity is exhausted | G90: CloudWatch to S3 export, Azure Log Analytics data export to storage, Cloud Logging sink to Cloud Storage | H90: Log sink configuration; alternate storage has current logs | I90: Level 3 - Low | J90: PR.IR-04 | K90: 2. Logging & Monitoring | L90: FAIL | M90: Added - Bitdefender
A91: ESBIT-AU-05 | B91: AU-05 | C91: Audit and Accountability (AU) | D91: Response to Audit Logging Process Failures | E91: Configure | F91: Alert when logging is stopped, deleted or log delivery fails | G91: CloudWatch alarm on StopLogging, Azure Monitor alert on diagnostic setting deletion, GCP log sink error alert | H91: Test alert received | I91: Level 1 - High | J91: DE.CM-09 | K91: 2. Logging & Monitoring | L91: NOT EVALUATED | M91: Original v3
A92: ESBIT-AU-06 | B92: AU-06 | C92: Audit and Accountability (AU) | D92: Audit Record Review, Analysis, and Reporting | E92: Implement | F92: Send logs to a SIEM and create correlation rules for privileged use, failed logins and configuration changes | G92: Microsoft Sentinel, AWS Security Hub and Security Lake, Google Chronicle | H92: Detection rule inventory | I92: Level 2 - Medium | J92: DE.AE-02 | K92: 2. Logging & Monitoring | L92: NOT EVALUATED | M92: Original v3
A93: ESBIT-AU-06(01) | B93: AU-06(01) | C93: Audit and Accountability (AU) | D93: Audit Record Review, Analysis, and Reporting | Automated Process Integration | E93: Implement | F93: Integrate audit review, analysis and reporting with automated processes such as SIEM rules and scheduled reports | G93: Microsoft Sentinel analytics rules, Amazon Security Lake with OpenSearch, Chronicle detections | H93: Rule list and scheduled report evidence | I93: Level 3 - Low | J93: DE.AE-02 | K93: 2. Logging & Monitoring | L93: FAIL | M93: Added - Bitdefender
A94: ESBIT-AU-06(03) | B94: AU-06(03) | C94: Audit and Accountability (AU) | D94: Audit Record Review, Analysis, and Reporting | Correlate Audit Record Repositories | E94: Implement | F94: Correlate audit records across accounts, subscriptions, projects and platforms in one place to reveal broader patterns | G94: Org-level CloudTrail into central SIEM, Sentinel multi-workspace, Chronicle SIEM | H94: Cross-source correlation rule and sample alert | I94: Level 2 - Medium | J94: DE.AE-02 | K94: 2. Logging & Monitoring | L94: FAIL | M94: Added - Bitdefender + Groups | N94: AU-6(3), AU-6(9)
A95: ESBIT-AU-06(04) | B95: AU-06(04) | C95: Audit and Accountability (AU) | D95: Audit Record Review, Analysis, and Reporting | Central Review and Analysis | E95: Implement | F95: Provide central review and analysis of audit records collected from all cloud accounts | G95: Central logging account, Sentinel or Chronicle workspace | H95: Dashboard showing all accounts reporting | I95: Level 3 - Low | J95: DE.AE-02 | K95: 2. Logging & Monitoring | L95: FAIL | M95: Added - Bitdefender
A96: ESBIT-AU-06(05) | B96: AU-06(05) | C96: Audit and Accountability (AU) | D96: Audit Record Review, Analysis, and Reporting | Integrated Analysis of Audit Records | E96: Implement | F96: Integrate audit analysis with vulnerability, threat and asset data to improve detection | G96: Sentinel with Defender for Cloud, Security Hub with Inspector and GuardDuty, SCC with Chronicle | H96: Correlated finding example | I96: Level 2 - Medium | J96: DE.AE-02 | K96: 2. Logging & Monitoring | L96: FAIL | M96: Added - Bitdefender
A97: ESBIT-AU-06(06) | B97: AU-06(06) | C97: Audit and Accountability (AU) | D97: Audit Record Review, Analysis, and Reporting | Correlation with Physical Monitoring | E97: Implement | F97: Correlate cloud audit records with physical access and facility monitoring where the organisation controls physical sites | G97: Badge and CCTV logs forwarded to SIEM alongside cloud sign-in logs | H97: Correlation rule for physical plus remote access | I97: Level 3 - Low | J97: DE.AE-02 | K97: 2. Logging & Monitoring | L97: NOT EVALUATED | M97: Added - Groups | N97: AU-6(6)
A98: ESBIT-AU-06(08) | B98: AU-06(08) | C98: Audit and Accountability (AU) | D98: Audit Record Review, Analysis, and Reporting | Full Text Analysis of Privileged Commands | E98: Enable | F98: Perform full-text analysis of privileged commands and administrative sessions on a separate analysis system | G98: Session Manager or Bastion recordings analysed in SIEM, auditd and command logging to SIEM | H98: Privileged command search results in SIEM | I98: Level 2 - Medium | J98: DE.AE-02 | K98: 2. Logging & Monitoring | L98: NOT EVALUATED | M98: Added - Groups | N98: AU-6(8), AU-9(6)
A99: ESBIT-AU-07(01) | B99: AU-07(01) | C99: Audit and Accountability (AU) | D99: Audit Record Reduction and Report Generation | Automatic Processing | E99: Configure | F99: Provide automatic processing of audit records (search, sort, filter) on the centralized logging platform | G99: KQL or SQL search in Log Analytics, Athena queries on CloudTrail, BigQuery on audit logs | H99: Saved queries and reports | I99: Level 3 - Low | J99: DE.AE-06 | K99: 2. Logging & Monitoring | L99: PASS | M99: Added - Bitdefender
A100: ESBIT-AU-08 | B100: AU-08 | C100: Audit and Accountability (AU) | D100: Time Stamps | E100: Configure | F100: Use the provider time service on all instances and record timestamps in UTC | G100: Amazon Time Sync Service, Azure host time sync, GCP metadata NTP | H100: Instance time-sync status | I100: Level 1 - High | J100: PR.PS-04 | K100: 2. Logging & Monitoring | L100: NOT EVALUATED | M100: Original v3
A101: ESBIT-AU-09 | B101: AU-09 | C101: Audit and Accountability (AU) | D101: Protection of Audit Information | E101: Configure | F101: Store logs in a separate, restricted log-archive account with immutability, versioning and integrity validation | G101: S3 Object Lock with log file validation, Azure immutable blob storage, GCP bucket lock | H101: Object lock/retention policy enabled | I101: Level 1 - High | J101: PR.PS-04 | K101: 2. Logging & Monitoring | L101: FAIL | M101: Original v3
A102: ESBIT-AU-09(02) | B102: AU-09(02) | C102: Audit and Accountability (AU) | D102: Protection of Audit Information | Store on Separate Physical Systems or Components | E102: Configure | F102: Store audit logs in a separate account, subscription or project from the systems that generate them | G102: Dedicated log archive AWS account, separate Azure subscription, dedicated GCP logging project | H102: Log archive account owned by security team; write-only access from workloads | I102: Level 2 - Medium | J102: PR.PS-04 | K102: 2. Logging & Monitoring | L102: FAIL | M102: Added - Bitdefender
A103: ESBIT-AU-09(03) | B103: AU-09(03) | C103: Audit and Accountability (AU) | D103: Protection of Audit Information | Cryptographic Protection | E103: Configure | F103: Protect audit information and logs with cryptographic integrity and encryption | G103: CloudTrail log file validation, S3 SSE-KMS, Azure immutable storage, GCP CMEK on log buckets | H103: Log validation result; encryption setting | I103: Level 1 - High | J103: PR.PS-04 | K103: 2. Logging & Monitoring | L103: FAIL | M103: Added - Bitdefender + Groups | N103: AU-9(3)
A104: ESBIT-AU-09(04) | B104: AU-09(04) | C104: Audit and Accountability (AU) | D104: Protection of Audit Information | Access by Subset of Privileged Users | E104: Configure | F104: Limit management of audit logging to a small set of privileged users | G104: Dedicated logging administrator role, SCP protecting CloudTrail, Azure RBAC on Log Analytics | H104: Role membership list; deny policy on trail deletion | I104: Level 1 - High | J104: PR.PS-04 | K104: 2. Logging & Monitoring | L104: NOT EVALUATED | M104: Added - Groups | N104: AU-9(4)
A105: ESBIT-AU-09(07) | B105: AU-09(07) | C105: Audit and Accountability (AU) | D105: Protection of Audit Information | Store on Component with Different Operating System | E105: Configure | F105: Store logs on a component with a different operating system or platform than the source system | G105: Central log archive on managed storage, separate platform from monitored VMs | H105: Architecture diagram | I105: Level 2 - Medium | J105: PR.PS-04 | K105: 2. Logging & Monitoring | L105: PASS | M105: Added - Bitdefender
...

Sheet Network Config Baseline
A1: Network Security Configuration Baseline (NIST SP 800-53 Rev. 5 - core configuration items)
A2: Purpose: this sheet turns the NIST SP 800-53 Rev. 5 controls into the core Network Security Configuration Baseline for routers, switches, firewalls, wireless controllers and access points, VPN and DNS/NTP services. It lists what administrators must configure, implement, install or enable on network devices.
A3: Scope: only rows tagged Network in the Config Baseline sheet are considered, limited to the 8 families requested (AC, AU, CA, CM, IA, RA, SC, SI). Other families (for example CP, IR, MA, PE) are left to their own baselines, and process controls are excluded.
A4: Selection principle: controls with a similar effect were consolidated so that only the main baseline items remain. For example AU-8 covers time synchronization (SC-45 is not repeated), AC-12 covers session timeouts (SC-10 is not repeated), and SC-20 covers DNS hardening (SC-21 and SC-22 are not repeated).
A5: Examples use common vendor terms (Cisco IOS, Junos, Palo Alto, FortiGate) as guidance only; map each item to the exact syntax and feature of the devices in use. Level is taken from the Config Baseline sheet (Level 1 = mandatory, Level 3 = lowest impact).
A7: Action Type legend
A8: Configure = set a parameter, policy or rule on an existing platform/service.
A9: Implement = build or deploy a mechanism, template, automation or architecture pattern.
A10: Install = install or onboard a tool, agent or scanner.
A11: Enable = turn on a feature, log source or detection service that is off by default.
A13: Coverage by control family
A14: Family | B14: Items | C14: Level 1 | D14: Level 2 | E14: Level 3 | F14: Configuration focus
A15: Access Control (AC) | B15: =COUNTIF($C$26:$C$95,$A15) -> 13 | C15: =COUNTIFS($C$26:$C$95,$A15,$I$26:$I$95,"Level 1*") -> 12 | D15: =COUNTIFS($C$26:$C$95,$A15,$I$26:$I$95,"Level 2*") -> 1 | E15: =COUNTIFS($C$26:$C$95,$A15,$I$26:$I$95,"Level 3*") -> 0 | F15: Central AAA, role-based command authorization, management-plane restriction, lockout, banner, idle timeout, secure remote access, wireless security.
A16: Audit and Accountability (AU) | B16: =COUNTIF($C$26:$C$95,$A16) -> 9 | C16: =COUNTIFS($C$26:$C$95,$A16,$I$26:$I$95,"Level 1*") -> 6 | D16: =COUNTIFS($C$26:$C$95,$A16,$I$26:$I$95,"Level 2*") -> 3 | E16: =COUNTIFS($C$26:$C$95,$A16,$I$26:$I$95,"Level 3*") -> 0 | F16: Device logging, remote TLS syslog, SIEM correlation, authenticated NTP, retention and failure alerts.
A17: Assessment, Authorization, and Monitoring (CA) | B17: =COUNTIF($C$26:$C$95,$A17) -> 3 | C17: =COUNTIFS($C$26:$C$95,$A17,$I$26:$I$95,"Level 1*") -> 0 | D17: =COUNTIFS($C$26:$C$95,$A17,$I$26:$I$95,"Level 2*") -> 3 | E17: =COUNTIFS($C$26:$C$95,$A17,$I$26:$I$95,"Level 3*") -> 0 | F17: Secure partner/WAN links, configuration drift monitoring, documented inter-zone flows.
A18: Configuration Management (CM) | B18: =COUNTIF($C$26:$C$95,$A18) -> 11 | C18: =COUNTIFS($C$26:$C$95,$A18,$I$26:$I$95,"Level 1*") -> 6 | D18: =COUNTIFS($C$26:$C$95,$A18,$I$26:$I$95,"Level 2*") -> 5 | E18: =COUNTIFS($C$26:$C$95,$A18,$I$26:$I$95,"Level 3*") -> 0 | F18: Golden templates, config backup and versioning, change control, CIS hardening and automation, disabling unused services, inventory and rogue-device detection, signed firmware.
A19: Identification and Authentication (IA) | B19: =COUNTIF($C$26:$C$95,$A19) -> 7 | C19: =COUNTIFS($C$26:$C$95,$A19,$I$26:$I$95,"Level 1*") -> 5 | D19: =COUNTIFS($C$26:$C$95,$A19,$I$26:$I$95,"Level 2*") -> 2 | E19: =COUNTIFS($C$26:$C$95,$A19,$I$26:$I$95,"Level 3*") -> 0 | F19: Named admin accounts, MFA, 802.1X device authentication, strong secrets and SNMPv3, SSH keys, guest authentication.
A20: Risk Assessment (RA) | B20: =COUNTIF($C$26:$C$95,$A20) -> 2 | C20: =COUNTIFS($C$26:$C$95,$A20,$I$26:$I$95,"Level 1*") -> 2 | D20: =COUNTIFS($C$26:$C$95,$A20,$I$26:$I$95,"Level 2*") -> 0 | E20: =COUNTIFS($C$26:$C$95,$A20,$I$26:$I$95,"Level 3*") -> 0 | F20: Scheduled and credentialed vulnerability scanning of network devices and firmware.
A21: System and Communications Protection (SC) | B21: =COUNTIF($C$26:$C$95,$A21) -> 16 | C21: =COUNTIFS($C$26:$C$95,$A21,$I$26:$I$95,"Level 1*") -> 7 | D21: =COUNTIFS($C$26:$C$95,$A21,$I$26:$I$95,"Level 2*") -> 9 | E21: =COUNTIFS($C$26:$C$95,$A21,$I$26:$I$95,"Level 3*") -> 0 | F21: Management plane separation, DoS protection, perimeter firewall/DMZ, default deny, egress filtering, segmentation, fail-closed, encryption in transit, key/PKI management, DNS hardening, wireless protection.
A22: System and Information Integrity (SI) | B22: =COUNTIF($C$26:$C$95,$A22) -> 9 | C22: =COUNTIFS($C$26:$C$95,$A22,$I$26:$I$95,"Level 1*") -> 5 | D22: =COUNTIFS($C$26:$C$95,$A22,$I$26:$I$95,"Level 2*") -> 4 | E22: =COUNTIFS($C$26:$C$95,$A22,$I$26:$I$95,"Level 3*") -> 0 | F22: Firmware patching, gateway malware inspection, IDS/IPS and flow monitoring, wireless IDS, DHCP snooping/DAI, firmware integrity and secure boot, email gateway.
A23: Total | B23: =SUM(B15:B22) -> 70 | C23: =SUM(C15:C22) -> 43 | D23: =SUM(D15:D22) -> 27 | E23: =SUM(E15:E22) -> 0
A25: Control ID New | B25: Control ID | C25: Control Family | D25: Control Name | E25: Action Type | F25: Baseline Setting to Configure | G25: Implementation Example | H25: Verification / Evidence | I25: Level | J25: CSF 2.0 Subcategory ID
A26: ESBIT-AC-02 | B26: AC-02 | C26: Access Control (AC) | D26: Account Management | E26: Configure | F26: Manage administrator accounts centrally through AAA (TACACS+/RADIUS); disable or rename default and local accounts; keep one protected break-glass account | G26: Cisco ISE or ClearPass TACACS+, Palo Alto and Juniper admin roles via LDAP/SAML | H26: AAA configuration; local account list | I26: Level 1 - High | J26: PR.AA-01
A27: ESBIT-AC-03 | B27: AC-03 | C27: Access Control (AC) | D27: Access Enforcement | E27: Configure | F27: Enforce role-based command authorization (read-only, operator, administrator) on every network device | G27: TACACS+ command authorization, Palo Alto admin roles, Junos login classes | H27: Test login with a read-only user | I27: Level 1 - High | J27: PR.AA-05
A28: ESBIT-AC-04 | B28: AC-04 | C28: Access Control (AC) | D28: Information Flow Enforcement | E28: Configure | F28: Control traffic between zones with ACLs and firewall policy; segment by VLAN/VRF (users, servers, management, guest, IoT) | G28: Cisco ACL and zone-based firewall, Palo Alto zones, FortiGate policies, VLAN/VRF | H28: Rulebase and ACL review | I28: Level 1 - High | J28: PR.IR-01
A29: ESBIT-AC-06 | B29: AC-06 | C29: Access Control (AC) | D29: Least Privilege | E29: Configure | F29: Assign least-privilege levels to administrators; only the network team can change configuration | G29: Privilege levels, Junos login classes, RBAC profiles | H29: Role assignment list | I29: Level 1 - High | J29: PR.AA-05
A30: ESBIT-AC-06(03) | B30: AC-06(03) | C30: Access Control (AC) | D30: Least Privilege | Network Access to Privileged Commands | E30: Configure | F30: Allow privileged commands only from the management network or jump host | G30: Management ACL, dedicated management VLAN, control-plane policing | H30: Access from a non-management IP fails | I30: Level 1 - High | J30: PR.AA-05
A31: ESBIT-AC-06(09) | B31: AC-06(09) | C31: Access Control (AC) | D31: Least Privilege | Log Use of Privileged Functions | E31: Enable | F31: Log all privileged commands executed on devices | G31: TACACS+ accounting, archive logging, Junos change-log | H31: Accounting log sample | I31: Level 1 - High | J31: PR.AA-05
A32: ESBIT-AC-07 | B32: AC-07 | C32: Access Control (AC) | D32: Unsuccessful Logon Attempts | E32: Configure | F32: Lock out or delay after 3-5 failed logins | G32: login block-for, Junos login retry-options, firewall admin lockout | H32: Failed-login test | I32: Level 1 - High | J32: PR.AA-03
A33: ESBIT-AC-08 | B33: AC-08 | C33: Access Control (AC) | D33: System Use Notification | E33: Configure | F33: Configure a legal warning banner on console, SSH and web management | G33: banner login and banner motd, Junos login message | H33: Banner displayed at login | I33: Level 2 - Medium | J33: GV.PO-01
A34: ESBIT-AC-12 | B34: AC-12 | C34: Access Control (AC) | D34: Session Termination | E34: Configure | F34: Set an idle timeout for management sessions (for example 10 minutes) | G34: exec-timeout, Junos idle-timeout, web admin timeout | H34: Idle session closes | I34: Level 1 - High | J34: PR.AA-03
A35: ESBIT-AC-17 | B35: AC-17 | C35: Access Control (AC) | D35: Remote Access | E35: Configure | F35: Permit management only through SSHv2, HTTPS or VPN from approved sources; disable Telnet and HTTP | G35: transport input ssh, ip http secure-server only, management access lists | H35: Port scan shows only 22/443 from management network | I35: Level 1 - High | J35: PR.IR-01
A36: ESBIT-AC-17(02) | B36: AC-17(02) | C36: Access Control (AC) | D36: Remote Access | Protection of Confidentiality and Integrity Using Encryption | E36: Configure | F36: Encrypt remote-access VPN with strong cipher suites | G36: IPsec IKEv2 with AES-256-GCM, SSL VPN with TLS 1.2 or higher | H36: VPN cipher report | I36: Level 1 - High | J36: PR.IR-01
... A95: ESBIT-SI-08 | B95: SI-08 | C95: System and Information Integrity (SI) | D95: Spam Protection | E95: Install | F95: Deploy an email and spam gateway with filtering and automatic updates | G95: Secure email gateway | H95: Filter policy enabled | I95: Level 2 - Medium | J95: DE.CM-01

Sheet Identity Config Baseline
A1: Identity Configuration Baseline (NIST SP 800-53 Rev. 5 - core configuration items)
A2: Purpose: this sheet turns the NIST SP 800-53 Rev. 5 controls into the core Identity Configuration Baseline for directories (Active Directory, Entra ID, LDAP), identity providers and SSO, privileged access management and identity governance. It lists the settings administrators must configure, implement, install or enable.
A3: Scope: only rows tagged Identity in the Config Baseline sheet are considered, limited to the 3 families AC, IA, PS. Controls for other domains are left to their own baselines.
A4: Selection principle: controls with a similar effect were consolidated so that only the main baseline items remain. Only rows tagged for this domain in the Config Baseline sheet were considered; base controls and the enhancements that add a distinct setting are kept.
A5: Examples use common product terms (Active Directory, Entra ID, Okta, SailPoint, CyberArk) as guidance only; map each item to the products in use. Level is taken from the Config Baseline sheet (Level 1 = mandatory, Level 3 = lowest impact).
A7: Action Type legend
A8: Configure = set a parameter, policy or rule on an existing platform/service.
A9: Implement = build or deploy a mechanism, template, automation or architecture pattern.
A10: Install = install or onboard a tool, agent or scanner.
A11: Enable = turn on a feature, log source or detection service that is off by default.
A13: Coverage by control family
A14: Family | B14: Items | C14: Level 1 | D14: Level 2 | E14: Level 3 | F14: Configuration focus
A15: Access Control (AC) | B15: =COUNTIF($C$21:$C$68,$A15) -> 22 | C15: =COUNTIFS($C$21:$C$68,$A15,$I$21:$I$68,"Level 1*") -> 9 | D15: =COUNTIFS($C$21:$C$68,$A15,$I$21:$I$68,"Level 2*") -> 13 | E15: =COUNTIFS($C$21:$C$68,$A15,$I$21:$I$68,"Level 3*") -> 0 | F15: Covers: Account Management, Access Enforcement, Separation of Duties, Least Privilege, Unsuccessful Logon Attempts, Concurrent Session Control, Session Termination.
A16: Identification and Authentication (IA) | B16: =COUNTIF($C$21:$C$68,$A16) -> 24 | C16: =COUNTIFS($C$21:$C$68,$A16,$I$21:$I$68,"Level 1*") -> 5 | D16: =COUNTIFS($C$21:$C$68,$A16,$I$21:$I$68,"Level 2*") -> 19 | E16: =COUNTIFS($C$21:$C$68,$A16,$I$21:$I$68,"Level 3*") -> 0 | F16: Covers: Identification and Authentication (Organizational Users), Identifier Management, Authenticator Management, Identification and Authentication (Non-organizational Users), Service Identification and Authentication, Re-authentication, Identity Providers and Authorization Servers.
A17: Personnel Security (PS) | B17: =COUNTIF($C$21:$C$68,$A17) -> 2 | C17: =COUNTIFS($C$21:$C$68,$A17,$I$21:$I$68,"Level 1*") -> 0 | D17: =COUNTIFS($C$21:$C$68,$A17,$I$21:$I$68,"Level 2*") -> 2 | E17: =COUNTIFS($C$21:$C$68,$A17,$I$21:$I$68,"Level 3*") -> 0 | F17: Covers: Personnel Termination, Personnel Transfer.
A18: Total | B18: =SUM(B15:B17) -> 48 | C18: =SUM(C15:C17) -> 14 | D18: =SUM(D15:D17) -> 34 | E18: =SUM(E15:E17) -> 0
A20: Control ID New | B20: Control ID | C20: Control Family | D20: Control Name | E20: Action Type | F20: Baseline Setting to Configure | G20: Implementation Example | H20: Verification / Evidence | I20: Level | J20: CSF 2.0 Subcategory ID
A21: ESBIT-AC-02 | B21: AC-02 | C21: Access Control (AC) | D21: Account Management | E21: Configure | F21: Manage all human, service and privileged accounts in one authoritative directory; require owner, approval and expiry; remove shared and unused accounts | G21: Active Directory, Entra ID, Okta, FreeIPA; HR-driven joiner-mover-leaver workflow | H21: Account inventory with owner and last logon; no orphan accounts | I21: Level 1 - High | J21: PR.AA-01
A22: ESBIT-AC-02(01) | B22: AC-02(01) | C22: Access Control (AC) | D22: Account Management | Automated System Account Management | E22: Implement | F22: Automate account creation, change, disable and removal from the HR or IGA source of truth | G22: SailPoint, Entra lifecycle workflows, Okta Lifecycle Management, SCIM connectors | H22: Provisioning logs; reconciliation report shows no drift | I22: Level 2 - Medium | J22: PR.AA-01
A23: ESBIT-AC-02(02) | B23: AC-02(02) | C23: Access Control (AC) | D23: Account Management | Automated Temporary and Emergency Account Management | E23: Configure | F23: Issue temporary and emergency accounts with an automatic expiry and alert on every use | G23: Time-bound accounts in AD, PIM eligible roles, vaulted break-glass accounts | H23: List of temporary accounts with expiry; break-glass alert log | I23: Level 2 - Medium | J23: PR.AA-01
A24: ESBIT-AC-02(03) | B24: AC-02(03) | C24: Access Control (AC) | D24: Account Management | Disable Accounts | E24: Configure | F24: Disable accounts automatically after the inactivity period (for example 45-90 days) or on expiry | G24: AD inactive-account script or GPO, Entra inactive user workflow, IGA rule | H24: Report of disabled inactive accounts; no stale enabled accounts | I24: Level 2 - Medium | J24: PR.AA-01
A25: ESBIT-AC-02(04) | B25: AC-02(04) | C25: Access Control (AC) | D25: Account Management | Automated Audit Actions | E25: Enable | F25: Audit and notify security on account creation, modification, enabling, disabling and removal | G25: AD events 4720-4726 to SIEM, Entra audit logs, IGA notifications | H25: SIEM rule and sample alert for account change | I25: Level 1 - High | J25: PR.AA-01
A26: ESBIT-AC-02(06) | B26: AC-02(06) | C26: Access Control (AC) | D26: Account Management | Dynamic Privilege Management | E26: Implement | F26: Grant privileged access just-in-time with policy-based, time-limited elevation instead of standing rights | G26: Entra PIM, CyberArk or BeyondTrust JIT elevation, sudo with approval | H26: Count of standing privileged accounts; elevation log | I26: Level 2 - Medium | J26: PR.AA-01
A27: ESBIT-AC-02(07) | B27: AC-02(07) | C27: Access Control (AC) | D27: Account Management | Privileged User Accounts | E27: Configure | F27: Keep privileged accounts separate from daily accounts, named per administrator and reviewed on a schedule | G27: Tiered admin accounts, privileged access workstations, PAM vault | H27: Privileged account list and review record | I27: Level 1 - High | J27: PR.AA-01
A28: ESBIT-AC-02(09) | B28: AC-02(09) | C28: Access Control (AC) | D28: Account Management | Restrictions on Use of Shared and Group Accounts | E28: Configure | F28: Prohibit shared and group accounts unless approved; where unavoidable, vault credentials and record each checkout | G28: Password vault checkout with session recording, no shared local admin | H28: Shared account register with approvals | I28: Level 2 - Medium | J28: PR.AA-01
A29: ESBIT-AC-02(11) | B29: AC-02(11) | C29: Access Control (AC) | D29: Account Management | Usage Conditions | E29: Configure | F29: Restrict account use by conditions such as time, location, device compliance and risk level | G29: Entra Conditional Access, Okta sign-on policy, AD logon-hour restrictions | H29: Conditional access policy export; blocked sign-in report | I29: Level 2 - Medium | J29: PR.AA-01
A30: ESBIT-AC-02(12) | B30: AC-02(12) | C30: Access Control (AC) | D30: Account Management | Account Monitoring for Atypical Usage | E30: Enable | F30: Monitor accounts for atypical use (impossible travel, unusual hours, mass access) and report to security | G30: Entra ID Protection, UEBA in SIEM, Okta ThreatInsight | H30: Detection rule list; sample alert | I30: Level 2 - Medium | J30: PR.AA-01
A31: ESBIT-AC-02(13) | B31: AC-02(13) | C31: Access Control (AC) | D31: Account Management | Disable Accounts for High-risk Individuals | E31: Configure | F31: Disable accounts of individuals identified as high risk (for example resigned with notice or under investigation) within the defined time | G31: HR-triggered immediate disable, IGA high-risk flag, PAM session revocation | H31: Disable timestamp versus HR trigger | I31: Level 2 - Medium | J31: PR.AA-01
... A68: ESBIT-PS-05 | B68: PS-05 | C68: Personnel Security (PS) | D68: Personnel Transfer | E68: Implement | F68: On transfer review and adjust access, removing rights no longer needed within the defined time | G68: IGA mover workflow, manager recertification | H68: Mover review records | I68: Level 2 - Medium | J68: GV.RR-04

Sheet Monitoring Config Baseline
A1: Monitoring Configuration Baseline (NIST SP 800-53 Rev. 5 - core configuration items)
A2: Purpose: this sheet turns the NIST SP 800-53 Rev. 5 controls into the core Monitoring Configuration Baseline for logging, SIEM, detection, threat hunting and alerting platforms. It lists the settings administrators must configure, implement, install or enable.
A3: Scope: only rows tagged Monitoring in the Config Baseline sheet are considered, limited to the 5 families AU, CA, IR, RA, SI. Controls for other domains are left to their own baselines.
A4: Selection principle: controls with a similar effect were consolidated so that only the main baseline items remain. Only rows tagged for this domain in the Config Baseline sheet were considered; base controls and the enhancements that add a distinct setting are kept.
A5: Examples use common product terms (Splunk, Microsoft Sentinel, Elastic, EDR, NDR, syslog) as guidance only; map each item to the tools in use. Level is taken from the Config Baseline sheet (Level 1 = mandatory, Level 3 = lowest impact).
A7: Action Type legend
A8: Configure = set a parameter, policy or rule on an existing platform/service.
A9: Implement = build or deploy a mechanism, template, automation or architecture pattern.
A10: Install = install or onboard a tool, agent or scanner.
A11: Enable = turn on a feature, log source or detection service that is off by default.
A13: Coverage by control family
A14: Family | B14: Items | C14: Level 1 | D14: Level 2 | E14: Level 3 | F14: Configuration focus
A15: Audit and Accountability (AU) | B15: =COUNTIF($C$23:$C$58,$A15) -> 21 | C15: =COUNTIFS($C$23:$C$58,$A15,$I$23:$I$58,"Level 1*") -> 11 | D15: =COUNTIFS($C$23:$C$58,$A15,$I$23:$I$58,"Level 2*") -> 10 | E15: =COUNTIFS($C$23:$C$58,$A15,$I$23:$I$58,"Level 3*") -> 0 | F15: Covers: Event Logging, Content of Audit Records, Audit Log Storage Capacity, Response to Audit Logging Process Failures, Audit Record Review, Analysis, and Reporting, Protection of Audit Information, Audit Record Retention, and related items.
A16: Assessment, Authorization, and Monitoring (CA) | B16: =COUNTIF($C$23:$C$58,$A16) -> 1 | C16: =COUNTIFS($C$23:$C$58,$A16,$I$23:$I$58,"Level 1*") -> 0 | D16: =COUNTIFS($C$23:$C$58,$A16,$I$23:$I$58,"Level 2*") -> 1 | E16: =COUNTIFS($C$23:$C$58,$A16,$I$23:$I$58,"Level 3*") -> 0 | F16: Covers: Continuous Monitoring.
A17: Incident Response (IR) | B17: =COUNTIF($C$23:$C$58,$A17) -> 1 | C17: =COUNTIFS($C$23:$C$58,$A17,$I$23:$I$58,"Level 1*") -> 0 | D17: =COUNTIFS($C$23:$C$58,$A17,$I$23:$I$58,"Level 2*") -> 1 | E17: =COUNTIFS($C$23:$C$58,$A17,$I$23:$I$58,"Level 3*") -> 0 | F17: Covers: Incident Handling.
A18: Risk Assessment (RA) | B18: =COUNTIF($C$23:$C$58,$A18) -> 1 | C18: =COUNTIFS($C$23:$C$58,$A18,$I$23:$I$58,"Level 1*") -> 0 | D18: =COUNTIFS($C$23:$C$58,$A18,$I$23:$I$58,"Level 2*") -> 1 | E18: =COUNTIFS($C$23:$C$58,$A18,$I$23:$I$58,"Level 3*") -> 0 | F18: Covers: Threat Hunting.
A19: System and Information Integrity (SI) | B19: =COUNTIF($C$23:$C$58,$A19) -> 12 | C19: =COUNTIFS($C$23:$C$58,$A19,$I$23:$I$58,"Level 1*") -> 3 | D19: =COUNTIFS($C$23:$C$58,$A19,$I$23:$I$58,"Level 2*") -> 9 | E19: =COUNTIFS($C$23:$C$58,$A19,$I$23:$I$58,"Level 3*") -> 0 | F19: Covers: System Monitoring.
A20: Total | B20: =SUM(B15:B19) -> 36 | C20: =SUM(C15:C19) -> 14 | D20: =SUM(D15:D19) -> 22 | E20: =SUM(E15:E19) -> 0
A22: Control ID New | B22: Control ID | C22: Control Family | D22: Control Name | E22: Action Type | F22: Baseline Setting to Configure | G22: Implementation Example | H22: Verification / Evidence | I22: Level | J22: CSF 2.0 Subcategory ID
A23: ESBIT-AU-02 | B23: AU-02 | C23: Audit and Accountability (AU) | D23: Event Logging | E23: Enable | F23: Enable audit logging for authentication, privileged actions, configuration change, security events and data access on every monitored system | G23: Windows and Linux audit policy, auditd, application audit logs, cloud audit logs | H23: Logging coverage report per system | I23: Level 1 - High | J23: PR.PS-04
A24: ESBIT-AU-02(03) | B24: AU-02(03) | C24: Audit and Accountability (AU) | D24: Event Logging | Reviews and Updates | E24: Implement | F24: Review and update the list of logged event types on a fixed schedule and after major change | G24: Annual logging standard review, detection engineering backlog | H24: Review record and change log of event list | I24: Level 2 - Medium | J24: PR.PS-04
A25: ESBIT-AU-03 | B25: AU-03 | C25: Audit and Accountability (AU) | D25: Content of Audit Records | E25: Configure | F25: Ensure each record has time, source, identity, event, resource and outcome in a structured format | G25: JSON or CEF logging, agent parsing rules | H25: Sample record review | I25: Level 1 - High | J25: PR.PS-04
A26: ESBIT-AU-03(01) | B26: AU-03(01) | C26: Audit and Accountability (AU) | D26: Content of Audit Records | Additional Audit Information | E26: Configure | F26: Add extra detail to records where needed, such as source address, user agent and command line | G26: Sysmon, command line auditing, web access log fields | H26: Sample records show added fields | I26: Level 1 - High | J26: PR.PS-04
A27: ESBIT-AU-04 | B27: AU-04 | C27: Audit and Accountability (AU) | D27: Audit Log Storage Capacity | E27: Configure | F27: Size log storage for the retention period and set capacity alarms and lifecycle rules | G27: SIEM index sizing, hot-warm-cold tiers, storage alerts | H27: Capacity report and alarm configuration | I27: Level 2 - Medium | J27: PR.IR-04
A28: ESBIT-AU-05 | B28: AU-05 | C28: Audit and Accountability (AU) | D28: Response to Audit Logging Process Failures | E28: Configure | F28: Alert on audit logging failures such as agent stop, source silence or full storage | G28: SIEM silent-source detection, agent health alerts | H28: Alert rule; test of a stopped agent | I28: Level 1 - High | J28: DE.CM-09
A29: ESBIT-AU-05(02) | B29: AU-05(02) | C29: Audit and Accountability (AU) | D29: Response to Audit Logging Process Failures | Real-time Alerts | E29: Enable | F29: Raise real-time alerts to responders on audit failure events | G29: Alert routing to on-call and ticketing | H29: Alert route test | I29: Level 2 - Medium | J29: DE.CM-09
A30: ESBIT-AU-05(05) | B30: AU-05(05) | C30: Audit and Accountability (AU) | D30: Response to Audit Logging Process Failures | Alternate Audit Logging Capability | E30: Implement | F30: Provide an alternate logging path if the primary logging capability fails | G30: Secondary syslog relay, local buffering with replay, dual forwarders | H30: Failover test result | I30: Level 1 - High | J30: DE.CM-09
A31: ESBIT-AU-06 | B31: AU-06 | C31: Audit and Accountability (AU) | D31: Audit Record Review, Analysis, and Reporting | E31: Implement | F31: Review and analyze audit records at a defined frequency and report findings; use automated analytics for scale | G31: SIEM analytics rules, daily SOC review, weekly reports | H31: Review record and sample findings | I31: Level 2 - Medium | J31: DE.AE-02
A32: ESBIT-AU-06(03) | B32: AU-06(03) | C32: Audit and Accountability (AU) | D32: Audit Record Review, Analysis, and Reporting | Correlate Audit Record Repositories | E32: Implement | F32: Correlate audit records across systems, network, endpoint and cloud sources | G32: SIEM correlation rules across log sources | H32: Correlation rule list and sample alert | I32: Level 2 - Medium | J32: DE.AE-02
A33: ESBIT-AU-06(05) | B33: AU-06(05) | C33: Audit and Accountability (AU) | D33: Audit Record Review, Analysis, and Reporting | Integrated Analysis of Audit Records | E33: Implement | F33: Integrate log analysis with vulnerability, asset and threat intelligence data | G33: SIEM enrichment with CMDB, scanner and threat feeds | H33: Enriched alert example | I33: Level 2 - Medium | J33: DE.AE-02
... A58: ESBIT-SI-04(24) | B58: SI-04(24) | C58: System and Information Integrity (SI) | D58: System Monitoring | Indicators of Compromise | E58: Enable | F58: Monitor for indicators of compromise from threat intelligence | G58: IOC feeds in SIEM and EDR, retro-hunt | H58: IOC feed configuration and matches log | I58: Level 2 - Medium | J58: DE.CM-01

Sheet Database Config Baseline
A1: Database Configuration Baseline (NIST SP 800-53 Rev. 5 - core configuration items)
A2: Purpose: this sheet turns the NIST SP 800-53 Rev. 5 controls into the core Database Configuration Baseline for relational and NoSQL database engines, data stores and their backups. It lists the settings administrators must configure, implement, install or enable.
A3: Scope: only rows tagged Database in the Config Baseline sheet are considered, limited to the 7 families AC, CM, CP, IA, RA, SC, SI. Database auditing is covered by the Monitoring baseline and AC-06(09) here, because AU controls are not tagged Database in the master sheet.
A4: Selection principle: controls with a similar effect were consolidated so that only the main baseline items remain. Only rows tagged for this domain in the Config Baseline sheet were considered; base controls and the enhancements that add a distinct setting are kept.
A5: Examples use common engine terms (Oracle, SQL Server, PostgreSQL, MySQL, MongoDB) as guidance only; map each item to the exact syntax of the engines in use. Level is taken from the Config Baseline sheet (Level 1 = mandatory, Level 3 = lowest impact).
A7: Action Type legend
A8: Configure = set a parameter, policy or rule on an existing platform/service.
A9: Implement = build or deploy a mechanism, template, automation or architecture pattern.
A10: Install = install or onboard a tool, agent or scanner.
A11: Enable = turn on a feature, log source or detection service that is off by default.
A13: Coverage by control family
A14: Family | B14: Items | C14: Level 1 | D14: Level 2 | E14: Level 3 | F14: Configuration focus
A15: Access Control (AC) | B15: =COUNTIF($C$25:$C$66,$A15) -> 15 | C15: =COUNTIFS($C$25:$C$66,$A15,$I$25:$I$66,"Level 1*") -> 9 | D15: =COUNTIFS($C$25:$C$66,$A15,$I$25:$I$66,"Level 2*") -> 6 | E15: =COUNTIFS($C$25:$C$66,$A15,$I$25:$I$66,"Level 3*") -> 0 | F15: Covers: Account Management, Access Enforcement, Least Privilege, Concurrent Session Control, Session Termination.
A16: Configuration Management (CM) | B16: =COUNTIF($C$25:$C$66,$A16) -> 5 | C16: =COUNTIFS($C$25:$C$66,$A16,$I$25:$I$66,"Level 1*") -> 2 | D16: =COUNTIFS($C$25:$C$66,$A16,$I$25:$I$66,"Level 2*") -> 3 | E16: =COUNTIFS($C$25:$C$66,$A16,$I$25:$I$66,"Level 3*") -> 0 | F16: Covers: Baseline Configuration, Configuration Settings.
A17: Contingency Planning (CP) | B17: =COUNTIF($C$25:$C$66,$A17) -> 6 | C17: =COUNTIFS($C$25:$C$66,$A17,$I$25:$I$66,"Level 1*") -> 3 | D17: =COUNTIFS($C$25:$C$66,$A17,$I$25:$I$66,"Level 2*") -> 3 | E17: =COUNTIFS($C$25:$C$66,$A17,$I$25:$I$66,"Level 3*") -> 0 | F17: Covers: System Backup, System Recovery and Reconstitution.
A18: Identification and Authentication (IA) | B18: =COUNTIF($C$25:$C$66,$A18) -> 6 | C18: =COUNTIFS($C$25:$C$66,$A18,$I$25:$I$66,"Level 1*") -> 1 | D18: =COUNTIFS($C$25:$C$66,$A18,$I$25:$I$66,"Level 2*") -> 5 | E18: =COUNTIFS($C$25:$C$66,$A18,$I$25:$I$66,"Level 3*") -> 0 | F18: Covers: Authenticator Management.
A19: Risk Assessment (RA) | B19: =COUNTIF($C$25:$C$66,$A19) -> 3 | C19: =COUNTIFS($C$25:$C$66,$A19,$I$25:$I$66,"Level 1*") -> 2 | D19: =COUNTIFS($C$25:$C$66,$A19,$I$25:$I$66,"Level 2*") -> 1 | E19: =COUNTIFS($C$25:$C$66,$A19,$I$25:$I$66,"Level 3*") -> 0 | F19: Covers: Vulnerability Monitoring and Scanning.
A20: System and Communications Protection (SC) | B20: =COUNTIF($C$25:$C$66,$A20) -> 3 | C20: =COUNTIFS($C$25:$C$66,$A20,$I$25:$I$66,"Level 1*") -> 3 | D20: =COUNTIFS($C$25:$C$66,$A20,$I$25:$I$66,"Level 2*") -> 0 | E20: =COUNTIFS($C$25:$C$66,$A20,$I$25:$I$66,"Level 3*") -> 0 | F20: Covers: Protection of Information at Rest.
A21: System and Information Integrity (SI) | B21: =COUNTIF($C$25:$C$66,$A21) -> 4 | C21: =COUNTIFS($C$25:$C$66,$A21,$I$25:$I$66,"Level 1*") -> 1 | D21: =COUNTIFS($C$25:$C$66,$A21,$I$25:$I$66,"Level 2*") -> 3 | E21: =COUNTIFS($C$25:$C$66,$A21,$I$25:$I$66,"Level 3*") -> 0 | F21: Covers: Information Input Validation, Information Management and Retention.
A22: Total | B22: =SUM(B15:B21) -> 42 | C22: =SUM(C15:C21) -> 21 | D22: =SUM(D15:D21) -> 21 | E22: =SUM(E15:E21) -> 0
A24: Control ID New | B24: Control ID | C24: Control Family | D24: Control Name | E24: Action Type | F24: Baseline Setting to Configure | G24: Implementation Example | H24: Verification / Evidence | I24: Level | J24: CSF 2.0 Subcategory ID
A25: ESBIT-AC-02 | B25: AC-02 | C25: Access Control (AC) | D25: Account Management | E25: Configure | F25: Manage database accounts (human, application, service, DBA) centrally; require owner and approval, lock or remove default and unused accounts | G25: Oracle, SQL Server, PostgreSQL, MySQL and MongoDB users via directory integration (AD, LDAP, Kerberos) | H25: Database user list with owner; default account status | I25: Level 1 - High | J25: PR.AA-01
A26: ESBIT-AC-02(03) | B26: AC-02(03) | C26: Access Control (AC) | D26: Account Management | Disable Accounts | E26: Configure | F26: Disable database accounts that are inactive beyond the policy period | G26: Scheduled job to lock inactive users, profile with password lifetime and inactive limit | H26: Inactive account report | I26: Level 2 - Medium | J26: PR.AA-01
A27: ESBIT-AC-02(04) | B27: AC-02(04) | C27: Access Control (AC) | D27: Account Management | Automated Audit Actions | E27: Enable | F27: Audit and alert on creation, modification, lock and drop of database accounts and roles | G27: Oracle Unified Audit, SQL Server Audit, pgAudit, MySQL audit plugin | H27: Audit entries for account DDL in SIEM | I27: Level 1 - High | J27: PR.AA-01
A28: ESBIT-AC-02(07) | B28: AC-02(07) | C28: Access Control (AC) | D28: Account Management | Privileged User Accounts | E28: Configure | F28: Keep DBA and other privileged database accounts named, separate from application accounts and reviewed regularly | G28: Named DBA accounts, no shared SYS or sa use, PAM vaulting | H28: Privileged account list and review record | I28: Level 1 - High | J28: PR.AA-01
A29: ESBIT-AC-02(09) | B29: AC-02(09) | C29: Access Control (AC) | D29: Account Management | Restrictions on Use of Shared and Group Accounts | E29: Configure | F29: Prohibit shared DBA and application logins; where unavoidable, vault credentials and record checkout | G29: Vaulted shared credentials with session recording | H29: Shared account register | I29: Level 2 - Medium | J29: PR.AA-01
A30: ESBIT-AC-03 | B30: AC-03 | C30: Access Control (AC) | D30: Access Enforcement | E30: Configure | F30: Enforce authorization on all database objects with deny by default; no access through PUBLIC grants | G30: GRANT and REVOKE policy, revoke PUBLIC privileges, schema-level permissions | H30: Privilege report per schema; PUBLIC grant audit | I30: Level 1 - High | J30: PR.AA-05
A31: ESBIT-AC-03(07) | B31: AC-03(07) | C31: Access Control (AC) | D31: Access Enforcement | Role-based Access Control | E31: Configure | F31: Use database roles mapped to job functions and grant roles instead of direct privileges | G31: Roles for read, write, admin; role-based grants in scripts | H31: Role-to-privilege matrix | I31: Level 2 - Medium | J31: PR.AA-05
A32: ESBIT-AC-03(11) | B32: AC-03(11) | C32: Access Control (AC) | D32: Access Enforcement | Restrict Access to Specific Information Types | E32: Configure | F32: Restrict access to sensitive columns and rows by information type | G32: Row-level security, column-level grants, dynamic data masking, Oracle Data Redaction | H32: Masking and row policy export | I32: Level 2 - Medium | J32: PR.AA-05
A33: ESBIT-AC-03(13) | B33: AC-03(13) | C33: Access Control (AC) | D33: Access Enforcement | Attribute-based Access Control | E33: Configure | F33: Where supported, use attribute-based row and object access decisions | G33: Oracle VPD, PostgreSQL row-level security policies, SQL Server security predicates | H33: Policy definition export | I33: Level 2 - Medium | J33: PR.AA-05
A34: ESBIT-AC-06 | B34: AC-06 | C34: Access Control (AC) | D34: Least Privilege | E34: Configure | F34: Give applications and users only the minimum privileges; no DBA rights for applications | G34: Least-privilege application schema owners, separate owner and runtime users | H34: Privilege review; count of accounts with DBA rights | I34: Level 1 - High | J34: PR.AA-05
A35: ESBIT-AC-06(05) | B35: AC-06(05) | C35: Access Control (AC) | D35: Least Privilege | Privileged Accounts | E35: Configure | F35: Restrict privileged database roles (sysadmin, SYSDBA, superuser) to named administrators with MFA and no daily use | G35: PAM-brokered DBA access, sysadmin role membership limited | H35: Privileged role membership list | I35: Level 1 - High | J35: PR.AA-05
... A66: ESBIT-SI-12 | B66: SI-12 | C66: System and Information Integrity (SI) | D66: Information Management and Retention | E66: Configure | F66: Manage retention and disposal of database records per policy, including archival and secure deletion | G66: Retention jobs, partitioning and purge, archive tier | H66: Retention schedule and purge logs | I66: Level 2 - Medium | J66: PR.DS-01

Sheet Application Config Baseline
A1: Application Configuration Baseline (NIST SP 800-53 Rev. 5 - core configuration items)
A2: Purpose: this sheet turns the NIST SP 800-53 Rev. 5 controls into the core Application Configuration Baseline for business applications, web and API services, operating systems and middleware that host them, and the secure development pipeline. It lists the settings administrators and developers must configure, implement, install or enable.
A3: Scope: only rows tagged Application in the Config Baseline sheet are considered, limited to the 10 families AC, AU, CM, CP, IA, PL, RA, SA, SC, SI. Many design-level SA and SC enhancements (for example SA-08 sub-principles, SC-30 to SC-51) are consolidated into the main items SA-03, SA-08, SA-11, SA-15 and SC-39.
A4: Selection principle: controls with a similar effect were consolidated so that only the main baseline items remain. Only rows tagged for this domain in the Config Baseline sheet were considered; base controls and the enhancements that add a distinct setting are kept.
A5: Examples use common terms (CIS Benchmarks, CI/CD, SAST, DAST, WAF, OIDC) as guidance only; map each item to the stack in use. Level is taken from the Config Baseline sheet (Level 1 = mandatory, Level 3 = lowest impact).
A7: Action Type legend
A8: Configure = set a parameter, policy or rule on an existing platform/service.
A9: Implement = build or deploy a mechanism, template, automation or architecture pattern.
A10: Install = install or onboard a tool, agent or scanner.
A11: Enable = turn on a feature, log source or detection service that is off by default.
A13: Coverage by control family
A14: Family | B14: Items | C14: Level 1 | D14: Level 2 | E14: Level 3 | F14: Configuration focus
A15: Access Control (AC) | B15: =COUNTIF($C$28:$C$117,$A15) -> 12 | C15: =COUNTIFS($C$28:$C$117,$A15,$I$28:$I$117,"Level 1*") -> 5 | D15: =COUNTIFS($C$28:$C$117,$A15,$I$28:$I$117,"Level 2*") -> 7 | E15: =COUNTIFS($C$28:$C$117,$A15,$I$28:$I$117,"Level 3*") -> 0 | F15: Covers: Access Enforcement, Separation of Duties, Least Privilege, Unsuccessful Logon Attempts, System Use Notification, Session Termination, Permitted Actions Without Identification or Authentication, and related items.
A16: Audit and Accountability (AU) | B16: =COUNTIF($C$28:$C$117,$A16) -> 3 | C16: =COUNTIFS($C$28:$C$117,$A16,$I$28:$I$117,"Level 1*") -> 2 | D16: =COUNTIFS($C$28:$C$117,$A16,$I$28:$I$117,"Level 2*") -> 0 | E16: =COUNTIFS($C$28:$C$117,$A16,$I$28:$I$117,"Level 3*") -> 1 | F16: Covers: Time Stamps, Protection of Audit Information, Non-repudiation.
A17: Configuration Management (CM) | B17: =COUNTIF($C$28:$C$117,$A17) -> 14 | C17: =COUNTIFS($C$28:$C$117,$A17,$I$28:$I$117,"Level 1*") -> 7 | D17: =COUNTIFS($C$28:$C$117,$A17,$I$28:$I$117,"Level 2*") -> 5 | E17: =COUNTIFS($C$28:$C$117,$A17,$I$28:$I$117,"Level 3*") -> 2 | F17: Covers: Baseline Configuration, Configuration Change Control, Access Restrictions for Change, Configuration Settings, Least Functionality, System Component Inventory, Software Usage Restrictions, and related items.
A18: Contingency Planning (CP) | B18: =COUNTIF($C$28:$C$117,$A18) -> 3 | C18: =COUNTIFS($C$28:$C$117,$A18,$I$28:$I$117,"Level 1*") -> 2 | D18: =COUNTIFS($C$28:$C$117,$A18,$I$28:$I$117,"Level 2*") -> 1 | E18: =COUNTIFS($C$28:$C$117,$A18,$I$28:$I$117,"Level 3*") -> 0 | F18: Covers: System Backup, System Recovery and Reconstitution.
A19: Identification and Authentication (IA) | B19: =COUNTIF($C$28:$C$117,$A19) -> 13 | C19: =COUNTIFS($C$28:$C$117,$A19,$I$28:$I$117,"Level 1*") -> 6 | D19: =COUNTIFS($C$28:$C$117,$A19,$I$28:$I$117,"Level 2*") -> 7 | E19: =COUNTIFS($C$28:$C$117,$A19,$I$28:$I$117,"Level 3*") -> 0 | F19: Covers: Identification and Authentication (Organizational Users), Device Identification and Authentication, Authenticator Management, Authentication Feedback, Identification and Authentication (Non-organizational Users), Service Identification and Authentication, Re-authentication.
A20: Planning (PL) | B20: =COUNTIF($C$28:$C$117,$A20) -> 1 | C20: =COUNTIFS($C$28:$C$117,$A20,$I$28:$I$117,"Level 1*") -> 0 | D20: =COUNTIFS($C$28:$C$117,$A20,$I$28:$I$117,"Level 2*") -> 1 | E20: =COUNTIFS($C$28:$C$117,$A20,$I$28:$I$117,"Level 3*") -> 0 | F20: Covers: Security and Privacy Architectures.
A21: Risk Assessment (RA) | B21: =COUNTIF($C$28:$C$117,$A21) -> 3 | C21: =COUNTIFS($C$28:$C$117,$A21,$I$28:$I$117,"Level 1*") -> 2 | D21: =COUNTIFS($C$28:$C$117,$A21,$I$28:$I$117,"Level 2*") -> 1 | E21: =COUNTIFS($C$28:$C$117,$A21,$I$28:$I$117,"Level 3*") -> 0 | F21: Covers: Vulnerability Monitoring and Scanning.
A22: System and Services Acquisition (SA) | B22: =COUNTIF($C$28:$C$117,$A22) -> 16 | C22: =COUNTIFS($C$28:$C$117,$A22,$I$28:$I$117,"Level 1*") -> 0 | D22: =COUNTIFS($C$28:$C$117,$A22,$I$28:$I$117,"Level 2*") -> 3 | E22: =COUNTIFS($C$28:$C$117,$A22,$I$28:$I$117,"Level 3*") -> 13 | F22: Covers: System Development Life Cycle, Security and Privacy Engineering Principles, Developer Configuration Management, Developer Testing and Evaluation, Development Process, Standards, and Tools, Unsupported System Components.
A23: System and Communications Protection (SC) | B23: =COUNTIF($C$28:$C$117,$A23) -> 10 | C23: =COUNTIFS($C$28:$C$117,$A23,$I$28:$I$117,"Level 1*") -> 7 | D23: =COUNTIFS($C$28:$C$117,$A23,$I$28:$I$117,"Level 2*") -> 3 | E23: =COUNTIFS($C$28:$C$117,$A23,$I$28:$I$117,"Level 3*") -> 0 | F23: Covers: Network Disconnect, Cryptographic Key Establishment and Management, Cryptographic Protection, Mobile Code, Session Authenticity, Fail in Known State, Protection of Information at Rest, and related items.
A24: System and Information Integrity (SI) | B24: =COUNTIF($C$28:$C$117,$A24) -> 15 | C24: =COUNTIFS($C$28:$C$117,$A24,$I$28:$I$117,"Level 1*") -> 8 | D24: =COUNTIFS($C$28:$C$117,$A24,$I$28:$I$117,"Level 2*") -> 6 | E24: =COUNTIFS($C$28:$C$117,$A24,$I$28:$I$117,"Level 3*") -> 1 | F24: Covers: Flaw Remediation, Malicious Code Protection, System Monitoring, Security Alerts, Advisories, and Directives, Software, Firmware, and Information Integrity, Information Input Validation, Error Handling, and related items.
A25: Total | B25: =SUM(B15:B24) -> 90 | C25: =SUM(C15:C24) -> 39 | D25: =SUM(D15:D24) -> 34 | E25: =SUM(E15:E24) -> 17
A27: Control ID New | B27: Control ID | C27: Control Family | D27: Control Name | E27: Action Type | F27: Baseline Setting to Configure | G27: Implementation Example | H27: Verification / Evidence | I27: Level | J27: CSF 2.0 Subcategory ID
A28: ESBIT-AC-03 | B28: AC-03 | C28: Access Control (AC) | D28: Access Enforcement | E28: Configure | F28: Enforce authorization on every application function and data object server-side; deny by default | G28: Application RBAC checks, API gateway authorization, framework authorization middleware | H28: Authorization test cases; access matrix | I28: Level 1 - High | J28: PR.AA-05
A29: ESBIT-AC-03(07) | B29: AC-03(07) | C29: Access Control (AC) | D29: Access Enforcement | Role-based Access Control | E29: Configure | F29: Implement role-based access with roles mapped to job functions in the application | G29: Role tables, IdP group claims mapped to app roles | H29: Role-to-function matrix | I29: Level 2 - Medium | J29: PR.AA-05
A30: ESBIT-AC-03(12) | B30: AC-03(12) | C30: Access Control (AC) | D30: Access Enforcement | Assert and Enforce Application Access | E30: Configure | F30: Assert and enforce application-level access for each session and API call | G30: Token scope validation, per-request authorization, OAuth scopes | H30: API authorization test results | I30: Level 2 - Medium | J30: PR.AA-05
A31: ESBIT-AC-03(13) | B31: AC-03(13) | C31: Access Control (AC) | D31: Access Enforcement | Attribute-based Access Control | E31: Configure | F31: Where supported, use attribute-based access (tenant, department, data class) for application decisions | G31: Policy engines such as OPA, attribute claims in tokens | H31: Policy definitions and test results | I31: Level 2 - Medium | J31: PR.AA-05
A32: ESBIT-AC-05 | B32: AC-05 | C32: Access Control (AC) | D32: Separation of Duties | E32: Implement | F32: Separate duties in the application so one user cannot initiate and approve a sensitive transaction | G32: Maker-checker workflow, separate roles for deploy and approve | H32: SoD test cases | I32: Level 2 - Medium | J32: PR.AA-05
A33: ESBIT-AC-06 | B33: AC-06 | C33: Access Control (AC) | D33: Least Privilege | E33: Configure | F33: Run the application and its service accounts with minimum privileges; no administrator or root runtime | G33: Dedicated service accounts, container non-root user, scoped API keys | H33: Service account privilege review | I33: Level 1 - High | J33: PR.AA-05
A34: ESBIT-AC-06(10) | B34: AC-06(10) | C34: Access Control (AC) | D34: Least Privilege | Prohibit Non-privileged Users from Executing Privileged Functions | E34: Configure | F34: Prevent ordinary users from invoking privileged application functions | G34: Admin endpoints separated and role-restricted, function-level checks | H34: Penetration test authorization findings | I34: Level 1 - High | J34: PR.AA-05
A35: ESBIT-AC-07 | B35: AC-07 | C35: Access Control (AC) | D35: Unsuccessful Logon Attempts | E35: Configure | F35: Limit failed logins in the application with lockout or throttling and generic error messages | G35: Account lockout, rate limiting, CAPTCHA after failures | H35: Lockout configuration; test result | I35: Level 1 - High | J35: PR.AA-03
A36: ESBIT-AC-08 | B36: AC-08 | C36: Access Control (AC) | D36: System Use Notification | E36: Configure | F36: Display the system use notification before granting access to the application where required | G36: Login banner in web application and admin consoles | H36: Screenshot of banner | I36: Level 2 - Medium | J36: GV.PO-01
A37: ESBIT-AC-12 | B37: AC-12 | C37: Access Control (AC) | D37: Session Termination | E37: Configure | F37: Expire application sessions after the idle and absolute timeouts defined by policy | G37: Session timeout settings in framework or IdP, server-side invalidation | H37: Session configuration export | I37: Level 1 - High | J37: PR.AA-03
A38: ESBIT-AC-14 | B38: AC-14 | C38: Access Control (AC) | D38: Permitted Actions Without Identification or Authentication | E38: Configure | F38: Define the small set of actions allowed without authentication and block all others | G38: Public endpoint allow-list, health check exceptions only | H38: Unauthenticated endpoint inventory | I38: Level 2 - Medium | J38: PR.AA-05
... A117: ESBIT-SI-16 | B117: SI-16 | C117: System and Information Integrity (SI) | D117: Memory Protection | E117: Configure | F117: Enable memory protection such as ASLR, DEP/NX and stack protection | G117: OS hardening defaults, compiler hardening flags | H117: Hardening scan results | I117: Level 1 - High | J117: PR.PS-05

Sheet Backup Config Baseline
A1: Backup Configuration Baseline (NIST SP 800-53 Rev. 5 - core configuration items)
A2: Purpose: this sheet turns the NIST SP 800-53 Rev. 5 controls into the core Backup and Recovery Configuration Baseline for backup platforms, alternate storage and recovery. It lists the settings administrators must configure, implement, install or enable.
A3: Scope: only rows tagged Backup in the Config Baseline sheet are considered; all of them belong to the 1 family CP. Many CP-02, CP-03 and CP-04 enhancements are process items and are consolidated into CP-02 and CP-04.
A4: Selection principle: controls with a similar effect were consolidated so that only the main baseline items remain. Only rows tagged for this domain in the Config Baseline sheet were considered; base controls and the enhancements that add a distinct setting are kept.
A5: Examples use common product terms (Veeam, Commvault, Veritas, Rubrik, AWS Backup) as guidance only; map each item to the backup tools in use. Level is taken from the Config Baseline sheet (Level 1 = mandatory, Level 3 = lowest impact).
A7: Action Type legend
A8: Configure = set a parameter, policy or rule on an existing platform/service.
A9: Implement = build or deploy a mechanism, template, automation or architecture pattern.
A10: Install = install or onboard a tool, agent or scanner.
A11: Enable = turn on a feature, log source or detection service that is off by default.
A13: Coverage by control family
A14: Family | B14: Items | C14: Level 1 | D14: Level 2 | E14: Level 3 | F14: Configuration focus
A15: Contingency Planning (CP) | B15: =COUNTIF($C$19:$C$33,$A15) -> 15 | C15: =COUNTIFS($C$19:$C$33,$A15,$I$19:$I$33,"Level 1*") -> 3 | D15: =COUNTIFS($C$19:$C$33,$A15,$I$19:$I$33,"Level 2*") -> 7 | E15: =COUNTIFS($C$19:$C$33,$A15,$I$19:$I$33,"Level 3*") -> 5 | F15: Covers: Contingency Plan, Contingency Plan Testing, Alternate Storage Site, System Backup, System Recovery and Reconstitution.
A16: Total | B16: =SUM(B15:B15) -> 15 | C16: =SUM(C15:C15) -> 3 | D16: =SUM(D15:D15) -> 7 | E16: =SUM(E15:E15) -> 5
A18: Control ID New | B18: Control ID | C18: Control Family | D18: Control Name | E18: Action Type | F18: Baseline Setting to Configure | G18: Implementation Example | H18: Verification / Evidence | I18: Level | J18: CSF 2.0 Subcategory ID
A19: ESBIT-CP-02 | B19: CP-02 | C19: Contingency Planning (CP) | D19: Contingency Plan | E19: Implement | F19: Document a contingency plan with recovery priorities, RTO and RPO for each system and backup scope | G19: Business impact analysis, DR plan in the GRC tool | H19: Approved plan with RTO and RPO table | I19: Level 3 - Low | J19: PR.IR-03
A20: ESBIT-CP-04 | B20: CP-04 | C20: Contingency Planning (CP) | D20: Contingency Plan Testing | E20: Implement | F20: Test recovery and failover at least annually and after major change, recording results and fixes | G20: Scheduled DR test, tabletop and technical failover exercise | H20: Test report with results and actions | I20: Level 3 - Low | J20: ID.IM-02
A21: ESBIT-CP-06 | B21: CP-06 | C21: Contingency Planning (CP) | D21: Alternate Storage Site | E21: Configure | F21: Keep backup copies at an alternate storage site in a separate location or region | G21: Offsite tape vault, second data center, cross-region object storage | H21: Alternate site backup inventory | I21: Level 2 - Medium | J21: PR.IR-03
A22: ESBIT-CP-06(01) | B22: CP-06(01) | C22: Contingency Planning (CP) | D22: Alternate Storage Site | Separation from Primary Site | E22: Configure | F22: Separate the alternate storage site from the primary so one event cannot affect both | G22: Different geography and power or network dependency | H22: Site separation statement | I22: Level 3 - Low | J22: PR.IR-03
A23: ESBIT-CP-06(02) | B23: CP-06(02) | C23: Contingency Planning (CP) | D23: Alternate Storage Site | Recovery Time and Recovery Point Objectives | E23: Configure | F23: Set replication and backup frequency to meet RTO and RPO at the alternate site | G23: Replication lag monitoring, backup schedule aligned to RPO | H23: Replication lag and schedule versus RPO | I23: Level 3 - Low | J23: PR.IR-03
A24: ESBIT-CP-09 | B24: CP-09 | C24: Contingency Planning (CP) | D24: System Backup | E24: Configure | F24: Back up user and system data and configuration on a schedule; define retention and scope | G24: Veeam, Commvault, Veritas, Rubrik, AWS Backup jobs | H24: Backup job report and policy export | I24: Level 1 - High | J24: PR.DS-11
A25: ESBIT-CP-09(01) | B25: CP-09(01) | C25: Contingency Planning (CP) | D25: System Backup | Testing for Reliability and Integrity | E25: Enable | F25: Verify backup reliability and integrity with automated checks | G25: Backup verification jobs, checksum and health checks | H25: Verification report | I25: Level 1 - High | J25: PR.DS-11
A26: ESBIT-CP-09(02) | B26: CP-09(02) | C26: Contingency Planning (CP) | D26: System Backup | Test Restoration Using Sampling | E26: Implement | F26: Restore a sample of backups regularly to prove the data can be recovered | G26: Scheduled restore tests in isolated sandbox (SureBackup or similar) | H26: Restore test log | I26: Level 2 - Medium | J26: PR.DS-11
A27: ESBIT-CP-09(03) | B27: CP-09(03) | C27: Contingency Planning (CP) | D27: System Backup | Separate Storage for Critical Information | E27: Configure | F27: Store backups of critical information in a separate facility or in an isolated, immutable store | G27: Immutable repository, air-gapped copy, vault with WORM | H27: Immutability and isolation settings | I27: Level 2 - Medium | J27: PR.DS-11
A28: ESBIT-CP-09(05) | B28: CP-09(05) | C28: Contingency Planning (CP) | D28: System Backup | Transfer to Alternate Storage Site | E28: Configure | F28: Transfer backups to the alternate storage site automatically within the required time | G28: Backup copy jobs, cross-site replication | H28: Copy job success report | I28: Level 2 - Medium | J28: PR.DS-11
A29: ESBIT-CP-09(06) | B29: CP-09(06) | C29: Contingency Planning (CP) | D29: System Backup | Redundant Secondary System | E29: Implement | F29: Keep a redundant secondary system ready to take over from backup data | G29: Standby environment, replicated VMs, pilot light | H29: Failover test record | I29: Level 2 - Medium | J29: PR.DS-11
... A33: ESBIT-CP-10(04) | B33: CP-10(04) | C33: Contingency Planning (CP) | D33: System Recovery and Reconstitution | Restore Within Time Period | E33: Implement | F33: Restore systems within the recovery time objective and verify it in tests | G33: Recovery orchestration with timed steps | H33: Measured recovery time versus RTO | I33: Level 3 - Low | J33: RC.RP-05

Sheet Governance Config Baseline
A1: Governance Configuration Baseline (NIST SP 800-53 Rev. 5 - core control items)
A2: Purpose: this sheet lists the governance, policy, training, assessment, incident process, privacy and program controls of NIST SP 800-53 Rev. 5 that support the technical baselines. They are process controls, so Action Type mostly means Implement and Evidence means documents and records rather than device settings.
A3: Scope: only rows tagged Governance in the Config Baseline sheet are considered, limited to the 19 families AC, AT, AU, CA, CM, CP, IA, IR, MA, PE, PL, PM, PS, PT, RA, SA, SC, SI, SR. The 18 policy and procedures controls (-01) are kept one per family; program management, privacy and training enhancements are consolidated into the main items.
A4: Selection principle: controls with a similar effect were consolidated so that only the main baseline items remain. Only rows tagged for this domain in the Config Baseline sheet were considered; base controls and the enhancements that add a distinct setting are kept.
A5: Examples name artefacts (policy in a GRC tool, LMS, risk register, tabletop exercise) as guidance only; adapt to the organization. Level is taken from the Config Baseline sheet (Level 1 = mandatory, Level 3 = lowest impact).
A7: Action Type legend
A8: Configure = set a parameter, policy or rule on an existing platform/service.
A9: Implement = build or deploy a mechanism, template, automation or architecture pattern.
A10: Install = install or onboard a tool, agent or scanner.
A11: Enable = turn on a feature, log source or detection service that is off by default.
A13: Coverage by control family
A14: Family | B14: Items | C14: Level 1 | D14: Level 2 | E14: Level 3 | F14: Configuration focus
A15: Access Control (AC) | B15: =COUNTIF($C$37:$C$78,$A15) -> 1 | C15: =COUNTIFS($C$37:$C$78,$A15,$I$37:$I$78,"Level 1*") -> 0 | D15: =COUNTIFS($C$37:$C$78,$A15,$I$37:$I$78,"Level 2*") -> 0 | E15: =COUNTIFS($C$37:$C$78,$A15,$I$37:$I$78,"Level 3*") -> 1 | F15: Covers: Policy and Procedures.
A16: Awareness and Training (AT) | B16: =COUNTIF($C$37:$C$78,$A16) -> 4 | C16: =COUNTIFS($C$37:$C$78,$A16,$I$37:$I$78,"Level 1*") -> 0 | D16: =COUNTIFS($C$37:$C$78,$A16,$I$37:$I$78,"Level 2*") -> 0 | E16: =COUNTIFS($C$37:$C$78,$A16,$I$37:$I$78,"Level 3*") -> 4 | F16: Covers: Policy and Procedures, Literacy Training and Awareness, Role-based Training, Training Records.
A17: Audit and Accountability (AU) | B17: =COUNTIF($C$37:$C$78,$A17) -> 2 | C17: =COUNTIFS($C$37:$C$78,$A17,$I$37:$I$78,"Level 1*") -> 0 | D17: =COUNTIFS($C$37:$C$78,$A17,$I$37:$I$78,"Level 2*") -> 1 | E17: =COUNTIFS($C$37:$C$78,$A17,$I$37:$I$78,"Level 3*") -> 1 | F17: Covers: Policy and Procedures, Audit Record Review, Analysis, and Reporting.
A18: Assessment, Authorization, and Monitoring (CA) | B18: =COUNTIF($C$37:$C$78,$A18) -> 4 | C18: =COUNTIFS($C$37:$C$78,$A18,$I$37:$I$78,"Level 1*") -> 0 | D18: =COUNTIFS($C$37:$C$78,$A18,$I$37:$I$78,"Level 2*") -> 0 | E18: =COUNTIFS($C$37:$C$78,$A18,$I$37:$I$78,"Level 3*") -> 4 | F18: Covers: Policy and Procedures, Control Assessments, Plan of Action and Milestones, Penetration Testing.
A19: Configuration Management (CM) | B19: =COUNTIF($C$37:$C$78,$A19) -> 1 | C19: =COUNTIFS($C$37:$C$78,$A19,$I$37:$I$78,"Level 1*") -> 0 | D19: =COUNTIFS($C$37:$C$78,$A19,$I$37:$I$78,"Level 2*") -> 0 | E19: =COUNTIFS($C$37:$C$78,$A19,$I$37:$I$78,"Level 3*") -> 1 | F19: Covers: Policy and Procedures.
A20: Contingency Planning (CP) | B20: =COUNTIF($C$37:$C$78,$A20) -> 1 | C20: =COUNTIFS($C$37:$C$78,$A20,$I$37:$I$78,"Level 1*") -> 0 | D20: =COUNTIFS($C$37:$C$78,$A20,$I$37:$I$78,"Level 2*") -> 0 | E20: =COUNTIFS($C$37:$C$78,$A20,$I$37:$I$78,"Level 3*") -> 1 | F20: Covers: Policy and Procedures.
A21: Identification and Authentication (IA) | B21: =COUNTIF($C$37:$C$78,$A21) -> 1 | C21: =COUNTIFS($C$37:$C$78,$A21,$I$37:$I$78,"Level 1*") -> 0 | D21: =COUNTIFS($C$37:$C$78,$A21,$I$37:$I$78,"Level 2*") -> 0 | E21: =COUNTIFS($C$37:$C$78,$A21,$I$37:$I$78,"Level 3*") -> 1 | F21: Covers: Policy and Procedures.
A22: Incident Response (IR) | B22: =COUNTIF($C$37:$C$78,$A22) -> 6 | C22: =COUNTIFS($C$37:$C$78,$A22,$I$37:$I$78,"Level 1*") -> 0 | D22: =COUNTIFS($C$37:$C$78,$A22,$I$37:$I$78,"Level 2*") -> 1 | E22: =COUNTIFS($C$37:$C$78,$A22,$I$37:$I$78,"Level 3*") -> 5 | F22: Covers: Policy and Procedures, Incident Response Training, Incident Response Testing, Incident Handling, Incident Reporting, Incident Response Plan.
A23: Maintenance (MA) | B23: =COUNTIF($C$37:$C$78,$A23) -> 1 | C23: =COUNTIFS($C$37:$C$78,$A23,$I$37:$I$78,"Level 1*") -> 0 | D23: =COUNTIFS($C$37:$C$78,$A23,$I$37:$I$78,"Level 2*") -> 0 | E23: =COUNTIFS($C$37:$C$78,$A23,$I$37:$I$78,"Level 3*") -> 1 | F23: Covers: Policy and Procedures.
A24: Physical and Environmental Protection (PE) | B24: =COUNTIF($C$37:$C$78,$A24) -> 1 | C24: =COUNTIFS($C$37:$C$78,$A24,$I$37:$I$78,"Level 1*") -> 0 | D24: =COUNTIFS($C$37:$C$78,$A24,$I$37:$I$78,"Level 2*") -> 0 | E24: =COUNTIFS($C$37:$C$78,$A24,$I$37:$I$78,"Level 3*") -> 1 | F24: Covers: Policy and Procedures.
A25: Planning (PL) | B25: =COUNTIF($C$37:$C$78,$A25) -> 3 | C25: =COUNTIFS($C$37:$C$78,$A25,$I$37:$I$78,"Level 1*") -> 0 | D25: =COUNTIFS($C$37:$C$78,$A25,$I$37:$I$78,"Level 2*") -> 0 | E25: =COUNTIFS($C$37:$C$78,$A25,$I$37:$I$78,"Level 3*") -> 3 | F25: Covers: Policy and Procedures, System Security and Privacy Plans, Rules of Behavior.
A26: Program Management (PM) | B26: =COUNTIF($C$37:$C$78,$A26) -> 3 | C26: =COUNTIFS($C$37:$C$78,$A26,$I$37:$I$78,"Level 1*") -> 0 | D26: =COUNTIFS($C$37:$C$78,$A26,$I$37:$I$78,"Level 2*") -> 0 | E26: =COUNTIFS($C$37:$C$78,$A26,$I$37:$I$78,"Level 3*") -> 3 | F26: Covers: Information Security Program Plan, System Inventory, Risk Management Strategy.
... A33: Supply Chain Risk Management (SR) | B33: =COUNTIF($C$37:$C$78,$A33) -> 1 | C33: =COUNTIFS($C$37:$C$78,$A33,$I$37:$I$78,"Level 1*") -> 0 | D33: =COUNTIFS($C$37:$C$78,$A33,$I$37:$I$78,"Level 2*") -> 0 | E33: =COUNTIFS($C$37:$C$78,$A33,$I$37:$I$78,"Level 3*") -> 1 | F33: Covers: Policy and Procedures.
A34: Total | B34: =SUM(B15:B33) -> 42 | C34: =SUM(C15:C33) -> 0 | D34: =SUM(D15:D33) -> 3 | E34: =SUM(E15:E33) -> 39
A36: Control ID New | B36: Control ID | C36: Control Family | D36: Control Name | E36: Action Type | F36: Baseline Setting to Configure | G36: Implementation Example | H36: Verification / Evidence | I36: Level | J36: CSF 2.0 Subcategory ID
A37: ESBIT-AC-01 | B37: AC-01 | C37: Access Control (AC) | D37: Policy and Procedures | E37: Implement | F37: Publish an approved access control policy and procedures with owner, scope and review cycle; review at least annually | G37: Policy in the GRC tool or document repository mapped to access control standards | H37: Signed policy with version and review date | I37: Level 3 - Low | J37: GV.PO-01
A38: ESBIT-AT-01 | B38: AT-01 | C38: Awareness and Training (AT) | D38: Policy and Procedures | E38: Implement | F38: Publish an approved awareness and training policy and procedures with owner, scope and review cycle; review at least annually | G38: Policy in the GRC tool or document repository mapped to training standards | H38: Signed policy with version and review date | I38: Level 3 - Low | J38: GV.PO-01
A39: ESBIT-AT-02 | B39: AT-02 | C39: Awareness and Training (AT) | D39: Literacy Training and Awareness | E39: Implement | F39: Provide security awareness training to all users at onboarding and at least annually, with phishing exercises | G39: LMS course, phishing simulation platform | H39: Completion report and simulation results | I39: Level 3 - Low | J39: PR.AT-01
A40: ESBIT-AT-03 | B40: AT-03 | C40: Awareness and Training (AT) | D40: Role-based Training | E40: Implement | F40: Provide role-based security training to administrators, developers and other privileged roles | G40: Role-specific courses, secure coding and admin hardening training | H40: Role-based completion records | I40: Level 3 - Low | J40: PR.AT-02
A41: ESBIT-AT-04 | B41: AT-04 | C41: Awareness and Training (AT) | D41: Training Records | E41: Implement | F41: Keep training records for each person for the defined period | G41: LMS records retention | H41: Training record export | I41: Level 3 - Low | J41: PR.AT-01
A42: ESBIT-AU-01 | B42: AU-01 | C42: Audit and Accountability (AU) | D42: Policy and Procedures | E42: Implement | F42: Publish an approved audit and accountability policy and procedures with owner, scope and review cycle; review at least annually | G42: Policy in the GRC tool or document repository mapped to audit and logging standards | H42: Signed policy with version and review date | I42: Level 3 - Low | J42: GV.PO-01
A43: ESBIT-AU-06 | B43: AU-06 | C43: Audit and Accountability (AU) | D43: Audit Record Review, Analysis, and Reporting | E43: Implement | F43: Review and analyze audit records at a defined frequency and report findings to management | G43: Weekly log review, SIEM report to management | H43: Review minutes and reports | I43: Level 2 - Medium | J43: DE.AE-02
A44: ESBIT-CA-01 | B44: CA-01 | C44: Assessment, Authorization, and Monitoring (CA) | D44: Policy and Procedures | E44: Implement | F44: Publish an approved assessment, authorization and monitoring policy and procedures with owner, scope and review cycle; review at least annually | G44: Policy in the GRC tool or document repository mapped to assessment and monitoring standards | H44: Signed policy with version and review date | I44: Level 3 - Low | J44: GV.PO-01
A45: ESBIT-CA-02 | B45: CA-02 | C45: Assessment, Authorization, and Monitoring (CA) | D45: Control Assessments | E45: Implement | F45: Assess security controls at least annually and after major change, using independent assessors for critical systems | G45: Internal audit and external assessments | H45: Assessment report with findings | I45: Level 3 - Low | J45: ID.IM-01
A46: ESBIT-CA-05 | B46: CA-05 | C46: Assessment, Authorization, and Monitoring (CA) | D46: Plan of Action and Milestones | E46: Implement | F46: Track remediation of findings in a plan of action with owner, due date and status | G46: Risk register and ticket tracking | H46: POA&M with status | I46: Level 3 - Low | J46: ID.RA-06
A47: ESBIT-CA-08 | B47: CA-08 | C47: Assessment, Authorization, and Monitoring (CA) | D47: Penetration Testing | E47: Implement | F47: Perform penetration testing on a schedule and after major change within an approved scope | G47: Annual external and internal pen test | H47: Pen test report and retest | I47: Level 3 - Low | J47: ID.RA-01
... A78: ESBIT-SR-01 | B78: SR-01 | C78: Supply Chain Risk Management (SR) | D78: Policy and Procedures | E78: Implement | F78: Publish an approved supply chain risk management policy and procedures with owner, scope and review cycle; review at least annually | G78: Policy in the GRC tool or document repository mapped to supply chain standards | H78: Signed policy with version and review date | I78: Level 3 - Low | J78: GV.PO-01

Sheet Physical Config Baseline
A1: Physical and Environmental Configuration Baseline (NIST SP 800-53 Rev. 5 - core control items)
A2: Purpose: this sheet lists the physical, environmental, media and maintenance controls of NIST SP 800-53 Rev. 5 that protect facilities, data centers and hardware. Most items are facility settings and procedures, so Action Type mostly means Implement or Configure on facility systems.
A3: Scope: only rows tagged Physical in the Config Baseline sheet are considered, limited to the 4 families MA, MP, PE, SR. Classified-information, citizenship and foreign-national enhancements are not applicable and are left out.
A4: Selection principle: controls with a similar effect were consolidated so that only the main baseline items remain. Only rows tagged for this domain in the Config Baseline sheet were considered; base controls and the enhancements that add a distinct setting are kept.
A5: Examples name facility systems (badge readers, CCTV, UPS, gas suppression) as guidance only; adapt to the sites in use. Level is taken from the Config Baseline sheet (Level 1 = mandatory, Level 3 = lowest impact).
A7: Action Type legend
A8: Configure = set a parameter, policy or rule on an existing platform/service.
A9: Implement = build or deploy a mechanism, template, automation or architecture pattern.
A10: Install = install or onboard a tool, agent or scanner.
A11: Enable = turn on a feature, log source or detection service that is off by default.
A13: Coverage by control family
A14: Family | B14: Items | C14: Level 1 | D14: Level 2 | E14: Level 3 | F14: Configuration focus
A15: Maintenance (MA) | B15: =COUNTIF($C$22:$C$47,$A15) -> 6 | C15: =COUNTIFS($C$22:$C$47,$A15,$I$22:$I$47,"Level 1*") -> 3 | D15: =COUNTIFS($C$22:$C$47,$A15,$I$22:$I$47,"Level 2*") -> 1 | E15: =COUNTIFS($C$22:$C$47,$A15,$I$22:$I$47,"Level 3*") -> 2 | F15: Covers: Controlled Maintenance, Nonlocal Maintenance, Maintenance Personnel.
A16: Media Protection (MP) | B16: =COUNTIF($C$22:$C$47,$A16) -> 6 | C16: =COUNTIFS($C$22:$C$47,$A16,$I$22:$I$47,"Level 1*") -> 0 | D16: =COUNTIFS($C$22:$C$47,$A16,$I$22:$I$47,"Level 2*") -> 6 | E16: =COUNTIFS($C$22:$C$47,$A16,$I$22:$I$47,"Level 3*") -> 0 | F16: Covers: Media Access, Media Storage, Media Transport, Media Sanitization, Media Use.
A17: Physical and Environmental Protection (PE) | B17: =COUNTIF($C$22:$C$47,$A17) -> 12 | C17: =COUNTIFS($C$22:$C$47,$A17,$I$22:$I$47,"Level 1*") -> 0 | D17: =COUNTIFS($C$22:$C$47,$A17,$I$22:$I$47,"Level 2*") -> 0 | E17: =COUNTIFS($C$22:$C$47,$A17,$I$22:$I$47,"Level 3*") -> 12 | F17: Covers: Physical Access Authorizations, Physical Access Control, Monitoring Physical Access, Visitor Access Records, Power Equipment and Cabling, Emergency Shutoff, Emergency Power, and related items.
A18: Supply Chain Risk Management (SR) | B18: =COUNTIF($C$22:$C$47,$A18) -> 2 | C18: =COUNTIFS($C$22:$C$47,$A18,$I$22:$I$47,"Level 1*") -> 0 | D18: =COUNTIFS($C$22:$C$47,$A18,$I$22:$I$47,"Level 2*") -> 0 | E18: =COUNTIFS($C$22:$C$47,$A18,$I$22:$I$47,"Level 3*") -> 2 | F18: Covers: Tamper Resistance and Detection, Component Disposal.
A19: Total | B19: =SUM(B15:B18) -> 26 | C19: =SUM(C15:C18) -> 3 | D19: =SUM(D15:D18) -> 7 | E19: =SUM(E15:E18) -> 16
A21: Control ID New | B21: Control ID | C21: Control Family | D21: Control Name | E21: Action Type | F21: Baseline Setting to Configure | G21: Implementation Example | H21: Verification / Evidence | I21: Level | J21: CSF 2.0 Subcategory ID
A22: ESBIT-MA-02 | B22: MA-02 | C22: Maintenance (MA) | D22: Controlled Maintenance | E22: Implement | F22: Approve, schedule and record all maintenance on hardware and facilities; sanitize equipment before it leaves | G22: Maintenance ticket with approval, maintenance log, sanitization checklist | H22: Maintenance records | I22: Level 3 - Low | J22: PR.PS-03
A23: ESBIT-MA-04 | B23: MA-04 | C23: Maintenance (MA) | D23: Nonlocal Maintenance | E23: Configure | F23: Allow remote (non-local) maintenance only with approval, strong authentication and session control | G23: Vendor VPN with MFA, jump host, time-boxed access | H23: Remote maintenance approvals and logs | I23: Level 1 - High | J23: PR.AA-05
A24: ESBIT-MA-04(01) | B24: MA-04(01) | C24: Maintenance (MA) | D24: Nonlocal Maintenance | Logging and Review | E24: Enable | F24: Log and review all remote maintenance sessions | G24: Session recording on jump host, log review | H24: Session logs and review record | I24: Level 1 - High | J24: PR.AA-05
A25: ESBIT-MA-04(04) | B25: MA-04(04) | C25: Maintenance (MA) | D25: Nonlocal Maintenance | Authentication and Separation of Maintenance Sessions | E25: Configure | F25: Separate remote maintenance sessions from other network sessions and terminate at session end | G25: Dedicated maintenance network or VLAN, session timeout | H25: Network separation and session end proof | I25: Level 2 - Medium | J25: PR.AA-05
A26: ESBIT-MA-04(06) | B26: MA-04(06) | C26: Maintenance (MA) | D26: Nonlocal Maintenance | Cryptographic Protection | E26: Configure | F26: Encrypt remote maintenance sessions | G26: IPsec or TLS VPN, SSH, TLS remote tools | H26: Protocol and cipher check | I26: Level 1 - High | J26: PR.AA-05
A27: ESBIT-MA-05 | B27: MA-05 | C27: Maintenance (MA) | D27: Maintenance Personnel | E27: Implement | F27: Authorize maintenance personnel, keep a list and escort or supervise those without authorization | G27: Authorized maintainer list, visitor escort procedure | H27: Authorized list; escort logs | I27: Level 3 - Low | J27: PR.AA-05
A28: ESBIT-MP-02 | B28: MP-02 | C28: Media Protection (MP) | D28: Media Access | E28: Configure | F28: Restrict access to digital and non-digital media to authorized people | G28: Locked media cabinets, access list, USB control | H28: Media access list | I28: Level 2 - Medium | J28: PR.DS-01
A29: ESBIT-MP-04 | B29: MP-04 | C29: Media Protection (MP) | D29: Media Storage | E29: Configure | F29: Store media securely according to classification and control access | G29: Safe or locked storage, media register, encrypted removable media | H29: Storage inspection record | I29: Level 2 - Medium | J29: PR.DS-01
A30: ESBIT-MP-05 | B30: MP-05 | C30: Media Protection (MP) | D30: Media Transport | E30: Implement | F30: Protect and control media during transport outside controlled areas and record custody | G30: Tamper-evident packaging, courier with tracking, chain-of-custody log | H30: Transport logs | I30: Level 2 - Medium | J30: PR.DS-02
A31: ESBIT-MP-05(04) | B31: MP-05(04) | C31: Media Protection (MP) | D31: Media Transport | Cryptographic Protection | E31: Configure | F31: Encrypt media that leaves controlled areas | G31: Encrypted drives and tapes, BitLocker To Go, LTO encryption | H31: Encryption status for removable media | I31: Level 2 - Medium | J31: PR.DS-02
A32: ESBIT-MP-06 | B32: MP-06 | C32: Media Protection (MP) | D32: Media Sanitization | E32: Implement | F32: Sanitize or destroy media before disposal, reuse or release using an approved method and record it | G32: NIST SP 800-88 wipe, degauss, shredding with certificate of destruction | H32: Sanitization certificates and log | I32: Level 2 - Medium | J32: PR.PS-03
... A47: ESBIT-SR-12 | B47: SR-12 | C47: Supply Chain Risk Management (SR) | D47: Component Disposal | E47: Implement | F47: Dispose of system components and media securely and record the disposal | G47: Certified disposal vendor, sanitization before disposal, asset register update | H47: Disposal certificates | I47: Level 3 - Low | J47: PR.PS-03

Sheet Third Party Config Baseline
A1: Third Party Configuration Baseline (NIST SP 800-53 Rev. 5 - core control items)
A2: Purpose: this sheet lists the external service provider and supply chain controls of NIST SP 800-53 Rev. 5 that define how suppliers, outsourced services and components are selected, contracted, assessed and monitored. They are contract and process controls with a few technical settings (location, keys, integrity).
A3: Scope: only rows tagged Third Party in the Config Baseline sheet are considered, limited to the 2 families SA, SR. Sub-items on diverse supply base, pedigree and sub-tier detail are consolidated into the main SR items.
A4: Selection principle: controls with a similar effect were consolidated so that only the main baseline items remain. Only rows tagged for this domain in the Config Baseline sheet were considered; base controls and the enhancements that add a distinct setting are kept.
A5: Examples name artefacts (contract schedule, SOC 2 review, SBOM, supplier questionnaire) as guidance only; adapt to the organization. Level is taken from the Config Baseline sheet (Level 1 = mandatory, Level 3 = lowest impact).
A7: Action Type legend
A8: Configure = set a parameter, policy or rule on an existing platform/service.
A9: Implement = build or deploy a mechanism, template, automation or architecture pattern.
A10: Install = install or onboard a tool, agent or scanner.
A11: Enable = turn on a feature, log source or detection service that is off by default.
A13: Coverage by control family
A14: Family | B14: Items | C14: Level 1 | D14: Level 2 | E14: Level 3 | F14: Configuration focus
A15: System and Services Acquisition (SA) | B15: =COUNTIF($C$20:$C$33,$A15) -> 6 | C15: =COUNTIFS($C$20:$C$33,$A15,$I$20:$I$33,"Level 1*") -> 0 | D15: =COUNTIFS($C$20:$C$33,$A15,$I$20:$I$33,"Level 2*") -> 3 | E15: =COUNTIFS($C$20:$C$33,$A15,$I$20:$I$33,"Level 3*") -> 3 | F15: Covers: External System Services.
A16: Supply Chain Risk Management (SR) | B16: =COUNTIF($C$20:$C$33,$A16) -> 8 | C16: =COUNTIFS($C$20:$C$33,$A16,$I$20:$I$33,"Level 1*") -> 0 | D16: =COUNTIFS($C$20:$C$33,$A16,$I$20:$I$33,"Level 2*") -> 0 | E16: =COUNTIFS($C$20:$C$33,$A16,$I$20:$I$33,"Level 3*") -> 8 | F16: Covers: Supply Chain Risk Management Plan, Supply Chain Controls and Processes, Provenance, Acquisition Strategies, Tools, and Methods, Supplier Assessments and Reviews, Notification Agreements, Inspection of Systems or Components, and related items.
A17: Total | B17: =SUM(B15:B16) -> 14 | C17: =SUM(C15:C16) -> 0 | D17: =SUM(D15:D16) -> 3 | E17: =SUM(E15:E16) -> 11
A19: Control ID New | B19: Control ID | C19: Control Family | D19: Control Name | E19: Action Type | F19: Baseline Setting to Configure | G19: Implementation Example | H19: Verification / Evidence | I19: Level | J19: CSF 2.0 Subcategory ID
A20: ESBIT-SA-09 | B20: SA-09 | C20: System and Services Acquisition (SA) | D20: External System Services | E20: Configure | F20: Require external service providers to meet defined security requirements and define user and provider responsibilities in contracts | G20: Shared-responsibility matrix, security schedule, SLA | H20: Signed contract with security schedule | I20: Level 2 - Medium | J20: GV.SC-07
A21: ESBIT-SA-09(01) | B21: SA-09(01) | C21: System and Services Acquisition (SA) | D21: External System Services | Risk Assessments and Organizational Approvals | E21: Implement | F21: Assess risk before engaging an external provider and get organizational approval | G21: Vendor risk assessment and approval workflow | H21: Completed assessments on file | I21: Level 3 - Low | J21: GV.SC-07
A22: ESBIT-SA-09(02) | B22: SA-09(02) | C22: System and Services Acquisition (SA) | D22: External System Services | Identification of Functions, Ports, Protocols, and Services | E22: Implement | F22: Identify the functions, ports, protocols and services the provider may use and restrict to those | G22: Approved connectivity list for each provider, firewall rules | H22: Provider service and port register | I22: Level 3 - Low | J22: GV.SC-07
A23: ESBIT-SA-09(05) | B23: SA-09(05) | C23: System and Services Acquisition (SA) | D23: External System Services | Processing, Storage, and Service Location | E23: Configure | F23: Restrict the location where provider processes, stores and delivers service data | G23: Data residency clauses, region-locked services | H23: Contract clause and region setting | I23: Level 3 - Low | J23: GV.SC-07
